Workbook

Sheet Sheet6
A1: Census Tract | B1: tract | C1: Town | D1: Distressed Tract1 | E1: CLM $ Collected | F1: % of Total CLM $ Collected | G1: Incentive Disbursements | H1: % of Total Incentive Disbursements | I1: Column1 | J1: Equitable | K1: Residential CLM $ Collected | L1: % of Total Residential CLM $ Collected | M1: Residential Incentive Disbursements | N1: % of Total Residential Incentive Disbursements | O1: Equitable 2 | P1: C&I CLM $ Collected | Q1: % of Total C&I CLM $ Collected | R1: C&I Incentive Disbursements | S1: % of TotalC&I Incentive Disbursements | T1: Equitable 3 | U1: diversity index table.adjusted income (thousands of $) | V1: diversity index table.median census housing cost | W1: diversity index table.Combined affluence rank | X1: diversity index table.rural rank | Y1: diversity index table.racial diversity index | Z1: diversity index table.composit index | AA1: diversity index table.rounded composite
A2: 9001070200 | B2: 9001070200 | C2: BRIDGEPORT | D2: No | E2: 0 | F2: 0 | G2: 8670.73 | H2: 0.00051608453 | I2: YES | J2: N/A | K2: 0 | L2: 0 | M2: 2227.93 | N2: 0.00051608453 | O2: N/A | P2: 0 | Q2: 0 | R2: 6442.8 | S2: 0.00051608453 | T2: N/A | U2: 27.729 | V2: 1292 | W2: 5 | X2: 1 | Y2: 4 | Z2: 4.5 | AA2: 5
A3: 9001070200 | B3: 9001070200 | C3: Bridgeport | D3: Yes | E3: 67503.345 | F3: 0.0023196537 | G3: 0 | H3: 0 | I3: N/A | J3: NO | K3: 45704.852 | L3: 0.0023196537 | M3: 0 | N3: 0 | O3: NO | P3: 21798.492 | Q3: 0.0023196537 | R3: 0 | S3: 0 | T3: NO | U3: 27.729 | V3: 1292 | W3: 5 | X3: 1 | Y3: 4 | Z3: 4.5 | AA3: 5
A4: 9001070200 | B4: 9001070200 | C4: TRUMBULL | D4: No | E4: 0 | F4: 0 | G4: 749.66 | H4: 4.4619995e-05 | I4: YES | J4: N/A | K4: 0 | L4: 0 | M4: 749.66 | N4: 4.4619995e-05 | O4: N/A | P4: 0 | Q4: 0 | R4: 0 | S4: 4.4619995e-05 | T4: N/A | U4: 27.729 | V4: 1292 | W4: 5 | X4: 1 | Y4: 4 | Z4: 4.5 | AA4: 5
A5: 9001070300 | B5: 9001070300 | C5: BRIDGEPORT | D5: No | E5: 0 | F5: 0 | G5: 213519.3 | H5: 0.012708735 | I5: YES | J5: N/A | K5: 0 | L5: 0 | M5: 202635.3 | N5: 0.012708735 | O5: N/A | P5: 0 | Q5: 0 | R5: 10884 | S5: 0.012708735 | T5: N/A | U5: 5.532 | V5: 433 | W5: 5 | X5: 1 | Y5: 4 | Z5: 4.5 | AA5: 5
A6: 9001070300 | B6: 9001070300 | C6: Bridgeport | D6: Yes | E6: 52641.309 | F6: 0.0018089416 | G6: 0 | H6: 0 | I6: N/A | J6: NO | K6: 16956.724 | L6: 0.0018089416 | M6: 0 | N6: 0 | O6: NO | P6: 35684.585 | Q6: 0.0018089416 | R6: 0 | S6: 0 | T6: NO | U6: 5.532 | V6: 433 | W6: 5 | X6: 1 | Y6: 4 | Z6: 4.5 | AA6: 5
A7: 9001071100 | B7: 9001071100 | C7: Bridgeport | D7: No | E7: 66899.111 | F7: 0.0022988901 | G7: 29836.83 | H7: 0.0017758973 | I7: NO | J7: NO | K7: 51783.79 | L7: 0.0022988901 | M7: 21423.83 | N7: 0.0017758973 | O7: NO | P7: 15115.321 | Q7: 0.0022988901 | R7: 8413 | S7: 0.0017758973 | T7: NO | U7: 25.633 | V7: 1271 | W7: 5 | X7: 1 | Y7: 5 | Z7: 5 | AA7: 5
A8: 9001071200 | B8: 9001071200 | C8: BRIDGEPORT | D8: No | E8: 0 | F8: 0 | G8: 20104.86 | H8: 0.0011966475 | I8: YES | J8: N/A | K8: 0 | L8: 0 | M8: 4593.86 | N8: 0.0011966475 | O8: N/A | P8: 0 | Q8: 0 | R8: 15511 | S8: 0.0011966475 | T8: N/A | U8: 13.99 | V8: 1107 | W8: 5 | X8: 1 | Y8: 5 | Z8: 5 | AA8: 5
A9: 9001071200 | B9: 9001071200 | C9: Bridgeport | D9: Yes | E9: 65667.876 | F9: 0.0022565805 | G9: 0 | H9: 0 | I9: N/A | J9: NO | K9: 45169.658 | L9: 0.0022565805 | M9: 0 | N9: 0 | O9: NO | P9: 20498.218 | Q9: 0.0022565805 | R9: 0 | S9: 0 | T9: NO | U9: 13.99 | V9: 1107 | W9: 5 | X9: 1 | Y9: 5 | Z9: 5 | AA9: 5
A10: 9001071300 | B10: 9001071300 | C10: BRIDGEPORT | D10: No | E10: 0 | F10: 0 | G10: 2772.32 | H10: 0.00016500934 | I10: YES | J10: N/A | K10: 0 | L10: 0 | M10: 1572.32 | N10: 0.00016500934 | O10: N/A | P10: 0 | Q10: 0 | R10: 1200 | S10: 0.00016500934 | T10: N/A | U10: 17.511 | V10: 1078 | W10: 5 | X10: 1 | Y10: 5 | Z10: 5 | AA10: 5
A11: 9001071300 | B11: 9001071300 | C11: Bridgeport | D11: Yes | E11: 54252.862 | F11: 0.0018643203 | G11: 0 | H11: 0 | I11: N/A | J11: NO | K11: 34389.421 | L11: 0.0018643203 | M11: 0 | N11: 0 | O11: NO | P11: 19863.441 | Q11: 0.0018643203 | R11: 0 | S11: 0 | T11: NO | U11: 17.511 | V11: 1078 | W11: 5 | X11: 1 | Y11: 5 | Z11: 5 | AA11: 5
A12: 9001071400 | B12: 9001071400 | C12: Bridgeport | D12: No | E12: 68350.447 | F12: 0.0023487632 | G12: 10239.37 | H12: 0.00060945047 | I12: NO | J12: NO | K12: 38432.276 | L12: 0.0023487632 | M12: 3327.16 | N12: 0.00060945047 | O12: NO | P12: 29918.171 | Q12: 0.0023487632 | R12: 6912.21 | S12: 0.00060945047 | T12: NO | U12: 22.64 | V12: 1131 | W12: 5 | X12: 1 | Y12: 5 | Z12: 5 | AA12: 5
A13: 9001071900 | B13: 9001071900 | C13: ANSONIA | D13: No | E13: 0 | F13: 0 | G13: 230 | H13: 1.3689671e-05 | I13: YES | J13: N/A | K13: 0 | L13: 0 | M13: 230 | N13: 1.3689671e-05 | O13: N/A | P13: 0 | Q13: 0 | R13: 0 | S13: 1.3689671e-05 | T13: N/A | U13: 26.15 | V13: 1287 | W13: 5 | X13: 1 | Y13: 5 | Z13: 5 | AA13: 5
... A117: 9009361402 | B117: 9009361402 | C117: New Haven | D117: Yes | E117: 40495.789 | F117: 0.0013915786 | G117: 0 | H117: 0 | I117: N/A | J117: NO | K117: 4781.3609 | L117: 0.0013915786 | M117: 0 | N117: 0 | O117: NO | P117: 35714.428 | Q117: 0.0013915786 | R117: 0 | S117: 0 | T117: NO | U117: 35.178 | V117: 1510 | W117: 4 | X117: 1 | Y117: 5 | Z117: 4.5 | AA117: 5
E120: =SUM(Merge5[CLM $ Collected ]) -> 3329185.9
F124: =E120+Sheet8!D64 -> 5940952.7

Sheet small load equity calcs
A1: Census Tract | B1: tract | C1: Town | D1: Distressed Tract1 | E1: CLM $ Collected | F1: % of Total CLM $ Collected | G1: Incentive Disbursements | H1: % of Total Incentive Disbursements | I1: Column1 | J1: Equitable | K1: Residential CLM $ Collected | L1: % of Total Residential CLM $ Collected | M1: Residential Incentive Disbursements | N1: % of Total Residential Incentive Disbursements | O1: Equitable 2 | P1: C&I CLM $ Collected | Q1: % of Total C&I CLM $ Collected | R1: C&I Incentive Disbursements | S1: % of TotalC&I Incentive Disbursements | T1: Equitable 3 | U1: diversity index table.adjusted income (thousands of $) | V1: diversity index table.median census housing cost | W1: diversity index table.Combined affluence rank | X1: diversity index table.rural rank | Y1: diversity index table.racial diversity index | Z1: diversity index table.composit index | AA1: diversity index table.rounded composite
A2: 9001055100 | B2: 9001055100 | C2: Easton | D2: No | E2: 394.428 | F2: 1.3553941e-05 | G2: 0 | H2: 0 | I2: N/A | J2: NO | K2: 394.428 | L2: 1.3553941e-05 | M2: 0 | N2: 0 | O2: NO | P2: 0 | Q2: 1.3553941e-05 | R2: 0 | S2: 0 | T2: NO | U2: 118.302 | V2: 4000 | W2: 1 | X2: 1 | Y2: 4 | Z2: 2.5 | AA2: 3
A3: 9001055200 | B3: 9001055200 | C3: Easton | D3: No | E3: 887.5106 | F3: 3.0498004e-05 | G3: 0 | H3: 0 | I3: N/A | J3: NO | K3: 887.5106 | L3: 3.0498004e-05 | M3: 0 | N3: 0 | O3: NO | P3: 0 | Q3: 3.0498004e-05 | R3: 0 | S3: 0 | T3: NO | U3: 141.638 | V3: 3750 | W3: 1 | X3: 1 | Y3: 1 | Z3: 1 | AA3: 1 | AC3: Row Labels | AD3: Sum of CLM $ Collected | AE3: Sum of Incentive Disbursements | AF3: Sum of Residential CLM $ Collected | AG3: Sum of Residential Incentive Disbursements | AH3: Sum of C&I CLM $ Collected | AI3: Sum of C&I Incentive Disbursements | AJ3: Composite Index
A4: 9001060100 | B4: 9001060100 | C4: Bridgeport | D4: No | E4: 0.9029 | F4: 3.1026838e-08 | G4: 0 | H4: 0 | I4: N/A | J4: N/A | K4: 0 | L4: 3.1026838e-08 | M4: 0 | N4: 0 | O4: N/A | P4: 0.9029 | Q4: 3.1026838e-08 | R4: 0 | S4: 0 | T4: N/A | U4: 85.387 | V4: 2313 | W4: 1 | X4: 1 | Y4: 2 | Z4: 1.5 | AA4: 2 | AC4: 1 | AD4: 1535395.4 | AE4: 489966.54 | AF4: 1233439.3 | AG4: 355917.5 | AH4: 301956.11 | AI4: 134049.04
A5: 9001060100 | B5: 9001060100 | C5: Fairfield | D5: No | E5: 71392.777 | F5: 0.0024533084 | G5: 20104.8 | H5: 0.0011966439 | I5: NO | J5: NO | K5: 58128.328 | L5: 0.0024533084 | M5: 19857.8 | N5: 0.0011966439 | O5: NO | P5: 13264.449 | Q5: 0.0024533084 | R5: 247 | S5: 0.0011966439 | T5: NO | U5: 85.387 | V5: 2313 | W5: 1 | X5: 1 | Y5: 2 | Z5: 1.5 | AA5: 2 | AC5: 2 | AD5: 2438778.6 | AE5: 840590.69 | AF5: 1849524.4 | AG5: 641461.43 | AH5: 589254.16 | AI5: 199129.26 | AK5: Row Labels | AL5: Sum of CLM $ Collected | AM5: Sum of Incentive Disbursements | AN5: Sum of Residential CLM $ Collected | AO5: Sum of Residential Incentive Disbursements | AP5: Sum of C&I CLM $ Collected | AQ5: Sum of C&I Incentive Disbursements
A6: 9001060100 | B6: 9001060100 | C6: Trumbull | D6: No | E6: 106.0054 | F6: 3.6427206e-06 | G6: 0 | H6: 0 | I6: N/A | J6: N/A | K6: 0 | L6: 3.6427206e-06 | M6: 0 | N6: 0 | O6: N/A | P6: 106.0054 | Q6: 3.6427206e-06 | R6: 0 | S6: 0 | T6: N/A | U6: 85.387 | V6: 2313 | W6: 1 | X6: 1 | Y6: 2 | Z6: 1.5 | AA6: 2 | AC6: 3 | AD6: 4435476.1 | AE6: 1795986.2 | AF6: 3153797.1 | AG6: 1288734.7 | AH6: 1281679 | AI6: 507251.52 | AK6: 1 | AL6: 875724.39 | AM6: 163490.93 | AN6: 721825.63 | AO6: 144167.93 | AP6: 153898.77 | AQ6: 19323
A7: 9001060200 | B7: 9001060200 | C7: Fairfield | D7: No | E7: 96972.012 | F7: 0.0033323014 | G7: 31534.58 | H7: 0.001876948 | I7: NO | J7: NO | K7: 78630.955 | L7: 0.0033323014 | M7: 29656.58 | N7: 0.001876948 | O7: NO | P7: 18341.057 | Q7: 0.0033323014 | R7: 1878 | S7: 0.001876948 | T7: NO | U7: 75.665 | V7: 2452 | W7: 1 | X7: 1 | Y7: 3 | Z7: 2 | AA7: 2 | AC7: 4 | AD7: 4048969.2 | AE7: 2234279.7 | AF7: 2680511.7 | AG7: 1554367.5 | AH7: 1368457.5 | AI7: 679912.24 | AK7: 2 | AL7: 2632944.6 | AM7: 1054449.1 | AN7: 2127184.9 | AO7: 766959.85 | AP7: 505759.68 | AQ7: 287489.29
A8: 9001060300 | B8: 9001060300 | C8: Fairfield | D8: No | E8: 100651.49 | F8: 0.0034587413 | G8: 19540.71 | H8: 0.0011630691 | I8: NO | J8: NO | K8: 92872.917 | L8: 0.0034587413 | M8: 19540.71 | N8: 0.0011630691 | O8: NO | P8: 7778.5729 | Q8: 0.0034587413 | R8: 0 | S8: 0.0011630691 | T8: NO | U8: 114.261 | V8: 3341 | W8: 1 | X8: 1 | Y8: 2 | Z8: 1.5 | AA8: 2 | AC8: 5 | AD8: 5080239.7 | AE8: 2194563.5 | AF8: 3212520.4 | AG8: 1176273.2 | AH8: 1867719.3 | AI8: 1018290.3 | AK8: 3 | AL8: 4733189.1 | AM8: 1902360.5 | AN8: 3270324 | AO8: 1307531.1 | AP8: 1462865.1 | AQ8: 594829.38
A9: 9001060400 | B9: 9001060400 | C9: Fairfield | D9: No | E9: 167953.61 | F9: 0.0057714803 | G9: 16361.63 | H9: 0.00097384928 | I9: NO | J9: NO | K9: 158569.58 | L9: 0.0057714803 | M9: 16361.63 | N9: 0.00097384928 | O9: NO | P9: 9384.0322 | Q9: 0.0057714803 | R9: 0 | S9: 0.00097384928 | T9: NO | U9: 146.927 | V9: 3810 | W9: 1 | X9: 1 | Y9: 1 | Z9: 1 | AA9: 1 | AC9: Grand Total | AD9: 17538859 | AE9: 7555386.7 | AF9: 12129793 | AG9: 5016754.3 | AH9: 5409066.1 | AI9: 2538632.3 | AK9: 4 | AL9: 4235912 | AM9: 2387206.9 | AN9: 2789481.1 | AO9: 1387531.3 | AP9: 1446431 | AQ9: 999675.57
A10: 9001060500 | B10: 9001060500 | C10: Fairfield | D10: No | E10: 77707.49 | F10: 0.0026703043 | G10: 7351.8 | H10: 0.00043758141 | I10: NO | J10: NO | K10: 71345.134 | L10: 0.0026703043 | M10: 7351.8 | N10: 0.00043758141 | O10: NO | P10: 6362.3551 | Q10: 0.0026703043 | R10: 0 | S10: 0.00043758141 | T10: NO | U10: 121.599 | V10: 3418 | W10: 1 | X10: 1 | Y10: 1 | Z10: 1 | AA10: 1 | AK10: 5 | AL10: 5061088.8 | AM10: 2047879.2 | AN10: 3220977.3 | AO10: 1410564.1 | AP10: 1840111.5 | AQ10: 637315.1
A11: 9001060600 | B11: 9001060600 | C11: Fairfield | D11: No | E11: 122971.58 | F11: 0.0042257384 | G11: 95807 | H11: 0.0057024623 | I11: YES | J11: YES | K11: 73188.417 | L11: 0.0042257384 | M11: 6296 | N11: 0.0057024623 | O11: YES | P11: 49783.158 | Q11: 0.0042257384 | R11: 89511 | S11: 0.0057024623 | T11: YES | U11: 116.734 | V11: 2525 | W11: 1 | X11: 1 | Y11: 2 | Z11: 1.5 | AA11: 2 | AK11: Grand Total | AL11: 17538859 | AM11: 7555386.7 | AN11: 12129793 | AO11: 5016754.3 | AP11: 5409066.1 | AQ11: 2538632.3
A12: 9001060700 | B12: 9001060700 | C12: Fairfield | D12: No | E12: 117727.44 | F12: 0.0040455315 | G12: 8336.04 | H12: 0.00049616368 | I12: NO | J12: NO | K12: 98856.621 | L12: 0.0040455315 | M12: 8336.04 | N12: 0.00049616368 | O12: NO | P12: 18870.823 | Q12: 0.0040455315 | R12: 0 | S12: 0.00049616368 | T12: NO | U12: 104.15 | V12: 2864 | W12: 1 | X12: 1 | Y12: 2 | Z12: 1.5 | AA12: 2
A13: 9001060800 | B13: 9001060800 | C13: Fairfield | D13: No | E13: 41183.172 | F13: 0.0014151995 | G13: 4387.52 | H13: 0.00026114655 | I13: NO | J13: NO | K13: 39085.891 | L13: 0.0014151995 | M13: 4387.52 | N13: 0.00026114655 | O13: NO | P13: 2097.2804 | Q13: 0.0014151995 | R13: 0 | S13: 0.00026114655 | T13: NO | U13: 103.645 | V13: 3043 | W13: 1 | X13: 1 | Y13: 2 | Z13: 1.5 | AA13: 2 | AK13: Row Labels | AL13: Collections % | AM13: Collections Disbursement | AN13: RES collections | AO13: RES disbursements | AP13: C&I Collection | AQ13: C&I disburse
A14: 9001060900 | B14: 9001060900 | C14: Fairfield | D14: No | E14: 49269.364 | F14: 0.0016930697 | G14: 30036.3 | H14: 0.0017877699 | I14: YES | J14: YES | K14: 48889.4 | L14: 0.0016930697 | M14: 30036.3 | N14: 0.0017877699 | O14: YES | P14: 379.9641 | Q14: 0.0016930697 | R14: 0 | S14: 0.0017877699 | T14: YES | U14: 82.66 | V14: 2698 | W14: 1 | X14: 1 | Y14: 1 | Z14: 1 | AA14: 1 | AK14: 1 | AL14: =AL6/AL$11 -> 0.049930523 | AM14: =AM6/AM$11 -> 0.021638989 | AN14: =AN6/AN$11 -> 0.059508487 | AO14: =AO6/AO$11 -> 0.028737291 | AP14: =AP6/AP$11 -> 0.028452004 | AQ14: =AQ6/AQ$11 -> 0.0076115788
A15: 9001061000 | B15: 9001061000 | C15: Fairfield | D15: No | E15: 141435.5 | F15: 0.0048602243 | G15: 84443.99 | H15: 0.0050261324 | I15: YES | J15: YES | K15: 73580.641 | L15: 0.0048602243 | M15: 75486.32 | N15: 0.0050261324 | O15: YES | P15: 67854.863 | Q15: 0.0048602243 | R15: 8957.67 | S15: 0.0050261324 | T15: YES | U15: 49.471 | V15: 1741 | W15: 3 | X15: 1 | Y15: 3 | Z15: 3 | AA15: 3 | AK15: 2 | AL15: =AL7/AL$11 -> 0.15012063 | AM15: =AM7/AM$11 -> 0.13956256 | AN15: =AN7/AN$11 -> 0.17536861 | AO15: =AO7/AO$11 -> 0.15287969 | AP15: =AP7/AP$11 -> 0.093502219 | AQ15: =AQ7/AQ$11 -> 0.11324574
A16: 9001061100 | B16: 9001061100 | C16: Fairfield | D16: No | E16: 72876.103 | F16: 0.0025042807 | G16: 4473.07 | H16: 0.00026623851 | I16: NO | J16: NO | K16: 67549.059 | L16: 0.0025042807 | M16: 4173.07 | N16: 0.00026623851 | O16: NO | P16: 5327.0441 | Q16: 0.0025042807 | R16: 300 | S16: 0.00026623851 | T16: NO | U16: 94.519 | V16: 2692 | W16: 1 | X16: 1 | Y16: 1 | Z16: 1 | AA16: 1 | AK16: 3 | AL16: =AL8/AL$11 -> 0.2698687 | AM16: =AM8/AM$11 -> 0.25178863 | AN16: =AN8/AN$11 -> 0.26961087 | AO16: =AO8/AO$11 -> 0.26063287 | AP16: =AP8/AP$11 -> 0.2704469 | AQ16: =AQ8/AQ$11 -> 0.23431096
A17: 9001061200 | B17: 9001061200 | C17: Fairfield | D17: No | E17: 37465.91 | F17: 0.0012874612 | G17: 19703.03 | H17: 0.0011727304 | I17: YES | J17: NO | K17: 35405.152 | L17: 0.0012874612 | M17: 19213.03 | N17: 0.0011727304 | O17: NO | P17: 2060.7587 | Q17: 0.0012874612 | R17: 490 | S17: 0.0011727304 | T17: NO | U17: 48.123 | V17: 1853 | W17: 3 | X17: 1 | Y17: 5 | Z17: 4 | AA17: 4 | AK17: 4 | AL17: =AL9/AL$11 -> 0.24151583 | AM17: =AM9/AM$11 -> 0.31596092 | AN17: =AN9/AN$11 -> 0.22996939 | AO17: =AO9/AO$11 -> 0.27657949 | AP17: =AP9/AP$11 -> 0.26740863 | AQ17: =AQ9/AQ$11 -> 0.39378509
A18: 9001061300 | B18: 9001061300 | C18: Fairfield | D18: No | E18: 75361.948 | F18: 0.0025897032 | G18: 35125.23 | H18: 0.0020906646 | I18: NO | J18: NO | K18: 51750.384 | L18: 0.0025897032 | M18: 7224.19 | N18: 0.0020906646 | O18: NO | P18: 23611.565 | Q18: 0.0025897032 | R18: 27901.04 | S18: 0.0020906646 | T18: NO | U18: 54.923 | V18: 1857 | W18: 3 | X18: 1 | Y18: 4 | Z18: 3.5 | AA18: 4 | AK18: 5 | AL18: =AL10/AL$11 -> 0.28856431 | AM18: =AM10/AM$11 -> 0.2710489 | AN18: =AN10/AN$11 -> 0.26554264 | AO18: =AO10/AO$11 -> 0.28117066 | AP18: =AP10/AP$11 -> 0.34019025 | AQ18: =AQ10/AQ$11 -> 0.25104663
A19: 9001061400 | B19: 9001061400 | C19: Fairfield | D19: No | E19: 118695.18 | F19: 0.0040787861 | G19: 8852.19 | H19: 0.00052688509 | I19: NO | J19: NO | K19: 47281.252 | L19: 0.0040787861 | M19: 5299.19 | N19: 0.00052688509 | O19: NO | P19: 71413.923 | Q19: 0.0040787861 | R19: 3553 | S19: 0.00052688509 | T19: NO | U19: 56.725 | V19: 1873 | W19: 3 | X19: 1 | Y19: 5 | Z19: 4 | AA19: 4
A20: 9001061500 | B20: 9001061500 | C20: Bridgeport | D20: No | E20: 539.357 | F20: 1.8534215e-05 | G20: 0 | H20: 0 | I20: N/A | J20: NO | K20: 0 | L20: 1.8534215e-05 | M20: 0 | N20: 0 | O20: NO | P20: 539.357 | Q20: 1.8534215e-05 | R20: 0 | S20: 0 | T20: NO | U20: 89.569 | V20: 2670 | W20: 1 | X20: 1 | Y20: 4 | Z20: 2.5 | AA20: 3 | AJ20: Affluence index
A21: 9001061500 | B21: 9001061500 | C21: Fairfield | D21: No | E21: 188421.01 | F21: 0.0064748126 | G21: 34700.67 | H21: 0.0020653946 | I21: NO | J21: NO | K21: 104123.37 | L21: 0.0064748126 | M21: 13917.12 | N21: 0.0020653946 | O21: NO | P21: 84297.644 | Q21: 0.0064748126 | R21: 20783.55 | S21: 0.0020653946 | T21: NO | U21: 89.569 | V21: 2670 | W21: 1 | X21: 1 | Y21: 4 | Z21: 2.5 | AA21: 3 | AK21: Row Labels | AL21: Sum of CLM $ Collected | AM21: Sum of Incentive Disbursements | AN21: Sum of Residential CLM $ Collected | AO21: Sum of Residential Incentive Disbursements | AP21: Sum of C&I CLM $ Collected | AQ21: Sum of C&I Incentive Disbursements
A22: 9001061600 | B22: 9001061600 | C22: Fairfield | D22: No | E22: 182195.89 | F22: 0.0062608955 | G22: 24755.48 | H22: 0.0014734538 | I22: NO | J22: NO | K22: 114122.91 | L22: 0.0062608955 | M22: 10431.48 | N22: 0.0014734538 | O22: NO | P22: 68072.98 | Q22: 0.0062608955 | R22: 14324 | S22: 0.0014734538 | T22: NO | U22: 80.624 | V22: 2370 | W22: 1 | X22: 1 | Y22: 1 | Z22: 1 | AA22: 1 | AK22: 1 | AL22: 2809461.1 | AM22: 878020.93 | AN22: 2230487.9 | AO22: 652857.03 | AP22: 578973.19 | AQ22: 225163.9
A23: 9001070100 | B23: 9001070100 | C23: BRIDGEPORT | D23: No | E23: 0 | F23: 0 | G23: 11586.15 | H23: 0.00068961123 | I23: YES | J23: N/A | K23: 0 | L23: 0 | M23: 11088.15 | N23: 0.00068961123 | O23: N/A | P23: 0 | Q23: 0 | R23: 498 | S23: 0.00068961123 | T23: N/A | U23: 59.891 | V23: 1489 | W23: 3 | X23: 1 | Y23: 4 | Z23: 3.5 | AA23: 4 | AK23: 2 | AL23: 3647227 | AM23: 1769873.3 | AN23: 2501741.3 | AO23: 901132.89 | AP23: 1145485.7 | AQ23: 868740.37
A24: 9001070100 | B24: 9001070100 | C24: Bridgeport | D24: Yes | E24: 118414.09 | F24: 0.0040691272 | G24: 0 | H24: 0 | I24: N/A | J24: NO | K24: 87876.711 | L24: 0.0040691272 | M24: 0 | N24: 0 | O24: NO | P24: 30537.383 | Q24: 0.0040691272 | R24: 0 | S24: 0 | T24: NO | U24: 59.891 | V24: 1489 | W24: 3 | X24: 1 | Y24: 4 | Z24: 3.5 | AA24: 4 | AK24: 3 | AL24: 3700388.6 | AM24: 1973902.6 | AN24: 2519773.1 | AO24: 1416615.2 | AP24: 1180615.5 | AQ24: 557287.41
A25: 9001070200 | B25: 9001070200 | C25: BRIDGEPORT | D25: No | E25: 0 | F25: 0 | G25: 8670.73 | H25: 0.00051608453 | I25: YES | J25: N/A | K25: 0 | L25: 0 | M25: 2227.93 | N25: 0.00051608453 | O25: N/A | P25: 0 | Q25: 0 | R25: 6442.8 | S25: 0.00051608453 | T25: N/A | U25: 27.729 | V25: 1292 | W25: 5 | X25: 1 | Y25: 4 | Z25: 4.5 | AA25: 5 | AK25: 4 | AL25: 3405799.7 | AM25: 1248759.9 | AN25: 2420231.1 | AO25: 904056.85 | AP25: 985568.57 | AQ25: 344703.07
A26: 9001070200 | B26: 9001070200 | C26: Bridgeport | D26: Yes | E26: 67503.345 | F26: 0.0023196537 | G26: 0 | H26: 0 | I26: N/A | J26: NO | K26: 45704.852 | L26: 0.0023196537 | M26: 0 | N26: 0 | O26: NO | P26: 21798.492 | Q26: 0.0023196537 | R26: 0 | S26: 0 | T26: NO | U26: 27.729 | V26: 1292 | W26: 5 | X26: 1 | Y26: 4 | Z26: 4.5 | AA26: 5 | AK26: 5 | AL26: 3975982.6 | AM26: 1684830 | AN26: 2457559.5 | AO26: 1142092.4 | AP26: 1518423 | AQ26: 542737.59
A27: 9001070200 | B27: 9001070200 | C27: TRUMBULL | D27: No | E27: 0 | F27: 0 | G27: 749.66 | H27: 4.4619995e-05 | I27: YES | J27: N/A | K27: 0 | L27: 0 | M27: 749.66 | N27: 4.4619995e-05 | O27: N/A | P27: 0 | Q27: 0 | R27: 0 | S27: 4.4619995e-05 | T27: N/A | U27: 27.729 | V27: 1292 | W27: 5 | X27: 1 | Y27: 4 | Z27: 4.5 | AA27: 5 | AK27: Grand Total | AL27: 17538859 | AM27: 7555386.7 | AN27: 12129793 | AO27: 5016754.3 | AP27: 5409066.1 | AQ27: 2538632.3
A28: 9001070300 | B28: 9001070300 | C28: BRIDGEPORT | D28: No | E28: 0 | F28: 0 | G28: 213519.3 | H28: 0.012708735 | I28: YES | J28: N/A | K28: 0 | L28: 0 | M28: 202635.3 | N28: 0.012708735 | O28: N/A | P28: 0 | Q28: 0 | R28: 10884 | S28: 0.012708735 | T28: N/A | U28: 5.532 | V28: 433 | W28: 5 | X28: 1 | Y28: 4 | Z28: 4.5 | AA28: 5
A29: 9001070300 | B29: 9001070300 | C29: Bridgeport | D29: Yes | E29: 52641.309 | F29: 0.0018089416 | G29: 0 | H29: 0 | I29: N/A | J29: NO | K29: 16956.724 | L29: 0.0018089416 | M29: 0 | N29: 0 | O29: NO | P29: 35684.585 | Q29: 0.0018089416 | R29: 0 | S29: 0 | T29: NO | U29: 5.532 | V29: 433 | W29: 5 | X29: 1 | Y29: 4 | Z29: 4.5 | AA29: 5 | AK29: Row Labels | AL29: Collections % | AM29: Collections Disbursement | AN29: RES collections | AO29: RES disbursements | AP29: C&I Collection | AQ29: C&I disburse
A30: 9001070400 | B30: 9001070400 | C30: BRIDGEPORT | D30: No | E30: 0 | F30: 0 | G30: 2503.53 | H30: 0.00014901088 | I30: YES | J30: N/A | K30: 0 | L30: 0 | M30: 1029.53 | N30: 0.00014901088 | O30: N/A | P30: 0 | Q30: 0 | R30: 1474 | S30: 0.00014901088 | T30: N/A | U30: 25.893 | V30: 912 | W30: 5 | X30: 1 | Y30: 5 | Z30: 5 | AA30: 5 | AK30: 1 | AL30: =AL22/AL$27 -> 0.16018494 | AM30: =AM22/AM$27 -> 0.11621125 | AN30: =AN22/AN$27 -> 0.18388508 | AO30: =AO22/AO$27 -> 0.13013534 | AP30: =AP22/AP$27 -> 0.10703755 | AQ30: =AQ22/AQ$27 -> 0.088694962
A31: 9001070400 | B31: 9001070400 | C31: Bridgeport | D31: Yes | E31: 23919.493 | F31: 0.0008219584 | G31: 0 | H31: 0 | I31: N/A | J31: NO | K31: 17866.172 | L31: 0.0008219584 | M31: 0 | N31: 0 | O31: NO | P31: 6053.3215 | Q31: 0.0008219584 | R31: 0 | S31: 0 | T31: NO | U31: 25.893 | V31: 912 | W31: 5 | X31: 1 | Y31: 5 | Z31: 5 | AA31: 5 | AK31: 2 | AL31: =AL23/AL$27 -> 0.20795121 | AM31: =AM23/AM$27 -> 0.23425317 | AN31: =AN23/AN$27 -> 0.20624765 | AO31: =AO23/AO$27 -> 0.17962468 | AP31: =AP23/AP$27 -> 0.21177145 | AQ31: =AQ23/AQ$27 -> 0.34220803
A32: 9001070400 | B32: 9001070400 | C32: Stratford | D32: Yes | E32: 50.8641 | F32: 1.7478704e-06 | G32: 0 | H32: 0 | I32: N/A | J32: N/A | K32: 50.8641 | L32: 1.7478704e-06 | M32: 0 | N32: 0 | O32: N/A | P32: 0 | Q32: 1.7478704e-06 | R32: 0 | S32: 0 | T32: N/A | U32: 25.893 | V32: 912 | W32: 5 | X32: 1 | Y32: 5 | Z32: 5 | AA32: 5 | AK32: 3 | AL32: =AL24/AL$27 -> 0.21098229 | AM32: =AM24/AM$27 -> 0.26125765 | AN32: =AN24/AN$27 -> 0.20773422 | AO32: =AO24/AO$27 -> 0.28237683 | AP32: =AP24/AP$27 -> 0.21826606 | AQ32: =AQ24/AQ$27 -> 0.21952269
A33: 9001070500 | B33: 9001070500 | C33: BRIDGEPORT | D33: No | E33: 0 | F33: 0 | G33: 16596.99 | H33: 0.00098785798 | I33: YES | J33: N/A | K33: 0 | L33: 0 | M33: 359.75 | N33: 0.00098785798 | O33: N/A | P33: 0 | Q33: 0 | R33: 16237.24 | S33: 0.00098785798 | T33: N/A | U33: 15.334 | V33: 1275 | W33: 5 | X33: 1 | Y33: 5 | Z33: 5 | AA33: 5 | AK33: 4 | AL33: =AL25/AL$27 -> 0.19418593 | AM33: =AM25/AM$27 -> 0.16528074 | AN33: =AN25/AN$27 -> 0.19952782 | AO33: =AO25/AO$27 -> 0.18020752 | AP33: =AP25/AP$27 -> 0.18220679 | AQ33: =AQ25/AQ$27 -> 0.13578298
A34: 9001070500 | B34: 9001070500 | C34: Bridgeport | D34: Yes | E34: 29086.941 | F34: 0.00099953018 | G34: 0 | H34: 0 | I34: N/A | J34: NO | K34: 23101.569 | L34: 0.00099953018 | M34: 0 | N34: 0 | O34: NO | P34: 5985.372 | Q34: 0.00099953018 | R34: 0 | S34: 0 | T34: NO | U34: 15.334 | V34: 1275 | W34: 5 | X34: 1 | Y34: 5 | Z34: 5 | AA34: 5 | AK34: 5 | AL34: =AL26/AL$27 -> 0.22669562 | AM34: =AM26/AM$27 -> 0.22299719 | AN34: =AN26/AN$27 -> 0.20260523 | AO34: =AO26/AO$27 -> 0.22765563 | AP34: =AP26/AP$27 -> 0.28071815 | AQ34: =AQ26/AQ$27 -> 0.21379133
A35: 9001070600 | B35: 9001070600 | C35: BRIDGEPORT | D35: No | E35: 0 | F35: 0 | G35: 110631.34 | H35: 0.0065848116 | I35: YES | J35: N/A | K35: 0 | L35: 0 | M35: 96774.69 | N35: 0.0065848116 | O35: N/A | P35: 0 | Q35: 0 | R35: 13856.65 | S35: 0.0065848116 | T35: N/A | U35: 18.833 | V35: 974 | W35: 5 | X35: 1 | Y35: 4 | Z35: 4.5 | AA35: 5
A36: 9001070600 | B36: 9001070600 | C36: Bridgeport | D36: Yes | E36: 144313.23 | F36: 0.0049591131 | G36: 0 | H36: 0 | I36: N/A | J36: NO | K36: 35967.757 | L36: 0.0049591131 | M36: 0 | N36: 0 | O36: NO | P36: 108345.47 | Q36: 0.0049591131 | R36: 0 | S36: 0 | T36: NO | U36: 18.833 | V36: 974 | W36: 5 | X36: 1 | Y36: 4 | Z36: 4.5 | AA36: 5 | AJ36: Racial Diversity
A37: 9001070900 | B37: 9001070900 | C37: BRIDGEPORT | D37: No | E37: 0 | F37: 0 | G37: 30327.01 | H37: 0.001805073 | I37: YES | J37: N/A | K37: 0 | L37: 0 | M37: 4170.01 | N37: 0.001805073 | O37: N/A | P37: 0 | Q37: 0 | R37: 26157 | S37: 0.001805073 | T37: N/A | U37: 20.158 | V37: 1228 | W37: 5 | X37: 1 | Y37: 5 | Z37: 5 | AA37: 5 | AK37: Row Labels | AL37: Sum of CLM $ Collected | AM37: Sum of Incentive Disbursements | AN37: Sum of Residential CLM $ Collected | AO37: Sum of Residential Incentive Disbursements | AP37: Sum of C&I CLM $ Collected | AQ37: Sum of C&I Incentive Disbursements
A38: 9001070900 | B38: 9001070900 | C38: Bridgeport | D38: Yes | E38: 40068.742 | F38: 0.0013769037 | G38: 0 | H38: 0 | I38: N/A | J38: NO | K38: 29174.959 | L38: 0.0013769037 | M38: 0 | N38: 0 | O38: NO | P38: 10893.783 | Q38: 0.0013769037 | R38: 0 | S38: 0 | T38: NO | U38: 20.158 | V38: 1228 | W38: 5 | X38: 1 | Y38: 5 | Z38: 5 | AA38: 5 | AK38: 1 | AL38: 1535395.4 | AM38: 489966.54 | AN38: 1233439.3 | AO38: 355917.5 | AP38: 301956.11 | AQ38: 134049.04
A39: 9001071000 | B39: 9001071000 | C39: BRIDGEPORT | D39: No | E39: 0 | F39: 0 | G39: 17169.5 | H39: 0.0010219339 | I39: YES | J39: N/A | K39: 0 | L39: 0 | M39: 14379.5 | N39: 0.0010219339 | O39: N/A | P39: 0 | Q39: 0 | R39: 2790 | S39: 0.0010219339 | T39: N/A | U39: 27.215 | V39: 1323 | W39: 5 | X39: 1 | Y39: 5 | Z39: 5 | AA39: 5 | AK39: 2 | AL39: 2438778.6 | AM39: 840590.69 | AN39: 1849524.4 | AO39: 641461.43 | AP39: 589254.16 | AQ39: 199129.26
A40: 9001071000 | B40: 9001071000 | C40: Bridgeport | D40: Yes | E40: 63545.393 | F40: 0.0021836445 | G40: 0 | H40: 0 | I40: N/A | J40: NO | K40: 37249.349 | L40: 0.0021836445 | M40: 0 | N40: 0 | O40: NO | P40: 26296.044 | Q40: 0.0021836445 | R40: 0 | S40: 0 | T40: NO | U40: 27.215 | V40: 1323 | W40: 5 | X40: 1 | Y40: 5 | Z40: 5 | AA40: 5 | AK40: 3 | AL40: 4435476.1 | AM40: 1795986.2 | AN40: 3153797.1 | AO40: 1288734.7 | AP40: 1281679 | AQ40: 507251.52
A41: 9001071100 | B41: 9001071100 | C41: Bridgeport | D41: No | E41: 66899.111 | F41: 0.0022988901 | G41: 29836.83 | H41: 0.0017758973 | I41: NO | J41: NO | K41: 51783.79 | L41: 0.0022988901 | M41: 21423.83 | N41: 0.0017758973 | O41: NO | P41: 15115.321 | Q41: 0.0022988901 | R41: 8413 | S41: 0.0017758973 | T41: NO | U41: 25.633 | V41: 1271 | W41: 5 | X41: 1 | Y41: 5 | Z41: 5 | AA41: 5 | AK41: 4 | AL41: 4048969.2 | AM41: 2234279.7 | AN41: 2680511.7 | AO41: 1554367.5 | AP41: 1368457.5 | AQ41: 679912.24
A42: 9001071200 | B42: 9001071200 | C42: BRIDGEPORT | D42: No | E42: 0 | F42: 0 | G42: 20104.86 | H42: 0.0011966475 | I42: YES | J42: N/A | K42: 0 | L42: 0 | M42: 4593.86 | N42: 0.0011966475 | O42: N/A | P42: 0 | Q42: 0 | R42: 15511 | S42: 0.0011966475 | T42: N/A | U42: 13.99 | V42: 1107 | W42: 5 | X42: 1 | Y42: 5 | Z42: 5 | AA42: 5 | AK42: 5 | AL42: 5080239.7 | AM42: 2194563.5 | AN42: 3212520.4 | AO42: 1176273.2 | AP42: 1867719.3 | AQ42: 1018290.3
A43: 9001071200 | B43: 9001071200 | C43: Bridgeport | D43: Yes | E43: 65667.876 | F43: 0.0022565805 | G43: 0 | H43: 0 | I43: N/A | J43: NO | K43: 45169.658 | L43: 0.0022565805 | M43: 0 | N43: 0 | O43: NO | P43: 20498.218 | Q43: 0.0022565805 | R43: 0 | S43: 0 | T43: NO | U43: 13.99 | V43: 1107 | W43: 5 | X43: 1 | Y43: 5 | Z43: 5 | AA43: 5 | AK43: Grand Total | AL43: 17538859 | AM43: 7555386.7 | AN43: 12129793 | AO43: 5016754.3 | AP43: 5409066.1 | AQ43: 2538632.3
A44: 9001071300 | B44: 9001071300 | C44: BRIDGEPORT | D44: No | E44: 0 | F44: 0 | G44: 2772.32 | H44: 0.00016500934 | I44: YES | J44: N/A | K44: 0 | L44: 0 | M44: 1572.32 | N44: 0.00016500934 | O44: N/A | P44: 0 | Q44: 0 | R44: 1200 | S44: 0.00016500934 | T44: N/A | U44: 17.511 | V44: 1078 | W44: 5 | X44: 1 | Y44: 5 | Z44: 5 | AA44: 5
A45: 9001071300 | B45: 9001071300 | C45: Bridgeport | D45: Yes | E45: 54252.862 | F45: 0.0018643203 | G45: 0 | H45: 0 | I45: N/A | J45: NO | K45: 34389.421 | L45: 0.0018643203 | M45: 0 | N45: 0 | O45: NO | P45: 19863.441 | Q45: 0.0018643203 | R45: 0 | S45: 0 | T45: NO | U45: 17.511 | V45: 1078 | W45: 5 | X45: 1 | Y45: 5 | Z45: 5 | AA45: 5 | AK45: Row Labels | AL45: Collections % | AM45: Collections Disbursement | AN45: RES collections | AO45: RES disbursements | AP45: C&I Collection | AQ45: C&I disburse
A46: 9001071400 | B46: 9001071400 | C46: Bridgeport | D46: No | E46: 68350.447 | F46: 0.0023487632 | G46: 10239.37 | H46: 0.00060945047 | I46: NO | J46: NO | K46: 38432.276 | L46: 0.0023487632 | M46: 3327.16 | N46: 0.00060945047 | O46: NO | P46: 29918.171 | Q46: 0.0023487632 | R46: 6912.21 | S46: 0.00060945047 | T46: NO | U46: 22.64 | V46: 1131 | W46: 5 | X46: 1 | Y46: 5 | Z46: 5 | AA46: 5 | AK46: 1 | AL46: =AL38/AL$43 -> 0.087542493 | AM46: =AM38/AM$43 -> 0.064849962 | AN46: =AN38/AN$43 -> 0.10168676 | AO46: =AO38/AO$43 -> 0.07094577 | AP46: =AP38/AP$43 -> 0.055824075 | AQ46: =AQ38/AQ$43 -> 0.052803645
A47: 9001071600 | B47: 9001071600 | C47: BRIDGEPORT | D47: No | E47: 0 | F47: 0 | G47: 1330.85 | H47: 7.9212604e-05 | I47: YES | J47: N/A | K47: 0 | L47: 0 | M47: 1330.85 | N47: 7.9212604e-05 | O47: N/A | P47: 0 | Q47: 0 | R47: 0 | S47: 7.9212604e-05 | T47: N/A | U47: 11.771 | V47: 1032 | W47: 5 | X47: 1 | Y47: 4 | Z47: 4.5 | AA47: 5 | AK47: 2 | AL47: =AL39/AL$43 -> 0.13905001 | AM47: =AM39/AM$43 -> 0.11125714 | AN47: =AN39/AN$43 -> 0.15247782 | AO47: =AO39/AO$43 -> 0.12786383 | AP47: =AP39/AP$43 -> 0.10893824 | AQ47: =AQ39/AQ$43 -> 0.078439582
A48: 9001071600 | B48: 9001071600 | C48: Bridgeport | D48: Yes | E48: 31813.544 | F48: 0.0010932259 | G48: 0 | H48: 0 | I48: N/A | J48: NO | K48: 24529.813 | L48: 0.0010932259 | M48: 0 | N48: 0 | O48: NO | P48: 7283.7306 | Q48: 0.0010932259 | R48: 0 | S48: 0 | T48: NO | U48: 11.771 | V48: 1032 | W48: 5 | X48: 1 | Y48: 4 | Z48: 4.5 | AA48: 5 | AK48: 3 | AL48: =AL40/AL$43 -> 0.25289422 | AM48: =AM40/AM$43 -> 0.23770937 | AN48: =AN40/AN$43 -> 0.2600042 | AO48: =AO40/AO$43 -> 0.25688614 | AP48: =AP40/AP$43 -> 0.23695015 | AQ48: =AQ40/AQ$43 -> 0.19981291
A49: 9001071900 | B49: 9001071900 | C49: ANSONIA | D49: No | E49: 0 | F49: 0 | G49: 230 | H49: 1.3689671e-05 | I49: YES | J49: N/A | K49: 0 | L49: 0 | M49: 230 | N49: 1.3689671e-05 | O49: N/A | P49: 0 | Q49: 0 | R49: 0 | S49: 1.3689671e-05 | T49: N/A | U49: 26.15 | V49: 1287 | W49: 5 | X49: 1 | Y49: 5 | Z49: 5 | AA49: 5 | AK49: 4 | AL49: =AL41/AL$43 -> 0.23085705 | AM49: =AM41/AM$43 -> 0.29572011 | AN49: =AN41/AN$43 -> 0.22098578 | AO49: =AO41/AO$43 -> 0.30983528 | AP49: =AP41/AP$43 -> 0.2529933 | AQ49: =AQ41/AQ$43 -> 0.26782619
A50: 9001071900 | B50: 9001071900 | C50: BRIDGEPORT | D50: No | E50: 0 | F50: 0 | G50: 8360.09 | H50: 0.00049759514 | I50: YES | J50: N/A | K50: 0 | L50: 0 | M50: 3390.23 | N50: 0.00049759514 | O50: N/A | P50: 0 | Q50: 0 | R50: 4969.86 | S50: 0.00049759514 | T50: N/A | U50: 26.15 | V50: 1287 | W50: 5 | X50: 1 | Y50: 5 | Z50: 5 | AA50: 5 | AK50: 5 | AL50: =AL42/AL$43 -> 0.28965623 | AM50: =AM42/AM$43 -> 0.29046343 | AN50: =AN42/AN$43 -> 0.26484544 | AO50: =AO42/AO$43 -> 0.23446897 | AP50: =AP42/AP$43 -> 0.34529423 | AQ50: =AQ42/AQ$43 -> 0.40111767
A51: 9001071900 | B51: 9001071900 | C51: Bridgeport | D51: Yes | E51: 64668.712 | F51: 0.0022222457 | G51: 0 | H51: 0 | I51: N/A | J51: NO | K51: 46534.636 | L51: 0.0022222457 | M51: 0 | N51: 0 | O51: NO | P51: 18134.076 | Q51: 0.0022222457 | R51: 0 | S51: 0 | T51: NO | U51: 26.15 | V51: 1287 | W51: 5 | X51: 1 | Y51: 5 | Z51: 5 | AA51: 5
A52: 9001072000 | B52: 9001072000 | C52: BRIDGEPORT | D52: No | E52: 0 | F52: 0 | G52: 19104.27 | H52: 0.0011370921 | I52: YES | J52: N/A | K52: 0 | L52: 0 | M52: 19032.27 | N52: 0.0011370921 | O52: N/A | P52: 0 | Q52: 0 | R52: 72 | S52: 0.0011370921 | T52: N/A | U52: 31.123 | V52: 1386 | W52: 4 | X52: 1 | Y52: 5 | Z52: 4.5 | AA52: 5
A53: 9001072000 | B53: 9001072000 | C53: Bridgeport | D53: Yes | E53: 52439.412 | F53: 0.0018020037 | G53: 0 | H53: 0 | I53: N/A | J53: NO | K53: 43927.02 | L53: 0.0018020037 | M53: 0 | N53: 0 | O53: NO | P53: 8512.3916 | Q53: 0.0018020037 | R53: 0 | S53: 0 | T53: NO | U53: 31.123 | V53: 1386 | W53: 4 | X53: 1 | Y53: 5 | Z53: 4.5 | AA53: 5
A54: 9001072100 | B54: 9001072100 | C54: Bridgeport | D54: No | E54: 147726.38 | F54: 0.0050764009 | G54: 46711.47 | H54: 0.0027802811 | I54: NO | J54: NO | K54: 119833.88 | L54: 0.0050764009 | M54: 44620.47 | N54: 0.0027802811 | O54: NO | P54: 27892.497 | Q54: 0.0050764009 | R54: 2091 | S54: 0.0027802811 | T54: NO | U54: 37.423 | V54: 1463 | W54: 4 | X54: 1 | Y54: 5 | Z54: 4.5 | AA54: 5
A55: 9001072100 | B55: 9001072100 | C55: Fairfield | D55: No | E55: 383.211 | F55: 1.3168486e-05 | G55: 0 | H55: 0 | I55: N/A | J55: NO | K55: 302.3541 | L55: 1.3168486e-05 | M55: 0 | N55: 0 | O55: NO | P55: 80.8569 | Q55: 1.3168486e-05 | R55: 0 | S55: 0 | T55: NO | U55: 37.423 | V55: 1463 | W55: 4 | X55: 1 | Y55: 5 | Z55: 4.5 | AA55: 5
A56: 9001072200 | B56: 9001072200 | C56: BRIDGEPORT | D56: No | E56: 0 | F56: 0 | G56: 74220.17 | H56: 0.0044176075 | I56: YES | J56: N/A | K56: 0 | L56: 0 | M56: 23077.93 | N56: 0.0044176075 | O56: N/A | P56: 0 | Q56: 0 | R56: 51142.24 | S56: 0.0044176075 | T56: N/A | U56: 31.307 | V56: 1641 | W56: 4 | X56: 1 | Y56: 4 | Z56: 4 | AA56: 4
A57: 9001072200 | B57: 9001072200 | C57: Bridgeport | D57: Yes | E57: 48370.035 | F57: 0.0016621655 | G57: 0 | H57: 0 | I57: N/A | J57: NO | K57: 41166.363 | L57: 0.0016621655 | M57: 0 | N57: 0 | O57: NO | P57: 7203.6723 | Q57: 0.0016621655 | R57: 0 | S57: 0 | T57: NO | U57: 31.307 | V57: 1641 | W57: 4 | X57: 1 | Y57: 4 | Z57: 4 | AA57: 4
A58: 9001072200 | B58: 9001072200 | C58: Fairfield | D58: Yes | E58: 1.5975 | F58: 5.4895752e-08 | G58: 0 | H58: 0 | I58: N/A | J58: N/A | K58: 0 | L58: 5.4895752e-08 | M58: 0 | N58: 0 | O58: N/A | P58: 1.5975 | Q58: 5.4895752e-08 | R58: 0 | S58: 0 | T58: N/A | U58: 31.307 | V58: 1641 | W58: 4 | X58: 1 | Y58: 4 | Z58: 4 | AA58: 4
A59: 9001072300 | B59: 9001072300 | C59: Bridgeport | D59: No | E59: 71996.737 | F59: 0.0024740626 | G59: 18750.49 | H59: 0.001116035 | I59: NO | J59: NO | K59: 62912.309 | L59: 0.0024740626 | M59: 15404.49 | N59: 0.001116035 | O59: NO | P59: 9084.4276 | Q59: 0.0024740626 | R59: 3346 | S59: 0.001116035 | T59: NO | U59: 36.318 | V59: 1594 | W59: 3 | X59: 1 | Y59: 5 | Z59: 4 | AA59: 4
A60: 9001072400 | B60: 9001072400 | C60: Bridgeport | D60: No | E60: 46883.466 | F60: 0.0016110818 | G60: 33071.41 | H60: 0.0019684206 | I60: YES | J60: YES | K60: 38727.082 | L60: 0.0016110818 | M60: 29244.41 | N60: 0.0019684206 | O60: YES | P60: 8156.3842 | Q60: 0.0016110818 | R60: 3827 | S60: 0.0019684206 | T60: YES | U60: 32.786 | V60: 1532 | W60: 4 | X60: 1 | Y60: 5 | Z60: 4.5 | AA60: 5
A61: 9001072500 | B61: 9001072500 | C61: Bridgeport | D61: No | E61: 93619.371 | F61: 0.0032170928 | G61: 19820.64 | H61: 0.0011797306 | I61: NO | J61: NO | K61: 78001.035 | L61: 0.0032170928 | M61: 18716.64 | N61: 0.0011797306 | O61: NO | P61: 15618.336 | Q61: 0.0032170928 | R61: 1104 | S61: 0.0011797306 | T61: NO | U61: 38.706 | V61: 1492 | W61: 4 | X61: 1 | Y61: 4 | Z61: 4 | AA61: 4
A62: 9001072500 | B62: 9001072500 | C62: Fairfield | D62: No | E62: 55.9806 | F62: 1.9236915e-06 | G62: 0 | H62: 0 | I62: N/A | J62: N/A | K62: 0 | L62: 1.9236915e-06 | M62: 0 | N62: 0 | O62: N/A | P62: 55.9806 | Q62: 1.9236915e-06 | R62: 0 | S62: 0 | T62: N/A | U62: 38.706 | V62: 1492 | W62: 4 | X62: 1 | Y62: 4 | Z62: 4 | AA62: 4
... A393: 9009361500 | B393: 9009361500 | C393: West Haven | D393: No | E393: 149377.59 | F393: 0.0051331423 | G393: 43604.06 | H393: 0.0025953271 | I393: NO | J393: NO | K393: 88395.971 | L393: 0.0051331423 | M393: 17211.07 | N393: 0.0025953271 | O393: NO | P393: 60981.615 | Q393: 0.0051331423 | R393: 26392.99 | S393: 0.0025953271 | T393: NO | U393: 34.21 | V393: 1260 | W393: 4 | X393: 1 | Y393: 5 | Z393: 4.5 | AA393: 5

Sheet Sheet4
A1: Row Labels | B1: Sum of Residential CLM $ Collected | C1: Sum of Residential Incentive Disbursements
A2: 9001070300 | B2: 16956.724 | C2: 202635.3
A3: 9001070400 | B3: 17917.036 | C3: 1029.53 | K3: Row Labels | L3: Sum of Residential CLM $ Collected | M3: Sum of Residential Incentive Disbursements | N3: HESReportTable.Distressed Tract1 | O3: HESReportTable.CLM $ Collected | P3: HESReportTable.Incentive Disbursements | Q3: HESReportTable.HES Total Units | R3: HESReportTable.HES Single Family | S3: HESReportTable.HES 2-4 Units | T3: HESReportTable.HES >4 Units | U3: HESReportTable.Incentives | V3: HESReportTable.HESIE Total Units | W3: HESReportTable.HESIE Single Family | X3: HESReportTable.HESIE 2-4 Units2 | Y3: HESReportTable.HESIE >4 Units | Z3: HESReportTable.HESIE Incentives
A4: 9001070500 | B4: 23101.569 | C4: 359.75 | K4: 9001070300 | L4: 16956.724 | M4: 202635.3 | N4: No | O4: 0 | P4: 202635.3 | Q4: 0 | U4: 0 | V4: 2 | W4: 0 | X4: 1 | Y4: 1 | Z4: 202635.3
A5: 9001070900 | B5: 29174.959 | C5: 4170.01 | K5: 9001070300 | L5: 16956.724 | M5: 202635.3 | N5: Yes | O5: 16956.724 | P5: 0 | Q5: 0 | U5: 0 | V5: 0 | Z5: 0
A6: 9001071000 | B6: 37249.349 | C6: 14379.5 | K6: 9001070400 | L6: 17917.036 | M6: 1029.53 | N6: No | O6: 0 | P6: 1029.53 | Q6: 3 | R6: 3 | S6: 0 | T6: 0 | U6: 380.24 | V6: 6 | W6: 2 | X6: 4 | Y6: 0 | Z6: 649.29 | AB6: Row Labels | AC6: Sum of Sum of Residential CLM $ Collected | AD6: Sum of Sum of Residential Incentive Disbursements | AE6: Sum of HESReportTable.CLM $ Collected | AF6: Sum of HESReportTable.Incentive Disbursements | AG6: Sum of HESReportTable.Incentives | AH6: Sum of HESReportTable.HESIE Incentives | AI6: Sum of HESReportTable.HES Total Units | AJ6: Sum of HESReportTable.HESIE Total Units
A7: 9001071100 | B7: 51783.79 | C7: 21423.83 | K7: 9001070400 | L7: 17917.036 | M7: 1029.53 | N7: Yes | O7: 17866.172 | P7: 0 | Q7: 0 | U7: 0 | V7: 0 | Z7: 0 | AB7: 9001070300 | AC7: 33913.448 | AD7: 405270.6 | AE7: 16956.724 | AF7: 202635.3 | AG7: 0 | AH7: 202635.3 | AI7: 0 | AJ7: 2
A8: 9001071200 | B8: 45169.658 | C8: 4593.86 | K8: 9001070400 | L8: 17917.036 | M8: 1029.53 | N8: Yes | O8: 50.8641 | P8: 0 | Q8: 0 | U8: 0 | V8: 0 | Z8: 0 | AB8: 9001070400 | AC8: 53751.107 | AD8: 3088.59 | AE8: 17917.036 | AF8: 1029.53 | AG8: 380.24 | AH8: 649.29 | AI8: 3 | AJ8: 6
A9: 9001071300 | B9: 34389.421 | C9: 1572.32 | K9: 9001070500 | L9: 23101.569 | M9: 359.75 | N9: No | O9: 0 | P9: 359.75 | Q9: 0 | U9: 75 | V9: 7 | W9: 0 | X9: 7 | Y9: 0 | Z9: 284.75 | AB9: 9001070500 | AC9: 46203.137 | AD9: 719.5 | AE9: 23101.569 | AF9: 359.75 | AG9: 75 | AH9: 284.75 | AI9: 0 | AJ9: 7
A10: 9001071400 | B10: 38432.276 | C10: 3327.16 | K10: 9001070500 | L10: 23101.569 | M10: 359.75 | N10: Yes | O10: 23101.569 | P10: 0 | Q10: 0 | U10: 0 | V10: 0 | Z10: 0 | AB10: 9001070900 | AC10: 58349.917 | AD10: 8340.02 | AE10: 29174.959 | AF10: 4170.01 | AG10: 1302.6 | AH10: 2867.41 | AI10: 1 | AJ10: 12
A11: 9001071600 | B11: 24529.813 | C11: 1330.85 | K11: 9001070900 | L11: 29174.959 | M11: 4170.01 | N11: No | O11: 0 | P11: 4170.01 | Q11: 1 | R11: 0 | S11: 1 | T11: 0 | U11: 1302.6 | V11: 12 | W11: 4 | X11: 8 | Y11: 0 | Z11: 2867.41 | AB11: 9001071000 | AC11: 74498.698 | AD11: 28759 | AE11: 37249.349 | AF11: 14379.5 | AG11: 118.52 | AH11: 14260.98 | AI11: 1 | AJ11: 17
A12: 9001071900 | B12: 46534.636 | C12: 3620.23 | K12: 9001070900 | L12: 29174.959 | M12: 4170.01 | N12: Yes | O12: 29174.959 | P12: 0 | Q12: 0 | U12: 0 | V12: 0 | Z12: 0 | AB12: 9001071100 | AC12: 51783.79 | AD12: 21423.83 | AE12: 51783.79 | AF12: 21423.83 | AG12: 1246.62 | AH12: 20177.21 | AI12: 5 | AJ12: 19
A13: 9001073300 | B13: 49786.05 | C13: 21408.65 | K13: 9001071000 | L13: 37249.349 | M13: 14379.5 | N13: No | O13: 0 | P13: 14379.5 | Q13: 1 | R13: 1 | S13: 0 | T13: 0 | U13: 118.52 | V13: 17 | W13: 2 | X13: 14 | Y13: 1 | Z13: 14260.98 | AB13: 9001071200 | AC13: 90339.316 | AD13: 9187.72 | AE13: 45169.658 | AF13: 4593.86 | AG13: 954.34 | AH13: 3639.52 | AI13: 2 | AJ13: 21
A14: 9001073400 | B14: 53978.009 | C14: 48424.62 | K14: 9001071000 | L14: 37249.349 | M14: 14379.5 | N14: Yes | O14: 37249.349 | P14: 0 | Q14: 0 | U14: 0 | V14: 0 | Z14: 0 | AB14: 9001071300 | AC14: 68778.842 | AD14: 3144.64 | AE14: 34389.421 | AF14: 1572.32 | AG14: 12.03 | AH14: 1560.29 | AI14: 1 | AJ14: 12
A15: 9001073500 | B15: 38030.339 | C15: 7178.22 | K15: 9001071100 | L15: 51783.79 | M15: 21423.83 | N15: No | O15: 51783.79 | P15: 21423.83 | Q15: 5 | R15: 4 | S15: 1 | T15: 0 | U15: 1246.62 | V15: 19 | W15: 9 | X15: 10 | Y15: 0 | Z15: 20177.21 | AB15: 9001071400 | AC15: 38432.276 | AD15: 3327.16 | AE15: 38432.276 | AF15: 3327.16 | AG15: 927.04 | AH15: 2400.12 | AI15: 2 | AJ15: 15
A16: 9001073600 | B16: 24351.613 | C16: 846.37 | K16: 9001071200 | L16: 45169.658 | M16: 4593.86 | N16: No | O16: 0 | P16: 4593.86 | Q16: 2 | R16: 2 | S16: 0 | T16: 0 | U16: 954.34 | V16: 21 | W16: 8 | X16: 13 | Y16: 0 | Z16: 3639.52 | AB16: 9001071600 | AC16: 49059.626 | AD16: 2661.7 | AE16: 24529.813 | AF16: 1330.85 | AG16: 0 | AH16: 1330.85 | AI16: 0 | AJ16: 8
A17: 9001073700 | B17: 64008.136 | C17: 24518.83 | K17: 9001071200 | L17: 45169.658 | M17: 4593.86 | N17: Yes | O17: 45169.658 | P17: 0 | Q17: 0 | U17: 0 | V17: 0 | Z17: 0 | AB17: 9001071900 | AC17: 139603.91 | AD17: 10860.69 | AE17: 46534.636 | AF17: 3620.23 | AG17: 404.3 | AH17: 3215.93 | AI17: 2 | AJ17: 11
A18: 9001073800 | B18: 25510.302 | C18: 2512.29 | K18: 9001071300 | L18: 34389.421 | M18: 1572.32 | N18: No | O18: 0 | P18: 1572.32 | Q18: 1 | R18: 0 | S18: 1 | T18: 0 | U18: 12.03 | V18: 12 | W18: 2 | X18: 10 | Y18: 0 | Z18: 1560.29 | AB18: 9001073300 | AC18: 99572.101 | AD18: 42817.3 | AE18: 49786.05 | AF18: 21408.65 | AG18: 1427.69 | AH18: 19980.96 | AI18: 3 | AJ18: 22
A19: 9001073900 | B19: 35070.079 | C19: 106775.64 | K19: 9001071300 | L19: 34389.421 | M19: 1572.32 | N19: Yes | O19: 34389.421 | P19: 0 | Q19: 0 | U19: 0 | V19: 0 | Z19: 0 | AB19: 9001073400 | AC19: 107956.02 | AD19: 96849.24 | AE19: 53978.009 | AF19: 48424.62 | AG19: 4874.45 | AH19: 43550.17 | AI19: 9 | AJ19: 29
A20: 9001074000 | B20: 26942.261 | C20: 13413.06 | K20: 9001071400 | L20: 38432.276 | M20: 3327.16 | N20: No | O20: 38432.276 | P20: 3327.16 | Q20: 2 | R20: 1 | S20: 1 | T20: 0 | U20: 927.04 | V20: 15 | W20: 2 | X20: 13 | Y20: 0 | Z20: 2400.12 | AB20: 9001073500 | AC20: 76060.678 | AD20: 14356.44 | AE20: 38030.339 | AF20: 7178.22 | AG20: 501.38 | AH20: 6676.84 | AI20: 5 | AJ20: 17
A21: 9001074300 | B21: 51618.49 | C21: 8289.77 | K21: 9001071600 | L21: 24529.813 | M21: 1330.85 | N21: No | O21: 0 | P21: 1330.85 | Q21: 0 | U21: 0 | V21: 8 | W21: 1 | X21: 7 | Y21: 0 | Z21: 1330.85 | AB21: 9001073600 | AC21: 48703.226 | AD21: 1692.74 | AE21: 24351.613 | AF21: 846.37 | AG21: 134.5 | AH21: 711.87 | AI21: 1 | AJ21: 7
A22: 9001074400 | B22: 54299.358 | C22: 20133.35 | K22: 9001071600 | L22: 24529.813 | M22: 1330.85 | N22: Yes | O22: 24529.813 | P22: 0 | Q22: 0 | U22: 0 | V22: 0 | Z22: 0 | AB22: 9001073700 | AC22: 192024.41 | AD22: 73556.49 | AE22: 64008.136 | AF22: 24518.83 | AG22: 3732.6 | AH22: 20786.23 | AI22: 3 | AJ22: 29
A23: 9001257200 | B23: 46248.605 | C23: 7200.74 | K23: 9001071900 | L23: 46534.636 | M23: 3620.23 | N23: No | O23: 0 | P23: 230 | Q23: 0 | U23: 0 | V23: 1 | W23: 1 | X23: 0 | Y23: 0 | Z23: 230 | AB23: 9001073800 | AC23: 51020.603 | AD23: 5024.58 | AE23: 25510.302 | AF23: 2512.29 | AG23: 2.34 | AH23: 447.45 | AI23: 1 | AJ23: 4
A24: 9009120200 | B24: 98996.496 | C24: 18704.38 | K24: 9001071900 | L24: 46534.636 | M24: 3620.23 | N24: No | O24: 0 | P24: 3390.23 | Q24: 2 | R24: 2 | S24: 0 | T24: 0 | U24: 404.3 | V24: 10 | W24: 3 | X24: 6 | Y24: 1 | Z24: 2985.93 | AB24: 9001073900 | AC24: 70140.158 | AD24: 213551.28 | AE24: 35070.079 | AF24: 106775.64 | AG24: 170.07 | AH24: 106605.57 | AI24: 2 | AJ24: 24
A25: 9009140200 | B25: 5569.7997 | C25: 0 | K25: 9001071900 | L25: 46534.636 | M25: 3620.23 | N25: Yes | O25: 46534.636 | P25: 0 | Q25: 0 | U25: 0 | V25: 0 | Z25: 0 | AB25: 9001074000 | AC25: 53884.523 | AD25: 26826.12 | AE25: 26942.261 | AF25: 13413.06 | AG25: 183.09 | AH25: 13229.97 | AI25: 1 | AJ25: 15
A26: 9009140300 | B26: 27566.795 | C26: 2174.45 | K26: 9001073300 | L26: 49786.05 | M26: 21408.65 | N26: No | O26: 0 | P26: 21408.65 | Q26: 3 | R26: 3 | S26: 0 | T26: 0 | U26: 1427.69 | V26: 22 | W26: 19 | X26: 2 | Y26: 1 | Z26: 19980.96 | AB26: 9001074300 | AC26: 154855.47 | AD26: 24869.31 | AE26: 51618.49 | AF26: 8289.77 | AG26: 550.87 | AH26: 7738.9 | AI26: 2 | AJ26: 26
A27: 9009140500 | B27: 40619.57 | C27: 2256.95 | K27: 9001073300 | L27: 49786.05 | M27: 21408.65 | N27: Yes | O27: 49786.05 | P27: 0 | Q27: 0 | U27: 0 | V27: 0 | Z27: 0 | AB27: 9001074400 | AC27: 108598.72 | AD27: 40266.7 | AE27: 54299.358 | AF27: 20133.35 | AG27: 3501.35 | AH27: 6632 | AI27: 9 | AJ27: 25
A28: 9009140600 | B28: 52288.773 | C28: 3999.65 | K28: 9001073400 | L28: 53978.009 | M28: 48424.62 | N28: No | O28: 0 | P28: 48424.62 | Q28: 9 | R28: 7 | S28: 2 | T28: 0 | U28: 4874.45 | V28: 29 | W28: 7 | X28: 22 | Y28: 0 | Z28: 43550.17 | AB28: 9001257200 | AC28: 46248.605 | AD28: 7200.74 | AE28: 46248.605 | AF28: 7200.74 | AG28: 481.19 | AH28: 6719.55 | AI28: 1 | AJ28: 15
A29: 9009141500 | B29: 89595.167 | C29: 47450.57 | K29: 9001073400 | L29: 53978.009 | M29: 48424.62 | N29: Yes | O29: 53978.009 | P29: 0 | Q29: 0 | U29: 0 | V29: 0 | Z29: 0 | AB29: 9009120200 | AC29: 296989.49 | AD29: 56113.14 | AE29: 98996.496 | AF29: 18704.38 | AG29: 9845.58 | AH29: 8858.8 | AI29: 16 | AJ29: 9
A30: 9009141600 | B30: 59212.537 | C30: 10815.87 | K30: 9001073500 | L30: 38030.339 | M30: 7178.22 | N30: No | O30: 0 | P30: 7178.22 | Q30: 5 | R30: 4 | S30: 1 | T30: 0 | U30: 501.38 | V30: 17 | W30: 4 | X30: 13 | Y30: 0 | Z30: 6676.84 | AB30: 9009140200 | AC30: 11139.599 | AD30: 0 | AE30: 5569.7997 | AF30: 0 | AG30: 0 | AH30: 0 | AI30: 0 | AJ30: 0
A31: 9009142300 | B31: 53392.116 | C31: 10400.34 | K31: 9001073500 | L31: 38030.339 | M31: 7178.22 | N31: Yes | O31: 38030.339 | P31: 0 | Q31: 0 | U31: 0 | V31: 0 | Z31: 0 | AB31: 9009140300 | AC31: 55133.59 | AD31: 4348.9 | AE31: 27566.795 | AF31: 2174.45 | AG31: 284.16 | AH31: 1890.29 | AI31: 1 | AJ31: 10
A32: 9009142400 | B32: 54491.193 | C32: 6815.37 | K32: 9001073600 | L32: 24351.613 | M32: 846.37 | N32: No | O32: 0 | P32: 846.37 | Q32: 1 | R32: 1 | S32: 0 | T32: 0 | U32: 134.5 | V32: 7 | W32: 1 | X32: 6 | Y32: 0 | Z32: 711.87 | AB32: 9009140500 | AC32: 81239.139 | AD32: 4513.9 | AE32: 40619.57 | AF32: 2256.95 | AG32: 1274.28 | AH32: 982.67 | AI32: 4 | AJ32: 5
A33: 9009142500 | B33: 65008.415 | C33: 7352.41 | K33: 9001073600 | L33: 24351.613 | M33: 846.37 | N33: Yes | O33: 24351.613 | P33: 0 | Q33: 0 | U33: 0 | V33: 0 | Z33: 0 | AB33: 9009140600 | AC33: 104577.55 | AD33: 7999.3 | AE33: 52288.773 | AF33: 3999.65 | AG33: 352.22 | AH33: 2334.93 | AI33: 4 | AJ33: 13
A34: 9009142700 | B34: 84074.735 | C34: 29975.46 | K34: 9001073700 | L34: 64008.136 | M34: 24518.83 | N34: No | O34: 0 | P34: 24518.83 | Q34: 3 | R34: 3 | S34: 0 | T34: 0 | U34: 3732.6 | V34: 29 | W34: 13 | X34: 16 | Y34: 0 | Z34: 20786.23 | AB34: 9009141500 | AC34: 268785.5 | AD34: 142351.71 | AE34: 89595.167 | AF34: 47450.57 | AG34: 2901.52 | AH34: 27049.05 | AI34: 9 | AJ34: 53
A35: 9009165500 | B35: 68231.695 | C35: 42137.05 | K35: 9001073700 | L35: 64008.136 | M35: 24518.83 | N35: Yes | O35: 64008.136 | P35: 0 | Q35: 0 | U35: 0 | V35: 0 | Z35: 0 | AB35: 9009141600 | AC35: 118425.07 | AD35: 21631.74 | AE35: 59212.537 | AF35: 10815.87 | AG35: 484.3 | AH35: 10331.57 | AI35: 4 | AJ35: 18
K36: 9001073700 | L36: 64008.136 | M36: 24518.83 | N36: Yes | O36: 0 | P36: 0 | Q36: 0 | U36: 0 | V36: 0 | Z36: 0 | AB36: 9009142300 | AC36: 160176.35 | AD36: 31201.02 | AE36: 53392.116 | AF36: 10400.34 | AG36: 2968.24 | AH36: 7432.1 | AI36: 10 | AJ36: 17
K37: 9001073800 | L37: 25510.302 | M37: 2512.29 | N37: No | O37: 0 | P37: 2512.29 | Q37: 1 | R37: 1 | S37: 0 | T37: 0 | U37: 2.34 | V37: 4 | W37: 1 | X37: 3 | Y37: 0 | Z37: 447.45 | AB37: 9009142400 | AC37: 108982.39 | AD37: 13630.74 | AE37: 54491.193 | AF37: 6815.37 | AG37: 2179.8 | AH37: 4635.57 | AI37: 6 | AJ37: 18
K38: 9001073800 | L38: 25510.302 | M38: 2512.29 | N38: Yes | O38: 25510.302 | P38: 0 | Q38: 0 | U38: 0 | V38: 0 | Z38: 0 | AB38: 9009142500 | AC38: 195025.24 | AD38: 22057.23 | AE38: 65008.414 | AF38: 7352.41 | AG38: 2183.98 | AH38: 5168.43 | AI38: 9 | AJ38: 8
K39: 9001073900 | L39: 35070.079 | M39: 106775.64 | N39: No | O39: 0 | P39: 106775.64 | Q39: 2 | R39: 2 | S39: 0 | T39: 0 | U39: 170.07 | V39: 24 | W39: 5 | X39: 17 | Y39: 2 | Z39: 106605.57 | AB39: 9009142700 | AC39: 168149.47 | AD39: 59950.92 | AE39: 84074.735 | AF39: 29975.46 | AG39: 8295.25 | AH39: 15680.21 | AI39: 8 | AJ39: 20
K40: 9001073900 | L40: 35070.079 | M40: 106775.64 | N40: Yes | O40: 35070.079 | P40: 0 | Q40: 0 | U40: 0 | V40: 0 | Z40: 0 | AB40: 9009165500 | AC40: 272926.78 | AD40: 168548.2 | AE40: 68231.695 | AF40: 42137.05 | AG40: 4512.21 | AH40: 37624.84 | AI40: 13 | AJ40: 21
K41: 9001074000 | L41: 26942.261 | M41: 13413.06 | N41: No | O41: 0 | P41: 13413.06 | Q41: 1 | R41: 1 | S41: 0 | T41: 0 | U41: 183.09 | V41: 15 | W41: 2 | X41: 13 | Y41: 0 | Z41: 13229.97 | AB41: Grand Total | AC41: 3555328.7 | AD41: 1576141.2 | AE41: 1534129.8 | AF41: 701226.38 | AG41: 56261.76 | AH41: 608089.62 | AI41: 138 | AJ41: 535
K42: 9001074000 | L42: 26942.261 | M42: 13413.06 | N42: Yes | O42: 26942.261 | P42: 0 | Q42: 0 | U42: 0 | V42: 0 | Z42: 0
K43: 9001074300 | L43: 51618.49 | M43: 8289.77 | N43: No | O43: 0 | P43: 8289.77 | Q43: 2 | R43: 0 | S43: 2 | T43: 0 | U43: 550.87 | V43: 26 | W43: 4 | X43: 22 | Y43: 0 | Z43: 7738.9
K44: 9001074300 | L44: 51618.49 | M44: 8289.77 | N44: Yes | O44: 51549.296 | P44: 0 | Q44: 0 | U44: 0 | V44: 0 | Z44: 0
K45: 9001074300 | L45: 51618.49 | M45: 8289.77 | N45: Yes | O45: 69.1943 | P45: 0 | Q45: 0 | U45: 0 | V45: 0 | Z45: 0
K46: 9001074400 | L46: 54299.358 | M46: 20133.35 | N46: No | O46: 0 | P46: 20133.35 | Q46: 9 | R46: 5 | S46: 4 | T46: 0 | U46: 3501.35 | V46: 25 | W46: 7 | X46: 17 | Y46: 1 | Z46: 6632
K47: 9001074400 | L47: 54299.358 | M47: 20133.35 | N47: Yes | O47: 54299.358 | P47: 0 | Q47: 0 | U47: 0 | V47: 0 | Z47: 0
K48: 9001257200 | L48: 46248.605 | M48: 7200.74 | N48: No | O48: 46248.605 | P48: 7200.74 | Q48: 1 | R48: 0 | S48: 1 | T48: 0 | U48: 481.19 | V48: 15 | W48: 5 | X48: 10 | Y48: 0 | Z48: 6719.55
K49: 9009120200 | L49: 98996.496 | M49: 18704.38 | N49: No | O49: 53.5323 | P49: 95.74 | Q49: 1 | R49: 1 | S49: 0 | T49: 0 | U49: 95.74 | V49: 0 | Z49: 0
K50: 9009120200 | L50: 98996.496 | M50: 18704.38 | N50: No | O50: 98942.964 | P50: 18608.64 | Q50: 15 | R50: 10 | S50: 5 | T50: 0 | U50: 9749.84 | V50: 9 | W50: 3 | X50: 6 | Y50: 0 | Z50: 8858.8
K51: 9009120200 | L51: 98996.496 | M51: 18704.38 | N51: No | O51: 0 | P51: 0 | Q51: 0 | U51: 0 | V51: 0 | Z51: 0
K52: 9009140200 | L52: 5569.7997 | M52: 0 | N52: No | O52: 0 | P52: 0 | Q52: 0 | U52: 0 | V52: 0 | Z52: 0
K53: 9009140200 | L53: 5569.7997 | M53: 0 | N53: Yes | O53: 5569.7997 | P53: 0 | Q53: 0 | U53: 0 | V53: 0 | Z53: 0
K54: 9009140300 | L54: 27566.795 | M54: 2174.45 | N54: No | O54: 0 | P54: 2174.45 | Q54: 1 | R54: 1 | S54: 0 | T54: 0 | U54: 284.16 | V54: 10 | W54: 2 | X54: 8 | Y54: 0 | Z54: 1890.29
K55: 9009140300 | L55: 27566.795 | M55: 2174.45 | N55: Yes | O55: 27566.795 | P55: 0 | Q55: 0 | U55: 0 | V55: 0 | Z55: 0
K56: 9009140500 | L56: 40619.57 | M56: 2256.95 | N56: No | O56: 0 | P56: 2256.95 | Q56: 4 | R56: 4 | S56: 0 | T56: 0 | U56: 1274.28 | V56: 5 | W56: 3 | X56: 2 | Y56: 0 | Z56: 982.67
K57: 9009140500 | L57: 40619.57 | M57: 2256.95 | N57: Yes | O57: 40619.57 | P57: 0 | Q57: 0 | U57: 0 | V57: 0 | Z57: 0
K58: 9009140600 | L58: 52288.773 | M58: 3999.65 | N58: No | O58: 0 | P58: 3999.65 | Q58: 4 | R58: 3 | S58: 1 | T58: 0 | U58: 352.22 | V58: 13 | W58: 5 | X58: 8 | Y58: 0 | Z58: 2334.93
K59: 9009140600 | L59: 52288.773 | M59: 3999.65 | N59: Yes | O59: 52288.773 | P59: 0 | Q59: 0 | U59: 0 | V59: 0 | Z59: 0
K60: 9009141500 | L60: 89595.167 | M60: 47450.57 | N60: Yes | O60: 94.991 | P60: 0 | Q60: 0 | U60: 0 | V60: 0 | Z60: 0
K61: 9009141500 | L61: 89595.167 | M61: 47450.57 | N61: No | O61: 0 | P61: 47450.57 | Q61: 9 | R61: 7 | S61: 2 | T61: 0 | U61: 2901.52 | V61: 53 | W61: 19 | X61: 34 | Y61: 0 | Z61: 27049.05
K62: 9009141500 | L62: 89595.167 | M62: 47450.57 | N62: Yes | O62: 89500.176 | P62: 0 | Q62: 0 | U62: 0 | V62: 0 | Z62: 0
K63: 9009141600 | L63: 59212.537 | M63: 10815.87 | N63: No | O63: 0 | P63: 10815.87 | Q63: 4 | R63: 1 | S63: 3 | T63: 0 | U63: 484.3 | V63: 18 | W63: 5 | X63: 13 | Y63: 0 | Z63: 10331.57
K64: 9009141600 | L64: 59212.537 | M64: 10815.87 | N64: Yes | O64: 59212.537 | P64: 0 | Q64: 0 | U64: 0 | V64: 0 | Z64: 0
K65: 9009142300 | L65: 53392.116 | M65: 10400.34 | N65: Yes | O65: 0 | P65: 0 | Q65: 0 | U65: 0 | V65: 0 | Z65: 0
K66: 9009142300 | L66: 53392.116 | M66: 10400.34 | N66: No | O66: 0 | P66: 10400.34 | Q66: 10 | R66: 3 | S66: 7 | T66: 0 | U66: 2968.24 | V66: 17 | W66: 2 | X66: 14 | Y66: 1 | Z66: 7432.1
K67: 9009142300 | L67: 53392.116 | M67: 10400.34 | N67: Yes | O67: 53392.116 | P67: 0 | Q67: 0 | U67: 0 | V67: 0 | Z67: 0
K68: 9009142400 | L68: 54491.193 | M68: 6815.37 | N68: No | O68: 0 | P68: 6815.37 | Q68: 6 | R68: 5 | S68: 1 | T68: 0 | U68: 2179.8 | V68: 18 | W68: 6 | X68: 12 | Y68: 0 | Z68: 4635.57
K69: 9009142400 | L69: 54491.193 | M69: 6815.37 | N69: Yes | O69: 54491.193 | P69: 0 | Q69: 0 | U69: 0 | V69: 0 | Z69: 0
K70: 9009142500 | L70: 65008.415 | M70: 7352.41 | N70: Yes | O70: 231.1571 | P70: 0 | Q70: 0 | U70: 0 | V70: 0 | Z70: 0
K71: 9009142500 | L71: 65008.415 | M71: 7352.41 | N71: No | O71: 0 | P71: 7352.41 | Q71: 9 | R71: 2 | S71: 7 | T71: 0 | U71: 2183.98 | V71: 8 | W71: 2 | X71: 6 | Y71: 0 | Z71: 5168.43
K72: 9009142500 | L72: 65008.415 | M72: 7352.41 | N72: Yes | O72: 64777.257 | P72: 0 | Q72: 0 | U72: 0 | V72: 0 | Z72: 0
K73: 9009142700 | L73: 84074.735 | M73: 29975.46 | N73: No | O73: 752.1549 | P73: 0 | Q73: 0 | U73: 0 | V73: 0 | Z73: 0
K74: 9009142700 | L74: 84074.735 | M74: 29975.46 | N74: No | O74: 83322.58 | P74: 29975.46 | Q74: 8 | R74: 8 | S74: 0 | T74: 0 | U74: 8295.25 | V74: 20 | W74: 11 | X74: 9 | Y74: 0 | Z74: 15680.21
K75: 9009165500 | L75: 68231.695 | M75: 42137.05 | N75: No | O75: 0 | P75: 42110.68 | Q75: 12 | R75: 10 | S75: 2 | T75: 0 | U75: 4485.84 | V75: 21 | W75: 11 | X75: 9 | Y75: 1 | Z75: 37624.84
K76: 9009165500 | L76: 68231.695 | M76: 42137.05 | N76: Yes | O76: 67465.568 | P76: 0 | Q76: 0 | U76: 0 | V76: 0 | Z76: 0
K77: 9009165500 | L77: 68231.695 | M77: 42137.05 | N77: No | O77: 0 | P77: 26.37 | Q77: 1 | R77: 1 | S77: 0 | T77: 0 | U77: 26.37 | V77: 0 | Z77: 0
K78: 9009165500 | L78: 68231.695 | M78: 42137.05 | N78: Yes | O78: 766.127 | P78: 0 | Q78: 0 | U78: 0 | V78: 0 | Z78: 0

Sheet HESParticipationStats
A1: id | B1: tract | C1: Geographic Area Name | D1: Estimate!!Occupied housing units!!Occupied housing units!!HOUSEHOLD INCOME IN THE PAST 12 MONTHS (IN 2019 INFLATION-ADJUSTED DOLLARS)!!Median household income (dollars) 250000 = 250000+ | E1: Estimate!!HOUSEHOLDS BY TYPE!!Total households!!Average household size | F1: Household Size Adjusted income = (Household Income)/(Household Size)^N N =1/2 | G1: adjusted income (thousands of $) | H1: incomee percentile | I1: Income Rank | J1: reverse income percentile | K1: REVERSE income Rank | L1: median census housing cost | M1: housing cost as percentage of income | N1: Housing cost rank as fraction of median income percentile | O1: housing cost rank | P1: Housing cost percentile | Q1: Housing cost rank on absolute housing cost | R1: Combined affluence rank | S1: CTRUCA.Primary RUCA Code 2010 | T1: CTRUCA.Secondary RUCA Code, 2010 (see errata) | U1: CTRUCA.Tract Population, 2010 | V1: CTRUCA.Land Area (square miles), 2010 | W1: CTRUCA.Population Density (per square mile), 2010 | X1: rural rank | Y1: racialdiversitytable.POC population | Z1: racialdiversitytable.POC % of population | AA1: racialdiversitytable.percentile rank | AB1: racial diversity index | AC1: composit index | AD1: rounded composite | AE1: Income <=60 %SMI? | AF1: Income <=80% SMI | AG1: HESReportTable.CLM $ Collected | AH1: HESReportTable.Incentive Disbursements | AI1: HESReportTable.HES Total Units | AJ1: HESReportTable.HES Single Family | AK1: HESReportTable.HES 2-4 Units | AL1: HESReportTable.HES >4 Units | AM1: HESReportTable.Incentives | AN1: HESReportTable.HESIE Total Units | AO1: HESReportTable.HESIE Single Family | AP1: HESReportTable.HESIE 2-4 Units2 | AQ1: HESReportTable.HESIE >4 Units | AR1: HESReportTable.HESIE Incentives | AX1: Income <=60 %SMI? | AY1: (All)
A2: 1400000US09001055100 | B2: 9001055100 | C2: Census Tract 551, Fairfield County, Connecticut | D2: 202500 | E2: 2.93 | F2: 118301.76 | G2: 118.302 | H2: 0.972 | I2: 5 | J2: 0.028 | K2: 1 | L2: 4000 | M2: 0.40574205 | N2: 0.693 | O2: 4 | P2: 0.011 | Q2: 1 | R2: 1 | S2: 1 | T2: 1 | U2: 5807 | V2: 13.373285 | W2: 434.2239 | X2: 1 | Y2: 942 | Z2: 16.875672 | AA2: 0.657 | AB2: 4 | AC2: 2.5 | AD2: 3 | AE2: No | AF2: No | AG2: 394.428 | AH2: 0 | AI2: 0 | AM2: 0 | AN2: 0 | AR2: 0 | AX2: Income <=80% SMI | AY2: (All)
A3: 1400000US09001055200 | B3: 9001055200 | C3: Census Tract 552, Fairfield County, Connecticut | D3: 247361 | E3: 3.05 | F3: 141638.5 | G3: 141.638 | H3: 0.992 | I3: 5 | J3: 0.008 | K3: 1 | L3: 3750 | M3: 0.31771023 | N3: 0.27 | O3: 2 | P3: 0.018 | Q3: 1 | R3: 1 | S3: 1 | T3: 1 | U3: 4372 | V3: 6.4253919 | W3: 680.42542 | X3: 1 | Y3: 241 | Z3: 5.1222104 | AA3: 0.143 | AB3: 1 | AC3: 1 | AD3: 1 | AE3: No | AF3: No | AG3: 887.5106 | AH3: 0 | AI3: 0 | AM3: 0 | AN3: 0 | AR3: 0 | BF3: BIPOC INDEX | BG3: Sum of HESReportTable.CLM $ Collected | BH3: Sum of HESReportTable.Incentive Disbursements | BI3: Sum of HESReportTable.HES Total Units | BJ3: Sum of HESReportTable.Incentives | BK3: Sum of HESReportTable.HESIE Total Units | BL3: Sum of HESReportTable.HESIE Incentives
A4: 1400000US09001060100 | B4: 9001060100 | C4: Census Tract 601, Fairfield County, Connecticut | D4: 139000 | E4: 2.65 | F4: 85387.021 | G4: 85.387 | H4: 0.91 | I4: 5 | J4: 0.09 | K4: 1 | L4: 2313 | M4: 0.32506111 | N4: 0.33 | O4: 2 | P4: 0.111 | Q4: 1 | R4: 1 | S4: 1 | T4: 1 | U4: 4152 | V4: 1.5389894 | W4: 2697.8744 | X4: 1 | Y4: 333 | Z4: 7.5441776 | AA4: 0.269 | AB4: 2 | AC4: 1.5 | AD4: 2 | AE4: No | AF4: No | AG4: 0 | AH4: 0 | AI4: 0 | AM4: 0 | AN4: 0 | AR4: 0 | AX4: Row Labels | AY4: Sum of HESReportTable.CLM $ Collected | AZ4: Sum of HESReportTable.Incentive Disbursements | BA4: Sum of HESReportTable.HES Total Units | BB4: Sum of HESReportTable.Incentives | BC4: Sum of HESReportTable.HESIE Total Units | BD4: Sum of HESReportTable.HESIE Incentives | BF4: 1 | BG4: 1233439.3 | BH4: 355917.5 | BI4: 315 | BJ4: 256816.2 | BK4: 37 | BL4: 96701.3
A5: 1400000US09001060100 | B5: 9001060100 | C5: Census Tract 601, Fairfield County, Connecticut | D5: 139000 | E5: 2.65 | F5: 85387.021 | G5: 85.387 | H5: 0.91 | I5: 5 | J5: 0.09 | K5: 1 | L5: 2313 | M5: 0.32506111 | N5: 0.33 | O5: 2 | P5: 0.111 | Q5: 1 | R5: 1 | S5: 1 | T5: 1 | U5: 4152 | V5: 1.5389894 | W5: 2697.8744 | X5: 1 | Y5: 333 | Z5: 7.5441776 | AA5: 0.269 | AB5: 2 | AC5: 1.5 | AD5: 2 | AE5: No | AF5: No | AG5: 58128.329 | AH5: 19857.8 | AI5: 16 | AJ5: 15 | AK5: 1 | AL5: 0 | AM5: 15652.21 | AN5: 2 | AO5: 2 | AP5: 0 | AQ5: 0 | AR5: 4205.59 | AX5: 9001055100 | AY5: 394.428 | AZ5: 0 | BA5: 0 | BB5: 0 | BC5: 0 | BD5: 0 | BF5: 2 | BG5: 1849524.4 | BH5: 641461.43 | BI5: 541 | BJ5: 476590.31 | BK5: 99 | BL5: 156221.12
A6: 1400000US09001060100 | B6: 9001060100 | C6: Census Tract 601, Fairfield County, Connecticut | D6: 139000 | E6: 2.65 | F6: 85387.021 | G6: 85.387 | H6: 0.91 | I6: 5 | J6: 0.09 | K6: 1 | L6: 2313 | M6: 0.32506111 | N6: 0.33 | O6: 2 | P6: 0.111 | Q6: 1 | R6: 1 | S6: 1 | T6: 1 | U6: 4152 | V6: 1.5389894 | W6: 2697.8744 | X6: 1 | Y6: 333 | Z6: 7.5441776 | AA6: 0.269 | AB6: 2 | AC6: 1.5 | AD6: 2 | AE6: No | AF6: No | AG6: 0 | AH6: 0 | AI6: 0 | AM6: 0 | AN6: 0 | AR6: 0 | AX6: 9001055200 | AY6: 887.5106 | AZ6: 0 | BA6: 0 | BB6: 0 | BC6: 0 | BD6: 0 | BF6: 3 | BG6: 3153797.1 | BH6: 1288734.7 | BI6: 924 | BJ6: 705952.43 | BK6: 273 | BL6: 357722.25
A7: 1400000US09001060200 | B7: 9001060200 | C7: Census Tract 602, Fairfield County, Connecticut | D7: 126838 | E7: 2.81 | F7: 75665.207 | G7: 75.665 | H7: 0.855 | I7: 5 | J7: 0.145 | K7: 1 | L7: 2452 | M7: 0.38887094 | N7: 0.659 | O7: 4 | P7: 0.082 | Q7: 1 | R7: 1 | S7: 1 | T7: 1 | U7: 4164 | V7: 1.5648428 | W7: 2660.9702 | X7: 1 | Y7: 523 | Z7: 11.992662 | AA7: 0.491 | AB7: 3 | AC7: 2 | AD7: 2 | AE7: No | AF7: No | AG7: 78630.955 | AH7: 29656.58 | AI7: 26 | AJ7: 26 | AK7: 0 | AL7: 0 | AM7: 20186.77 | AN7: 3 | AO7: 3 | AP7: 0 | AQ7: 0 | AR7: 9469.81 | AX7: 9001060100 | AY7: 58128.329 | AZ7: 19857.8 | BA7: 16 | BB7: 15652.21 | BC7: 2 | BD7: 4205.59 | BF7: 4 | BG7: 2680511.7 | BH7: 1554367.5 | BI7: 604 | BJ7: 407795.79 | BK7: 365 | BL7: 1136526.7
A8: 1400000US09001060300 | B8: 9001060300 | C8: Census Tract 603, Fairfield County, Connecticut | D8: 195250 | E8: 2.92 | F8: 114261.42 | G8: 114.261 | H8: 0.965 | I8: 5 | J8: 0.035 | K8: 1 | L8: 3341 | M8: 0.35087959 | N8: 0.484 | O8: 3 | P8: 0.03 | Q8: 1 | R8: 1 | S8: 1 | T8: 1 | U8: 4088 | V8: 4.5106101 | W8: 906.30755 | X8: 1 | Y8: 260 | Z8: 6.5689742 | AA8: 0.221 | AB8: 2 | AC8: 1.5 | AD8: 2 | AE8: No | AF8: No | AG8: 92872.917 | AH8: 19540.71 | AI8: 15 | AJ8: 15 | AK8: 0 | AL8: 0 | AM8: 11061.91 | AN8: 2 | AO8: 2 | AP8: 0 | AQ8: 0 | AR8: 8478.8 | AX8: 9001060200 | AY8: 78630.955 | AZ8: 29656.58 | BA8: 26 | BB8: 20186.77 | BC8: 3 | BD8: 9469.81 | BF8: 5 | BG8: 3212520.4 | BH8: 1176273.2 | BI8: 543 | BJ8: 310393.14 | BK8: 730 | BL8: 846505.08
A9: 1400000US09001060400 | B9: 9001060400 | C9: Census Tract 604, Fairfield County, Connecticut | D9: 247169 | E9: 2.83 | F9: 146926.72 | G9: 146.927 | H9: 1 | I9: 5 | J9: 0 | K9: 0 | L9: 3810 | M9: 0.31117553 | N9: 0.229 | O9: 2 | P9: 0.014 | Q9: 1 | R9: 1 | S9: 1 | T9: 1 | U9: 4443 | V9: 8.6430864 | W9: 514.05248 | X9: 1 | Y9: 233 | Z9: 5.1548673 | AA9: 0.144 | AB9: 1 | AC9: 1 | AD9: 1 | AE9: No | AF9: No | AG9: 158569.58 | AH9: 16361.63 | AI9: 15 | AJ9: 15 | AK9: 0 | AL9: 0 | AM9: 16361.63 | AN9: 0 | AR9: 0 | AX9: 9001060300 | AY9: 92872.917 | AZ9: 19540.71 | BA9: 15 | BB9: 11061.91 | BC9: 2 | BD9: 8478.8
A10: 1400000US09001060500 | B10: 9001060500 | C10: Census Tract 605, Fairfield County, Connecticut | D10: 216500 | E10: 3.17 | F10: 121598.51 | G10: 121.599 | H10: 0.973 | I10: 5 | J10: 0.027 | K10: 1 | L10: 3418 | M10: 0.33730675 | N10: 0.407 | O10: 3 | P10: 0.026 | Q10: 1 | R10: 1 | S10: 1 | T10: 1 | U10: 2841 | V10: 2.1100526 | W10: 1346.4119 | X10: 1 | Y10: 162 | Z10: 5.865315 | AA10: 0.182 | AB10: 1 | AC10: 1 | AD10: 1 | AE10: No | AF10: No | AG10: 71345.135 | AH10: 7351.8 | AI10: 13 | AJ10: 13 | AK10: 0 | AL10: 0 | AM10: 7351.8 | AN10: 0 | AR10: 0 | AX10: 9001060400 | AY10: 158569.58 | AZ10: 16361.63 | BA10: 15 | BB10: 16361.63 | BC10: 0 | BD10: 0
A11: 1400000US09001060600 | B11: 9001060600 | C11: Census Tract 606, Fairfield County, Connecticut | D11: 174712 | E11: 2.24 | F11: 116734.37 | G11: 116.734 | H11: 0.969 | I11: 5 | J11: 0.031 | K11: 1 | L11: 2525 | M11: 0.25956367 | N11: 0.032 | O11: 1 | P11: 0.075 | Q11: 1 | R11: 1 | S11: 1 | T11: 1 | U11: 2336 | V11: 1.1912198 | W11: 1961.0151 | X11: 1 | Y11: 212 | Z11: 9.1934085 | AA11: 0.361 | AB11: 2 | AC11: 1.5 | AD11: 2 | AE11: No | AF11: No | AG11: 73188.417 | AH11: 6296 | AI11: 9 | AJ11: 9 | AK11: 0 | AL11: 0 | AM11: 6296 | AN11: 0 | AR11: 0 | AX11: 9001060500 | AY11: 71345.135 | AZ11: 7351.8 | BA11: 13 | BB11: 7351.8 | BC11: 0 | BD11: 0
A12: 1400000US09001060700 | B12: 9001060700 | C12: Census Tract 607, Fairfield County, Connecticut | D12: 180694 | E12: 3.01 | F12: 104150.29 | G12: 104.15 | H12: 0.953 | I12: 5 | J12: 0.047 | K12: 1 | L12: 2864 | M12: 0.32998468 | N12: 0.358 | O12: 2 | P12: 0.05 | Q12: 1 | R12: 1 | S12: 1 | T12: 1 | U12: 7675 | V12: 2.0484516 | W12: 3746.7325 | X12: 1 | Y12: 575 | Z12: 7.2037083 | AA12: 0.251 | AB12: 2 | AC12: 1.5 | AD12: 2 | AE12: No | AF12: No | AG12: 98856.621 | AH12: 8336.04 | AI12: 15 | AJ12: 15 | AK12: 0 | AL12: 0 | AM12: 8336.04 | AN12: 0 | AR12: 0 | AX12: 9001060600 | AY12: 73188.417 | AZ12: 6296 | BA12: 9 | BB12: 6296 | BC12: 0 | BD12: 0
A13: 1400000US09001060800 | B13: 9001060800 | C13: Census Tract 608, Fairfield County, Connecticut | D13: 171250 | E13: 2.73 | F13: 103645.21 | G13: 103.645 | H13: 0.952 | I13: 5 | J13: 0.048 | K13: 1 | L13: 3043 | M13: 0.35231728 | N13: 0.492 | O13: 3 | P13: 0.044 | Q13: 1 | R13: 1 | S13: 1 | T13: 1 | U13: 2139 | V13: 0.54970564 | W13: 3891.1735 | X13: 1 | Y13: 154 | Z13: 7.3020389 | AA13: 0.256 | AB13: 2 | AC13: 1.5 | AD13: 2 | AE13: No | AF13: No | AG13: 39085.891 | AH13: 4387.52 | AI13: 7 | AJ13: 7 | AK13: 0 | AL13: 0 | AM13: 4254.42 | AN13: 1 | AO13: 1 | AP13: 0 | AQ13: 0 | AR13: 133.1 | AX13: 9001060700 | AY13: 98856.621 | AZ13: 8336.04 | BA13: 15 | BB13: 8336.04 | BC13: 0 | BD13: 0
A14: 1400000US09001060900 | B14: 9001060900 | C14: Census Tract 609, Fairfield County, Connecticut | D14: 140278 | E14: 2.88 | F14: 82659.604 | G14: 82.66 | H14: 0.896 | I14: 5 | J14: 0.104 | K14: 1 | L14: 2698 | M14: 0.39167862 | N14: 0.667 | O14: 4 | P14: 0.059 | Q14: 1 | R14: 1 | S14: 1 | T14: 1 | U14: 2447 | V14: 0.57765634 | W14: 4236.0826 | X14: 1 | Y14: 128 | Z14: 4.8338369 | AA14: 0.133 | AB14: 1 | AC14: 1 | AD14: 1 | AE14: No | AF14: No | AG14: 48889.4 | AH14: 30036.3 | AI14: 13 | AJ14: 13 | AK14: 0 | AL14: 0 | AM14: 10016.58 | AN14: 1 | AO14: 1 | AP14: 0 | AQ14: 0 | AR14: 20019.72 | AX14: 9001060800 | AY14: 39085.891 | AZ14: 4387.52 | BA14: 7 | BB14: 4254.42 | BC14: 1 | BD14: 133.1 | BF14: BIPOC INDEX
A15: 1400000US09001061000 | B15: 9001061000 | C15: Census Tract 610, Fairfield County, Connecticut | D15: 78844 | E15: 2.54 | F15: 49471.126 | G15: 49.471 | H15: 0.461 | I15: 3 | J15: 0.539 | K15: 3 | L15: 1741 | M15: 0.42230695 | N15: 0.734 | O15: 4 | P15: 0.288 | Q15: 2 | R15: 3 | S15: 1 | T15: 1 | U15: 3816 | V15: 1.2856179 | W15: 2968.2225 | X15: 1 | Y15: 547 | Z15: 14.065312 | AA15: 0.572 | AB15: 3 | AC15: 3 | AD15: 3 | AE15: No | AF15: No | AG15: 73580.641 | AH15: 75486.32 | AI15: 17 | AJ15: 17 | AK15: 0 | AL15: 0 | AM15: 14143.73 | AN15: 3 | AO15: 3 | AP15: 0 | AQ15: 0 | AR15: 2267.59 | AX15: 9001060900 | AY15: 48889.4 | AZ15: 30036.3 | BA15: 13 | BB15: 10016.58 | BC15: 1 | BD15: 20019.72 | BF15: 1 | BG15: =BG4/SUM(BG$4:BG$8) -> 0.10168676 | BH15: =BH4/SUM(BH$4:BH$8) -> 0.07094577 | BI15: =BI4/SUM(BI$4:BI$8) -> 0.10761872 | BJ15: =BJ4/SUM(BJ$4:BJ$8) -> 0.11903152 | BK15: =BK4/SUM(BK$4:BK$8) -> 0.024601064 | BL15: =BL4/SUM(BL$4:BL$8) -> 0.037283486
A16: 1400000US09001061100 | B16: 9001061100 | C16: Census Tract 611, Fairfield County, Connecticut | D16: 163438 | E16: 2.99 | F16: 94518.636 | G16: 94.519 | H16: 0.934 | I16: 5 | J16: 0.066 | K16: 1 | L16: 2692 | M16: 0.34177387 | N16: 0.429 | O16: 3 | P16: 0.06 | Q16: 1 | R16: 1 | S16: 1 | T16: 1 | U16: 3771 | V16: 1.0451898 | W16: 3607.9572 | X16: 1 | Y16: 183 | Z16: 4.7631442 | AA16: 0.126 | AB16: 1 | AC16: 1 | AD16: 1 | AE16: No | AF16: No | AG16: 67549.059 | AH16: 4173.07 | AI16: 12 | AJ16: 12 | AK16: 0 | AL16: 0 | AM16: 4173.07 | AN16: 0 | AR16: 0 | AX16: 9001061000 | AY16: 73580.641 | AZ16: 75486.32 | BA16: 17 | BB16: 14143.73 | BC16: 3 | BD16: 2267.59 | BF16: 2 | BG16: =BG5/SUM(BG$4:BG$8) -> 0.15247782 | BH16: =BH5/SUM(BH$4:BH$8) -> 0.12786383 | BI16: =BI5/SUM(BI$4:BI$8) -> 0.18483088 | BJ16: =BJ5/SUM(BJ$4:BJ$8) -> 0.22089443 | BK16: =BK5/SUM(BK$4:BK$8) -> 0.065824468 | BL16: =BL5/SUM(BL$4:BL$8) -> 0.060231537
A17: 1400000US09001061200 | B17: 9001061200 | C17: Census Tract 612, Fairfield County, Connecticut | D17: 81667 | E17: 2.88 | F17: 48122.741 | G17: 48.123 | H17: 0.433 | I17: 3 | J17: 0.567 | K17: 3 | L17: 1853 | M17: 0.46206844 | N17: 0.801 | O17: 5 | P17: 0.23 | Q17: 2 | R17: 3 | S17: 1 | T17: 1 | U17: 2186 | V17: 0.30555701 | W17: 7154.1477 | X17: 1 | Y17: 661 | Z17: 26.397764 | AA17: 0.844 | AB17: 5 | AC17: 4 | AD17: 4 | AE17: No | AF17: No | AG17: 35405.152 | AH17: 19213.03 | AI17: 12 | AJ17: 9 | AK17: 3 | AL17: 0 | AM17: 5648.47 | AN17: 1 | AO17: 1 | AP17: 0 | AQ17: 0 | AR17: 13564.56 | AX17: 9001061100 | AY17: 67549.059 | AZ17: 4173.07 | BA17: 12 | BB17: 4173.07 | BC17: 0 | BD17: 0 | BF17: 3 | BG17: =BG6/SUM(BG$4:BG$8) -> 0.2600042 | BH17: =BH6/SUM(BH$4:BH$8) -> 0.25688614 | BI17: =BI6/SUM(BI$4:BI$8) -> 0.31568159 | BJ17: =BJ6/SUM(BJ$4:BJ$8) -> 0.32720128 | BK17: =BK6/SUM(BK$4:BK$8) -> 0.18151596 | BL17: =BL6/SUM(BL$4:BL$8) -> 0.13792092
A18: 1400000US09001061300 | B18: 9001061300 | C18: Census Tract 613, Fairfield County, Connecticut | D18: 90913 | E18: 2.74 | F18: 54922.552 | G18: 54.923 | H18: 0.557 | I18: 3 | J18: 0.443 | K18: 3 | L18: 1857 | M18: 0.40573497 | N18: 0.692 | O18: 4 | P18: 0.229 | Q18: 2 | R18: 3 | S18: 1 | T18: 1 | U18: 2954 | V18: 0.48268332 | W18: 6119.9546 | X18: 1 | Y18: 571 | Z18: 18.366034 | AA18: 0.699 | AB18: 4 | AC18: 3.5 | AD18: 4 | AE18: No | AF18: No | AG18: 51750.384 | AH18: 7224.19 | AI18: 9 | AJ18: 8 | AK18: 1 | AL18: 0 | AM18: 4853.85 | AN18: 3 | AO18: 3 | AP18: 0 | AQ18: 0 | AR18: 2370.34 | AX18: 9001061200 | AY18: 35405.152 | AZ18: 19213.03 | BA18: 12 | BB18: 5648.47 | BC18: 1 | BD18: 13564.56 | BF18: 4 | BG18: =BG7/SUM(BG$4:BG$8) -> 0.22098578 | BH18: =BH7/SUM(BH$4:BH$8) -> 0.30983528 | BI18: =BI7/SUM(BI$4:BI$8) -> 0.20635463 | BJ18: =BJ7/SUM(BJ$4:BJ$8) -> 0.18900892 | BK18: =BK7/SUM(BK$4:BK$8) -> 0.24268617 | BL18: =BL7/SUM(BL$4:BL$8) -> 0.4381914
A19: 1400000US09001061400 | B19: 9001061400 | C19: Census Tract 614, Fairfield County, Connecticut | D19: 91467 | E19: 2.6 | F19: 56725.425 | G19: 56.725 | H19: 0.594 | I19: 3 | J19: 0.406 | K19: 3 | L19: 1873 | M19: 0.39622444 | N19: 0.677 | O19: 4 | P19: 0.219 | Q19: 2 | R19: 3 | S19: 1 | T19: 1 | U19: 2736 | V19: 0.62377084 | W19: 4386.2262 | X19: 1 | Y19: 858 | Z19: 27.86619 | AA19: 0.864 | AB19: 5 | AC19: 4 | AD19: 4 | AE19: No | AF19: No | AG19: 47281.252 | AH19: 5299.19 | AI19: 6 | AJ19: 5 | AK19: 1 | AL19: 0 | AM19: 3377.69 | AN19: 2 | AO19: 2 | AP19: 0 | AQ19: 0 | AR19: 1921.5 | AX19: 9001061300 | AY19: 51750.384 | AZ19: 7224.19 | BA19: 9 | BB19: 4853.85 | BC19: 3 | BD19: 2370.34 | BF19: 5 | BG19: =BG8/SUM(BG$4:BG$8) -> 0.26484544 | BH19: =BH8/SUM(BH$4:BH$8) -> 0.23446897 | BI19: =BI8/SUM(BI$4:BI$8) -> 0.18551418 | BJ19: =BJ8/SUM(BJ$4:BJ$8) -> 0.14386385 | BK19: =BK8/SUM(BK$4:BK$8) -> 0.48537234 | BL19: =BL8/SUM(BL$4:BL$8) -> 0.32637266
A20: 1400000US09001061500 | B20: 9001061500 | C20: Census Tract 615, Fairfield County, Connecticut | D20: 148804 | E20: 2.76 | F20: 89569.482 | G20: 89.569 | H20: 0.923 | I20: 5 | J20: 0.077 | K20: 1 | L20: 2670 | M20: 0.35771112 | N20: 0.52 | O20: 3 | P20: 0.063 | Q20: 1 | R20: 1 | S20: 1 | T20: 1 | U20: 4692 | V20: 1.4069876 | W20: 3334.7842 | X20: 1 | Y20: 854 | Z20: 17.659222 | AA20: 0.68 | AB20: 4 | AC20: 2.5 | AD20: 3 | AE20: No | AF20: No | AG20: 0 | AH20: 0 | AI20: 0 | AM20: 0 | AN20: 0 | AR20: 0 | AX20: 9001061400 | AY20: 47281.252 | AZ20: 5299.19 | BA20: 6 | BB20: 3377.69 | BC20: 2 | BD20: 1921.5
A21: 1400000US09001061500 | B21: 9001061500 | C21: Census Tract 615, Fairfield County, Connecticut | D21: 148804 | E21: 2.76 | F21: 89569.482 | G21: 89.569 | H21: 0.923 | I21: 5 | J21: 0.077 | K21: 1 | L21: 2670 | M21: 0.35771112 | N21: 0.52 | O21: 3 | P21: 0.063 | Q21: 1 | R21: 1 | S21: 1 | T21: 1 | U21: 4692 | V21: 1.4069876 | W21: 3334.7842 | X21: 1 | Y21: 854 | Z21: 17.659222 | AA21: 0.68 | AB21: 4 | AC21: 2.5 | AD21: 3 | AE21: No | AF21: No | AG21: 104123.37 | AH21: 13917.12 | AI21: 18 | AJ21: 18 | AK21: 0 | AL21: 0 | AM21: 8101.4 | AN21: 4 | AO21: 4 | AP21: 0 | AQ21: 0 | AR21: 5815.72 | AX21: 9001061500 | AY21: 104123.37 | AZ21: 13917.12 | BA21: 18 | BB21: 8101.4 | BC21: 4 | BD21: 5815.72
A22: 1400000US09001061600 | B22: 9001061600 | C22: Census Tract 616, Fairfield County, Connecticut | D22: 129250 | E22: 2.57 | F22: 80623.935 | G22: 80.624 | H22: 0.883 | I22: 5 | J22: 0.117 | K22: 1 | L22: 2370 | M22: 0.35274885 | N22: 0.495 | O22: 3 | P22: 0.094 | Q22: 1 | R22: 1 | S22: 1 | T22: 1 | U22: 4964 | V22: 2.0182839 | W22: 2459.5153 | X22: 1 | Y22: 323 | Z22: 5.9583103 | AA22: 0.185 | AB22: 1 | AC22: 1 | AD22: 1 | AE22: No | AF22: No | AG22: 114122.91 | AH22: 10431.48 | AI22: 21 | AJ22: 20 | AK22: 1 | AL22: 0 | AM22: 9358.37 | AN22: 2 | AO22: 2 | AP22: 0 | AQ22: 0 | AR22: 1073.11 | AX22: 9001061600 | AY22: 114122.91 | AZ22: 10431.48 | BA22: 21 | BB22: 9358.37 | BC22: 2 | BD22: 1073.11
A23: 1400000US09001070100 | B23: 9001070100 | C23: Census Tract 701, Fairfield County, Connecticut | D23: 88021 | E23: 2.16 | F23: 59890.705 | G23: 59.891 | H23: 0.651 | I23: 4 | J23: 0.349 | K23: 2 | L23: 1489 | M23: 0.29834346 | N23: 0.16 | O23: 1 | P23: 0.49 | Q23: 3 | R23: 3 | S23: 1 | T23: 1 | U23: 5021 | V23: 0.65223159 | W23: 7698.1858 | X23: 1 | Y23: 764 | Z23: 15.384615 | AA23: 0.609 | AB23: 4 | AC23: 3.5 | AD23: 4 | AE23: No | AF23: No | AG23: 0 | AH23: 11088.15 | AI23: 14 | AJ23: 12 | AK23: 2 | AL23: 0 | AM23: 8716.18 | AN23: 5 | AO23: 4 | AP23: 1 | AQ23: 0 | AR23: 2371.97 | AX23: 9001070100 | AY23: 87876.711 | AZ23: 11088.15 | BA23: 14 | BB23: 8716.18 | BC23: 5 | BD23: 2371.97 | BF23: Income <= 80% SMI | BG23: Sum of HESReportTable.CLM $ Collected | BH23: Sum of HESReportTable.Incentive Disbursements | BI23: Sum of HESReportTable.HES Total Units | BJ23: Sum of HESReportTable.Incentives | BK23: Sum of HESReportTable.HESIE Total Units | BL23: Sum of HESReportTable.HESIE Incentives
A24: 1400000US09001070100 | B24: 9001070100 | C24: Census Tract 701, Fairfield County, Connecticut | D24: 88021 | E24: 2.16 | F24: 59890.705 | G24: 59.891 | H24: 0.651 | I24: 4 | J24: 0.349 | K24: 2 | L24: 1489 | M24: 0.29834346 | N24: 0.16 | O24: 1 | P24: 0.49 | Q24: 3 | R24: 3 | S24: 1 | T24: 1 | U24: 5021 | V24: 0.65223159 | W24: 7698.1858 | X24: 1 | Y24: 764 | Z24: 15.384615 | AA24: 0.609 | AB24: 4 | AC24: 3.5 | AD24: 4 | AE24: No | AF24: No | AG24: 87876.711 | AH24: 0 | AI24: 0 | AM24: 0 | AN24: 0 | AR24: 0 | AX24: 9001070200 | AY24: 45704.852 | AZ24: 2977.59 | BA24: 8 | BB24: 1549.83 | BC24: 8 | BD24: 1427.76 | BF24: No | BG24: 8556139.3 | BH24: 3529907.5 | BI24: 2478 | BJ24: 1932663.6 | BK24: 606 | BL24: 1361674
A25: 1400000US09001070200 | B25: 9001070200 | C25: Census Tract 702, Fairfield County, Connecticut | D25: 42688 | E25: 2.37 | F25: 27728.836 | G25: 27.729 | H25: 0.139 | I25: 1 | J25: 0.861 | K25: 5 | L25: 1292 | M25: 0.55912914 | N25: 0.897 | O25: 5 | P25: 0.662 | Q25: 4 | R25: 5 | S25: 1 | T25: 1 | U25: 4052 | V25: 0.32567255 | W25: 12441.945 | X25: 1 | Y25: 665 | Z25: 17.139175 | AA25: 0.661 | AB25: 4 | AC25: 4.5 | AD25: 5 | AE25: Yes | AF25: Yes | AG25: 0 | AH25: 2227.93 | AI25: 7 | AJ25: 7 | AK25: 0 | AL25: 0 | AM25: 800.17 | AN25: 8 | AO25: 4 | AP25: 4 | AQ25: 0 | AR25: 1427.76 | AX25: 9001070300 | AY25: 16956.724 | AZ25: 202635.3 | BA25: 0 | BB25: 0 | BC25: 2 | BD25: 202635.3 | BF25: Yes | BG25: 3573653.6 | BH25: 1486846.8 | BI25: 449 | BJ25: 224884.29 | BK25: 898 | BL25: 1232002.5
A26: 1400000US09001070200 | B26: 9001070200 | C26: Census Tract 702, Fairfield County, Connecticut | D26: 42688 | E26: 2.37 | F26: 27728.836 | G26: 27.729 | H26: 0.139 | I26: 1 | J26: 0.861 | K26: 5 | L26: 1292 | M26: 0.55912914 | N26: 0.897 | O26: 5 | P26: 0.662 | Q26: 4 | R26: 5 | S26: 1 | T26: 1 | U26: 4052 | V26: 0.32567255 | W26: 12441.945 | X26: 1 | Y26: 665 | Z26: 17.139175 | AA26: 0.661 | AB26: 4 | AC26: 4.5 | AD26: 5 | AE26: Yes | AF26: Yes | AG26: 45704.852 | AH26: 0 | AI26: 0 | AM26: 0 | AN26: 0 | AR26: 0 | AX26: 9001070400 | AY26: 17917.036 | AZ26: 1029.53 | BA26: 3 | BB26: 380.24 | BC26: 6 | BD26: 649.29
A27: 1400000US09001070200 | B27: 9001070200 | C27: Census Tract 702, Fairfield County, Connecticut | D27: 42688 | E27: 2.37 | F27: 27728.836 | G27: 27.729 | H27: 0.139 | I27: 1 | J27: 0.861 | K27: 5 | L27: 1292 | M27: 0.55912914 | N27: 0.897 | O27: 5 | P27: 0.662 | Q27: 4 | R27: 5 | S27: 1 | T27: 1 | U27: 4052 | V27: 0.32567255 | W27: 12441.945 | X27: 1 | Y27: 665 | Z27: 17.139175 | AA27: 0.661 | AB27: 4 | AC27: 4.5 | AD27: 5 | AE27: Yes | AF27: Yes | AG27: 0 | AH27: 749.66 | AI27: 1 | AJ27: 1 | AK27: 0 | AL27: 0 | AM27: 749.66 | AN27: 0 | AR27: 0 | AX27: 9001070500 | AY27: 23101.569 | AZ27: 359.75 | BA27: 0 | BB27: 75 | BC27: 7 | BD27: 284.75
A28: 1400000US09001070300 | B28: 9001070300 | C28: Census Tract 703, Fairfield County, Connecticut | D28: 9958 | E28: 3.24 | F28: 5532.2222 | G28: 5.532 | H28: 0.001 | I28: 1 | J28: 0.999 | K28: 5 | L28: 433 | M28: 0.93922474 | N28: 0.993 | O28: 5 | P28: 1 | Q28: 5 | R28: 5 | S28: 1 | T28: 1 | U28: 1297 | V28: 0.41493629 | W28: 3125.7811 | X28: 1 | Y28: 282 | Z28: 20.317003 | AA28: 0.743 | AB28: 4 | AC28: 4.5 | AD28: 5 | AE28: Yes | AF28: Yes | AG28: 0 | AH28: 202635.3 | AI28: 0 | AM28: 0 | AN28: 2 | AO28: 0 | AP28: 1 | AQ28: 1 | AR28: 202635.3 | AX28: 9001070600 | AY28: 35967.757 | AZ28: 96774.69 | BA28: 0 | BB28: 0 | BC28: 4 | BD28: 96774.69 | BF28: No | BG28: =BG24/SUM(BG$24:BG$25) -> 0.70538214 | BH28: =BH24/SUM(BH$24:BH$25) -> 0.70362376 | BI28: =BI24/SUM(BI$24:BI$25) -> 0.84660061 | BJ28: =BJ24/SUM(BJ$24:BJ$25) -> 0.89576857 | BK28: =BK24/SUM(BK$24:BK$25) -> 0.40292553 | BL28: =BL24/SUM(BL$24:BL$25) -> 0.52499762
A29: 1400000US09001070300 | B29: 9001070300 | C29: Census Tract 703, Fairfield County, Connecticut | D29: 9958 | E29: 3.24 | F29: 5532.2222 | G29: 5.532 | H29: 0.001 | I29: 1 | J29: 0.999 | K29: 5 | L29: 433 | M29: 0.93922474 | N29: 0.993 | O29: 5 | P29: 1 | Q29: 5 | R29: 5 | S29: 1 | T29: 1 | U29: 1297 | V29: 0.41493629 | W29: 3125.7811 | X29: 1 | Y29: 282 | Z29: 20.317003 | AA29: 0.743 | AB29: 4 | AC29: 4.5 | AD29: 5 | AE29: Yes | AF29: Yes | AG29: 16956.724 | AH29: 0 | AI29: 0 | AM29: 0 | AN29: 0 | AR29: 0 | AX29: 9001070900 | AY29: 29174.959 | AZ29: 4170.01 | BA29: 1 | BB29: 1302.6 | BC29: 12 | BD29: 2867.41 | BF29: Yes | BG29: =BG25/SUM(BG$24:BG$25) -> 0.29461786 | BH29: =BH25/SUM(BH$24:BH$25) -> 0.29637624 | BI29: =BI25/SUM(BI$24:BI$25) -> 0.15339939 | BJ29: =BJ25/SUM(BJ$24:BJ$25) -> 0.10423143 | BK29: =BK25/SUM(BK$24:BK$25) -> 0.59707447 | BL29: =BL25/SUM(BL$24:BL$25) -> 0.47500238
A30: 1400000US09001070400 | B30: 9001070400 | C30: Census Tract 704, Fairfield County, Connecticut | D30: 35313 | E30: 1.86 | F30: 25892.748 | G30: 25.893 | H30: 0.122 | I30: 1 | J30: 0.878 | K30: 5 | L30: 912 | M30: 0.42266661 | N30: 0.738 | O30: 4 | P30: 0.969 | Q30: 5 | R30: 5 | S30: 1 | T30: 1 | U30: 1693 | V30: 0.6728259 | W30: 2516.2527 | X30: 1 | Y30: 429 | Z30: 28.986486 | AA30: 0.868 | AB30: 5 | AC30: 5 | AD30: 5 | AE30: Yes | AF30: Yes | AG30: 0 | AH30: 1029.53 | AI30: 3 | AJ30: 3 | AK30: 0 | AL30: 0 | AM30: 380.24 | AN30: 6 | AO30: 2 | AP30: 4 | AQ30: 0 | AR30: 649.29 | AX30: 9001071000 | AY30: 37249.349 | AZ30: 14379.5 | BA30: 1 | BB30: 118.52 | BC30: 17 | BD30: 14260.98
A31: 1400000US09001070400 | B31: 9001070400 | C31: Census Tract 704, Fairfield County, Connecticut | D31: 35313 | E31: 1.86 | F31: 25892.748 | G31: 25.893 | H31: 0.122 | I31: 1 | J31: 0.878 | K31: 5 | L31: 912 | M31: 0.42266661 | N31: 0.738 | O31: 4 | P31: 0.969 | Q31: 5 | R31: 5 | S31: 1 | T31: 1 | U31: 1693 | V31: 0.6728259 | W31: 2516.2527 | X31: 1 | Y31: 429 | Z31: 28.986486 | AA31: 0.868 | AB31: 5 | AC31: 5 | AD31: 5 | AE31: Yes | AF31: Yes | AG31: 17866.172 | AH31: 0 | AI31: 0 | AM31: 0 | AN31: 0 | AR31: 0 | AX31: 9001071100 | AY31: 51783.79 | AZ31: 21423.83 | BA31: 5 | BB31: 1246.62 | BC31: 19 | BD31: 20177.21
A32: 1400000US09001070400 | B32: 9001070400 | C32: Census Tract 704, Fairfield County, Connecticut | D32: 35313 | E32: 1.86 | F32: 25892.748 | G32: 25.893 | H32: 0.122 | I32: 1 | J32: 0.878 | K32: 5 | L32: 912 | M32: 0.42266661 | N32: 0.738 | O32: 4 | P32: 0.969 | Q32: 5 | R32: 5 | S32: 1 | T32: 1 | U32: 1693 | V32: 0.6728259 | W32: 2516.2527 | X32: 1 | Y32: 429 | Z32: 28.986486 | AA32: 0.868 | AB32: 5 | AC32: 5 | AD32: 5 | AE32: Yes | AF32: Yes | AG32: 50.8641 | AH32: 0 | AI32: 0 | AM32: 0 | AN32: 0 | AR32: 0 | AX32: 9001071200 | AY32: 45169.658 | AZ32: 4593.86 | BA32: 2 | BB32: 954.34 | BC32: 21 | BD32: 3639.52
A33: 1400000US09001070500 | B33: 9001070500 | C33: Census Tract 705, Fairfield County, Connecticut | D33: 24342 | E33: 2.52 | F33: 15334.019 | G33: 15.334 | H33: 0.02 | I33: 1 | J33: 0.98 | K33: 5 | L33: 1275 | M33: 0.99778149 | N33: 0.996 | O33: 5 | P33: 0.681 | Q33: 4 | R33: 5 | S33: 1 | T33: 1 | U33: 2801 | V33: 0.14780223 | W33: 18951 | X33: 1 | Y33: 597 | Z33: 32.183288 | AA33: 0.91 | AB33: 5 | AC33: 5 | AD33: 5 | AE33: Yes | AF33: Yes | AG33: 0 | AH33: 359.75 | AI33: 0 | AM33: 75 | AN33: 7 | AO33: 0 | AP33: 7 | AQ33: 0 | AR33: 284.75 | AX33: 9001071300 | AY33: 34389.421 | AZ33: 1572.32 | BA33: 1 | BB33: 12.03 | BC33: 12 | BD33: 1560.29 | BF33: Income <= 60% SMI
A34: 1400000US09001070500 | B34: 9001070500 | C34: Census Tract 705, Fairfield County, Connecticut | D34: 24342 | E34: 2.52 | F34: 15334.019 | G34: 15.334 | H34: 0.02 | I34: 1 | J34: 0.98 | K34: 5 | L34: 1275 | M34: 0.99778149 | N34: 0.996 | O34: 5 | P34: 0.681 | Q34: 4 | R34: 5 | S34: 1 | T34: 1 | U34: 2801 | V34: 0.14780223 | W34: 18951 | X34: 1 | Y34: 597 | Z34: 32.183288 | AA34: 0.91 | AB34: 5 | AC34: 5 | AD34: 5 | AE34: Yes | AF34: Yes | AG34: 23101.569 | AH34: 0 | AI34: 0 | AM34: 0 | AN34: 0 | AR34: 0 | AX34: 9001071400 | AY34: 38432.276 | AZ34: 3327.16 | BA34: 2 | BB34: 927.04 | BC34: 15 | BD34: 2400.12 | BF34: No | BG34: 10030582 | BH34: 4208394.9 | BI34: 2717 | BJ34: 2055698.2 | BK34: 932 | BL34: 1926291.7
A35: 1400000US09001070600 | B35: 9001070600 | C35: Census Tract 706, Fairfield County, Connecticut | D35: 23598 | E35: 1.57 | F35: 18833.254 | G35: 18.833 | H35: 0.048 | I35: 1 | J35: 0.952 | K35: 5 | L35: 974 | M35: 0.62060437 | N35: 0.933 | O35: 5 | P35: 0.952 | Q35: 5 | R35: 5 | S35: 1 | T35: 1 | U35: 2445 | V35: 0.6903588 | W35: 3541.6366 | X35: 1 | Y35: 525 | Z35: 20.539906 | AA35: 0.753 | AB35: 4 | AC35: 4.5 | AD35: 5 | AE35: Yes | AF35: Yes | AG35: 0 | AH35: 96774.69 | AI35: 0 | AM35: 0 | AN35: 4 | AO35: 1 | AP35: 1 | AQ35: 2 | AR35: 96774.69 | AX35: 9001071600 | AY35: 24529.813 | AZ35: 1330.85 | BA35: 0 | BB35: 0 | BC35: 8 | BD35: 1330.85 | BF35: Yes | BG35: 2099211.1 | BH35: 808359.4 | BI35: 210 | BJ35: 101849.64 | BK35: 572 | BL35: 667384.76
A36: 1400000US09001070600 | B36: 9001070600 | C36: Census Tract 706, Fairfield County, Connecticut | D36: 23598 | E36: 1.57 | F36: 18833.254 | G36: 18.833 | H36: 0.048 | I36: 1 | J36: 0.952 | K36: 5 | L36: 974 | M36: 0.62060437 | N36: 0.933 | O36: 5 | P36: 0.952 | Q36: 5 | R36: 5 | S36: 1 | T36: 1 | U36: 2445 | V36: 0.6903588 | W36: 3541.6366 | X36: 1 | Y36: 525 | Z36: 20.539906 | AA36: 0.753 | AB36: 4 | AC36: 4.5 | AD36: 5 | AE36: Yes | AF36: Yes | AG36: 35967.757 | AH36: 0 | AI36: 0 | AM36: 0 | AN36: 0 | AR36: 0 | AX36: 9001071900 | AY36: 46534.636 | AZ36: 3620.23 | BA36: 2 | BB36: 404.3 | BC36: 11 | BD36: 3215.93
A37: 1400000US09001070900 | B37: 9001070900 | C37: Census Tract 709, Fairfield County, Connecticut | D37: 35492 | E37: 3.1 | F37: 20158.101 | G37: 20.158 | H37: 0.06 | I37: 1 | J37: 0.94 | K37: 5 | L37: 1228 | M37: 0.73102123 | N37: 0.972 | O37: 5 | P37: 0.739 | Q37: 4 | R37: 5 | S37: 1 | T37: 1 | U37: 2584 | V37: 0.17075678 | W37: 15132.635 | X37: 1 | Y37: 888 | Z37: 30.769231 | AA37: 0.894 | AB37: 5 | AC37: 5 | AD37: 5 | AE37: Yes | AF37: Yes | AG37: 0 | AH37: 4170.01 | AI37: 1 | AJ37: 0 | AK37: 1 | AL37: 0 | AM37: 1302.6 | AN37: 12 | AO37: 4 | AP37: 8 | AQ37: 0 | AR37: 2867.41 | AX37: 9001072000 | AY37: 43927.02 | AZ37: 19032.27 | BA37: 6 | BB37: 2207.03 | BC37: 21 | BD37: 16825.24
A38: 1400000US09001070900 | B38: 9001070900 | C38: Census Tract 709, Fairfield County, Connecticut | D38: 35492 | E38: 3.1 | F38: 20158.101 | G38: 20.158 | H38: 0.06 | I38: 1 | J38: 0.94 | K38: 5 | L38: 1228 | M38: 0.73102123 | N38: 0.972 | O38: 5 | P38: 0.739 | Q38: 4 | R38: 5 | S38: 1 | T38: 1 | U38: 2584 | V38: 0.17075678 | W38: 15132.635 | X38: 1 | Y38: 888 | Z38: 30.769231 | AA38: 0.894 | AB38: 5 | AC38: 5 | AD38: 5 | AE38: Yes | AF38: Yes | AG38: 29174.959 | AH38: 0 | AI38: 0 | AM38: 0 | AN38: 0 | AR38: 0 | AX38: 9001072100 | AY38: 120136.23 | AZ38: 44620.47 | BA38: 17 | BB38: 9086.13 | BC38: 35 | BD38: 35534.34 | BF38: No | BG38: =BG34/SUM(BG$34:BG$35) -> 0.8269376 | BH38: =BH34/SUM(BH$34:BH$35) -> 0.83886805 | BI38: =BI34/SUM(BI$34:BI$35) -> 0.92825419 | BJ38: =BJ34/SUM(BJ$34:BJ$35) -> 0.9527938 | BK38: =BK34/SUM(BK$34:BK$35) -> 0.61968085 | BL38: =BL34/SUM(BL$34:BL$35) -> 0.74268774
A39: 1400000US09001071000 | B39: 9001071000 | C39: Census Tract 710, Fairfield County, Connecticut | D39: 48148 | E39: 3.13 | F39: 27214.859 | G39: 27.215 | H39: 0.137 | I39: 1 | J39: 0.863 | K39: 5 | L39: 1323 | M39: 0.5833578 | N39: 0.912 | O39: 5 | P39: 0.632 | Q39: 4 | R39: 5 | S39: 1 | T39: 1 | U39: 3563 | V39: 0.44304143 | W39: 8042.1372 | X39: 1 | Y39: 1168 | Z39: 33.89437 | AA39: 0.925 | AB39: 5 | AC39: 5 | AD39: 5 | AE39: No | AF39: Yes | AG39: 0 | AH39: 14379.5 | AI39: 1 | AJ39: 1 | AK39: 0 | AL39: 0 | AM39: 118.52 | AN39: 17 | AO39: 2 | AP39: 14 | AQ39: 1 | AR39: 14260.98 | AX39: 9001072200 | AY39: 41166.363 | AZ39: 23077.93 | BA39: 19 | BB39: 10983.51 | BC39: 10 | BD39: 12094.42 | BF39: Yes | BG39: =BG35/SUM(BG$34:BG$35) -> 0.1730624 | BH39: =BH35/SUM(BH$34:BH$35) -> 0.16113195 | BI39: =BI35/SUM(BI$34:BI$35) -> 0.071745815 | BJ39: =BJ35/SUM(BJ$34:BJ$35) -> 0.047206202 | BK39: =BK35/SUM(BK$34:BK$35) -> 0.38031915 | BL39: =BL35/SUM(BL$34:BL$35) -> 0.25731226
A40: 1400000US09001071000 | B40: 9001071000 | C40: Census Tract 710, Fairfield County, Connecticut | D40: 48148 | E40: 3.13 | F40: 27214.859 | G40: 27.215 | H40: 0.137 | I40: 1 | J40: 0.863 | K40: 5 | L40: 1323 | M40: 0.5833578 | N40: 0.912 | O40: 5 | P40: 0.632 | Q40: 4 | R40: 5 | S40: 1 | T40: 1 | U40: 3563 | V40: 0.44304143 | W40: 8042.1372 | X40: 1 | Y40: 1168 | Z40: 33.89437 | AA40: 0.925 | AB40: 5 | AC40: 5 | AD40: 5 | AE40: No | AF40: Yes | AG40: 37249.349 | AH40: 0 | AI40: 0 | AM40: 0 | AN40: 0 | AR40: 0 | AX40: 9001072300 | AY40: 62912.309 | AZ40: 15404.49 | BA40: 14 | BB40: 7767.78 | BC40: 11 | BD40: 7636.71
A41: 1400000US09001071100 | B41: 9001071100 | C41: Census Tract 711, Fairfield County, Connecticut | D41: 48500 | E41: 3.58 | F41: 25633.047 | G41: 25.633 | H41: 0.12 | I41: 1 | J41: 0.88 | K41: 5 | L41: 1271 | M41: 0.59501316 | N41: 0.917 | O41: 5 | P41: 0.684 | Q41: 4 | R41: 5 | S41: 1 | T41: 1 | U41: 4576 | V41: 0.25589153 | W41: 17882.577 | X41: 1 | Y41: 1300 | Z41: 26.321118 | AA41: 0.848 | AB41: 5 | AC41: 5 | AD41: 5 | AE41: No | AF41: Yes | AG41: 51783.79 | AH41: 21423.83 | AI41: 5 | AJ41: 4 | AK41: 1 | AL41: 0 | AM41: 1246.62 | AN41: 19 | AO41: 9 | AP41: 10 | AQ41: 0 | AR41: 20177.21 | AX41: 9001072400 | AY41: 38727.082 | AZ41: 29244.41 | BA41: 12 | BB41: 5480.74 | BC41: 8 | BD41: 23763.67
A42: 1400000US09001071200 | B42: 9001071200 | C42: Census Tract 712, Fairfield County, Connecticut | D42: 24271 | E42: 3.01 | F42: 13989.572 | G42: 13.99 | H42: 0.013 | I42: 1 | J42: 0.987 | K42: 5 | L42: 1107 | M42: 0.94956444 | N42: 0.995 | O42: 5 | P42: 0.869 | Q42: 5 | R42: 5 | S42: 1 | T42: 1 | U42: 5205 | V42: 0.21484154 | W42: 24227.159 | X42: 1 | Y42: 1849 | Z42: 33.569354 | AA42: 0.92 | AB42: 5 | AC42: 5 | AD42: 5 | AE42: Yes | AF42: Yes | AG42: 0 | AH42: 4593.86 | AI42: 2 | AJ42: 2 | AK42: 0 | AL42: 0 | AM42: 954.34 | AN42: 21 | AO42: 8 | AP42: 13 | AQ42: 0 | AR42: 3639.52 | AX42: 9001072500 | AY42: 78001.035 | AZ42: 18716.64 | BA42: 31 | BB42: 13275.87 | BC42: 14 | BD42: 5440.77 | BF42: Energy Burdened Census Tracts (N = 34) | BG42: Sum of Sum of Residential CLM $ Collected | BH42: Sum of Sum of Residential Incentive Disbursements | BI42: Sum of HESReportTable.Incentive Disbursements | BJ42: Sum of HESReportTable.HESIE Incentives | BK42: Sum of HESReportTable.HES Total Units | BL42: Sum of HESReportTable.HESIE Total Units
A43: 1400000US09001071200 | B43: 9001071200 | C43: Census Tract 712, Fairfield County, Connecticut | D43: 24271 | E43: 3.01 | F43: 13989.572 | G43: 13.99 | H43: 0.013 | I43: 1 | J43: 0.987 | K43: 5 | L43: 1107 | M43: 0.94956444 | N43: 0.995 | O43: 5 | P43: 0.869 | Q43: 5 | R43: 5 | S43: 1 | T43: 1 | U43: 5205 | V43: 0.21484154 | W43: 24227.159 | X43: 1 | Y43: 1849 | Z43: 33.569354 | AA43: 0.92 | AB43: 5 | AC43: 5 | AD43: 5 | AE43: Yes | AF43: Yes | AG43: 45169.658 | AH43: 0 | AI43: 0 | AM43: 0 | AN43: 0 | AR43: 0 | AX43: 9001072600 | AY43: 118393.07 | AZ43: 43073.09 | BA43: 21 | BB43: 16945 | BC43: 18 | BD43: 26128.09 | BF43: Energy bill >= 6% household income | BG43: 3555328.7 | BH43: 1576141.2 | BI43: 701226.38 | BJ43: 608089.62 | BK43: 138 | BL43: 535
A44: 1400000US09001071300 | B44: 9001071300 | C44: Census Tract 713, Fairfield County, Connecticut | D44: 27072 | E44: 2.39 | F44: 17511.421 | G44: 17.511 | H44: 0.038 | I44: 1 | J44: 0.962 | K44: 5 | L44: 1078 | M44: 0.73871789 | N44: 0.974 | O44: 5 | P44: 0.89 | Q44: 5 | R44: 5 | S44: 1 | T44: 1 | U44: 3030 | V44: 0.11966619 | W44: 25320.435 | X44: 1 | Y44: 664 | Z44: 24.601704 | AA44: 0.817 | AB44: 5 | AC44: 5 | AD44: 5 | AE44: Yes | AF44: Yes | AG44: 0 | AH44: 1572.32 | AI44: 1 | AJ44: 0 | AK44: 1 | AL44: 0 | AM44: 12.03 | AN44: 12 | AO44: 2 | AP44: 10 | AQ44: 0 | AR44: 1560.29 | AX44: 9001072700 | AY44: 60251.686 | AZ44: 47344.93 | BA44: 15 | BB44: 13515.44 | BC44: 22 | BD44: 33829.49 | BF44: Total | BG44: =BG34+BG35 -> 12129793 | BH44: =BH34+BH35 -> 5016754.3 | BI44: =BJ24+BJ25 -> 2157547.9 | BJ44: =BL24+BL25 -> 2593676.5 | BK44: =BI34+BI35 -> 2927 | BL44: =BK24+BK25 -> 1504
A45: 1400000US09001071300 | B45: 9001071300 | C45: Census Tract 713, Fairfield County, Connecticut | D45: 27072 | E45: 2.39 | F45: 17511.421 | G45: 17.511 | H45: 0.038 | I45: 1 | J45: 0.962 | K45: 5 | L45: 1078 | M45: 0.73871789 | N45: 0.974 | O45: 5 | P45: 0.89 | Q45: 5 | R45: 5 | S45: 1 | T45: 1 | U45: 3030 | V45: 0.11966619 | W45: 25320.435 | X45: 1 | Y45: 664 | Z45: 24.601704 | AA45: 0.817 | AB45: 5 | AC45: 5 | AD45: 5 | AE45: Yes | AF45: Yes | AG45: 34389.421 | AH45: 0 | AI45: 0 | AM45: 0 | AN45: 0 | AR45: 0 | AX45: 9001072800 | AY45: 67221.614 | AZ45: 239893.12 | BA45: 9 | BB45: 5076.94 | BC45: 21 | BD45: 234816.18 | BF45: % | BG45: =BG43/BG44 -> 0.29310713 | BH45: =BH43/BH44 -> 0.31417548 | BI45: =BI43/BI44 -> 0.32501081 | BJ45: =BJ43/BJ44 -> 0.23445084 | BK45: =BK43/BK44 -> 0.04714725 | BL45: =BL43/BL44 -> 0.35571809
A46: 1400000US09001071400 | B46: 9001071400 | C46: Census Tract 714, Fairfield County, Connecticut | D46: 40245 | E46: 3.16 | F46: 22639.581 | G46: 22.64 | H46: 0.089 | I46: 1 | J46: 0.911 | K46: 5 | L46: 1131 | M46: 0.59948105 | N46: 0.923 | O46: 5 | P46: 0.835 | Q46: 5 | R46: 5 | S46: 1 | T46: 1 | U46: 3861 | V46: 0.22587711 | W46: 17093.366 | X46: 1 | Y46: 1007 | Z46: 27.725771 | AA46: 0.867 | AB46: 5 | AC46: 5 | AD46: 5 | AE46: Yes | AF46: Yes | AG46: 38432.276 | AH46: 3327.16 | AI46: 2 | AJ46: 1 | AK46: 1 | AL46: 0 | AM46: 927.04 | AN46: 15 | AO46: 2 | AP46: 13 | AQ46: 0 | AR46: 2400.12 | AX46: 9001072900 | AY46: 67533.59 | AZ46: 53807.48 | BA46: 19 | BB46: 8358.1 | BC46: 30 | BD46: 45449.38
A47: 1400000US09001071600 | B47: 9001071600 | C47: Census Tract 716, Fairfield County, Connecticut | D47: 21895 | E47: 3.46 | F47: 11770.825 | G47: 11.771 | H47: 0.003 | I47: 1 | J47: 0.997 | K47: 5 | L47: 1032 | M47: 1.0520928 | N47: 0.998 | O47: 5 | P47: 0.921 | Q47: 5 | R47: 5 | S47: 1 | T47: 1 | U47: 2448 | V47: 0.066529652 | W47: 36795.623 | X47: 1 | Y47: 565 | Z47: 21.67242 | AA47: 0.78 | AB47: 4 | AC47: 4.5 | AD47: 5 | AE47: Yes | AF47: Yes | AG47: 0 | AH47: 1330.85 | AI47: 0 | AM47: 0 | AN47: 8 | AO47: 1 | AP47: 7 | AQ47: 0 | AR47: 1330.85 | AX47: 9001073000 | AY47: 27163.765 | AZ47: 17678.66 | BA47: 5 | BB47: 2053.25 | BC47: 20 | BD47: 15625.41
A48: 1400000US09001071600 | B48: 9001071600 | C48: Census Tract 716, Fairfield County, Connecticut | D48: 21895 | E48: 3.46 | F48: 11770.825 | G48: 11.771 | H48: 0.003 | I48: 1 | J48: 0.997 | K48: 5 | L48: 1032 | M48: 1.0520928 | N48: 0.998 | O48: 5 | P48: 0.921 | Q48: 5 | R48: 5 | S48: 1 | T48: 1 | U48: 2448 | V48: 0.066529652 | W48: 36795.623 | X48: 1 | Y48: 565 | Z48: 21.67242 | AA48: 0.78 | AB48: 4 | AC48: 4.5 | AD48: 5 | AE48: Yes | AF48: Yes | AG48: 24529.813 | AH48: 0 | AI48: 0 | AM48: 0 | AN48: 0 | AR48: 0 | AX48: 9001073100 | AY48: 69720.743 | AZ48: 34954.18 | BA48: 14 | BB48: 8317.02 | BC48: 30 | BD48: 26637.16
A49: 1400000US09001071900 | B49: 9001071900 | C49: Census Tract 719, Fairfield County, Connecticut | D49: 42969 | E49: 2.7 | F49: 26150.101 | G49: 26.15 | H49: 0.125 | I49: 1 | J49: 0.875 | K49: 5 | L49: 1287 | M49: 0.59059046 | N49: 0.914 | O49: 5 | P49: 0.666 | Q49: 4 | R49: 5 | S49: 1 | T49: 1 | U49: 4831 | V49: 0.19074374 | W49: 25327.174 | X49: 1 | Y49: 1373 | Z49: 27.742978 | AA49: 0.868 | AB49: 5 | AC49: 5 | AD49: 5 | AE49: Yes | AF49: Yes | AG49: 0 | AH49: 230 | AI49: 0 | AM49: 0 | AN49: 1 | AO49: 1 | AP49: 0 | AQ49: 0 | AR49: 230 | AX49: 9001073200 | AY49: 24209.61 | AZ49: 3053.03 | BA49: 3 | BB49: 563.2 | BC49: 7 | BD49: 2489.83
A50: 1400000US09001071900 | B50: 9001071900 | C50: Census Tract 719, Fairfield County, Connecticut | D50: 42969 | E50: 2.7 | F50: 26150.101 | G50: 26.15 | H50: 0.125 | I50: 1 | J50: 0.875 | K50: 5 | L50: 1287 | M50: 0.59059046 | N50: 0.914 | O50: 5 | P50: 0.666 | Q50: 4 | R50: 5 | S50: 1 | T50: 1 | U50: 4831 | V50: 0.19074374 | W50: 25327.174 | X50: 1 | Y50: 1373 | Z50: 27.742978 | AA50: 0.868 | AB50: 5 | AC50: 5 | AD50: 5 | AE50: Yes | AF50: Yes | AG50: 0 | AH50: 3390.23 | AI50: 2 | AJ50: 2 | AK50: 0 | AL50: 0 | AM50: 404.3 | AN50: 10 | AO50: 3 | AP50: 6 | AQ50: 1 | AR50: 2985.93 | AX50: 9001073300 | AY50: 49786.05 | AZ50: 21408.65 | BA50: 3 | BB50: 1427.69 | BC50: 22 | BD50: 19980.96 | BF50: Income <= 80% SMI > 60% | BG50: Sum of HESReportTable.CLM $ Collected | BH50: Sum of HESReportTable.Incentive Disbursements | BI50: Sum of HESReportTable.HES Total Units | BJ50: Sum of HESReportTable.Incentives | BK50: Sum of HESReportTable.HESIE Total Units | BL50: Sum of HESReportTable.HESIE Incentives
A51: 1400000US09001071900 | B51: 9001071900 | C51: Census Tract 719, Fairfield County, Connecticut | D51: 42969 | E51: 2.7 | F51: 26150.101 | G51: 26.15 | H51: 0.125 | I51: 1 | J51: 0.875 | K51: 5 | L51: 1287 | M51: 0.59059046 | N51: 0.914 | O51: 5 | P51: 0.666 | Q51: 4 | R51: 5 | S51: 1 | T51: 1 | U51: 4831 | V51: 0.19074374 | W51: 25327.174 | X51: 1 | Y51: 1373 | Z51: 27.742978 | AA51: 0.868 | AB51: 5 | AC51: 5 | AD51: 5 | AE51: Yes | AF51: Yes | AG51: 46534.636 | AH51: 0 | AI51: 0 | AM51: 0 | AN51: 0 | AR51: 0 | AX51: 9001073400 | AY51: 53978.009 | AZ51: 48424.62 | BA51: 9 | BB51: 4874.45 | BC51: 29 | BD51: 43550.17 | BF51: Total | BG51: 12129793 | BH51: 5016754.3 | BI51: 2927 | BJ51: 2157547.9 | BK51: 1504 | BL51: 2593676.5
A52: 1400000US09001072000 | B52: 9001072000 | C52: Census Tract 720, Fairfield County, Connecticut | D52: 52909 | E52: 2.89 | F52: 31122.941 | G52: 31.123 | H52: 0.189 | I52: 1 | J52: 0.811 | K52: 5 | L52: 1386 | M52: 0.53439679 | N52: 0.875 | O52: 5 | P52: 0.575 | Q52: 3 | R52: 4 | S52: 1 | T52: 1 | U52: 3565 | V52: 0.26560316 | W52: 13422.28 | X52: 1 | Y52: 818 | Z52: 23.251848 | AA52: 0.806 | AB52: 5 | AC52: 4.5 | AD52: 5 | AE52: No | AF52: Yes | AG52: 0 | AH52: 19032.27 | AI52: 6 | AJ52: 5 | AK52: 1 | AL52: 0 | AM52: 2207.03 | AN52: 21 | AO52: 14 | AP52: 6 | AQ52: 1 | AR52: 16825.24 | AX52: 9001073500 | AY52: 38030.339 | AZ52: 7178.22 | BA52: 5 | BB52: 501.38 | BC52: 17 | BD52: 6676.84 | BF52: Yes | BG52: 1474442.5 | BH52: 678487.38 | BI52: 239 | BJ52: 123034.65 | BK52: 326 | BL52: 564617.73
A53: 1400000US09001072000 | B53: 9001072000 | C53: Census Tract 720, Fairfield County, Connecticut | D53: 52909 | E53: 2.89 | F53: 31122.941 | G53: 31.123 | H53: 0.189 | I53: 1 | J53: 0.811 | K53: 5 | L53: 1386 | M53: 0.53439679 | N53: 0.875 | O53: 5 | P53: 0.575 | Q53: 3 | R53: 4 | S53: 1 | T53: 1 | U53: 3565 | V53: 0.26560316 | W53: 13422.28 | X53: 1 | Y53: 818 | Z53: 23.251848 | AA53: 0.806 | AB53: 5 | AC53: 4.5 | AD53: 5 | AE53: No | AF53: Yes | AG53: 43927.02 | AH53: 0 | AI53: 0 | AM53: 0 | AN53: 0 | AR53: 0 | AX53: 9001073600 | AY53: 24351.613 | AZ53: 846.37 | BA53: 1 | BB53: 134.5 | BC53: 7 | BD53: 711.87
A54: 1400000US09001072100 | B54: 9001072100 | C54: Census Tract 721, Fairfield County, Connecticut | D54: 56009 | E54: 2.24 | F54: 37422.587 | G54: 37.423 | H54: 0.263 | I54: 2 | J54: 0.737 | K54: 4 | L54: 1463 | M54: 0.46912844 | N54: 0.812 | O54: 5 | P54: 0.51 | Q54: 3 | R54: 4 | S54: 1 | T54: 1 | U54: 6094 | V54: 0.50058726 | W54: 12173.702 | X54: 1 | Y54: 1196 | Z54: 22.894334 | AA54: 0.801 | AB54: 5 | AC54: 4.5 | AD54: 5 | AE54: No | AF54: Yes | AG54: 119833.88 | AH54: 44620.47 | AI54: 17 | AJ54: 16 | AK54: 1 | AL54: 0 | AM54: 9086.13 | AN54: 35 | AO54: 21 | AP54: 14 | AQ54: 0 | AR54: 35534.34 | AX54: 9001073700 | AY54: 64008.136 | AZ54: 24518.83 | BA54: 3 | BB54: 3732.6 | BC54: 29 | BD54: 20786.23 | BF54: % | BG54: =BG52/BG51 -> 0.12155546 | BH54: =BH52/BH51 -> 0.13524429 | BI54: =BI52/BI51 -> 0.08165357 | BJ54: =BJ52/BJ51 -> 0.057025224 | BK54: =BK52/BK51 -> 0.21675532 | BL54: =BL52/BL51 -> 0.21769012
A55: 1400000US09001072100 | B55: 9001072100 | C55: Census Tract 721, Fairfield County, Connecticut | D55: 56009 | E55: 2.24 | F55: 37422.587 | G55: 37.423 | H55: 0.263 | I55: 2 | J55: 0.737 | K55: 4 | L55: 1463 | M55: 0.46912844 | N55: 0.812 | O55: 5 | P55: 0.51 | Q55: 3 | R55: 4 | S55: 1 | T55: 1 | U55: 6094 | V55: 0.50058726 | W55: 12173.702 | X55: 1 | Y55: 1196 | Z55: 22.894334 | AA55: 0.801 | AB55: 5 | AC55: 4.5 | AD55: 5 | AE55: No | AF55: Yes | AG55: 302.3541 | AH55: 0 | AI55: 0 | AM55: 0 | AN55: 0 | AR55: 0 | AX55: 9001073800 | AY55: 25510.302 | AZ55: 2512.29 | BA55: 1 | BB55: 2.34 | BC55: 4 | BD55: 447.45
A56: 1400000US09001072200 | B56: 9001072200 | C56: Census Tract 722, Fairfield County, Connecticut | D56: 49402 | E56: 2.49 | F56: 31307.245 | G56: 31.307 | H56: 0.193 | I56: 1 | J56: 0.807 | K56: 5 | L56: 1641 | M56: 0.62899178 | N56: 0.936 | O56: 5 | P56: 0.356 | Q56: 2 | R56: 4 | S56: 1 | T56: 1 | U56: 3828 | V56: 0.3481213 | W56: 10996.167 | X56: 1 | Y56: 728 | Z56: 18.743563 | AA56: 0.721 | AB56: 4 | AC56: 4 | AD56: 4 | AE56: No | AF56: Yes | AG56: 0 | AH56: 23077.93 | AI56: 19 | AJ56: 17 | AK56: 2 | AL56: 0 | AM56: 10983.51 | AN56: 10 | AO56: 6 | AP56: 4 | AQ56: 0 | AR56: 12094.42 | AX56: 9001073900 | AY56: 35070.079 | AZ56: 106775.64 | BA56: 2 | BB56: 170.07 | BC56: 24 | BD56: 106605.57
A57: 1400000US09001072200 | B57: 9001072200 | C57: Census Tract 722, Fairfield County, Connecticut | D57: 49402 | E57: 2.49 | F57: 31307.245 | G57: 31.307 | H57: 0.193 | I57: 1 | J57: 0.807 | K57: 5 | L57: 1641 | M57: 0.62899178 | N57: 0.936 | O57: 5 | P57: 0.356 | Q57: 2 | R57: 4 | S57: 1 | T57: 1 | U57: 3828 | V57: 0.3481213 | W57: 10996.167 | X57: 1 | Y57: 728 | Z57: 18.743563 | AA57: 0.721 | AB57: 4 | AC57: 4 | AD57: 4 | AE57: No | AF57: Yes | AG57: 41166.363 | AH57: 0 | AI57: 0 | AM57: 0 | AN57: 0 | AR57: 0 | AX57: 9001074000 | AY57: 26942.261 | AZ57: 13413.06 | BA57: 1 | BB57: 183.09 | BC57: 15 | BD57: 13229.97
A58: 1400000US09001072200 | B58: 9001072200 | C58: Census Tract 722, Fairfield County, Connecticut | D58: 49402 | E58: 2.49 | F58: 31307.245 | G58: 31.307 | H58: 0.193 | I58: 1 | J58: 0.807 | K58: 5 | L58: 1641 | M58: 0.62899178 | N58: 0.936 | O58: 5 | P58: 0.356 | Q58: 2 | R58: 4 | S58: 1 | T58: 1 | U58: 3828 | V58: 0.3481213 | W58: 10996.167 | X58: 1 | Y58: 728 | Z58: 18.743563 | AA58: 0.721 | AB58: 4 | AC58: 4 | AD58: 4 | AE58: No | AF58: Yes | AG58: 0 | AH58: 0 | AI58: 0 | AM58: 0 | AN58: 0 | AR58: 0 | AX58: 9001074300 | AY58: 51618.49 | AZ58: 8289.77 | BA58: 2 | BB58: 550.87 | BC58: 26 | BD58: 7738.9 | BF58: High arrearage municipalities (Small load) | BG58: C&LM Collections | BH58: C&LM Incentives | BI58: All C&LM Collections | BJ58: All C&LM disbersements
A59: 1400000US09001072300 | B59: 9001072300 | C59: Census Tract 723, Fairfield County, Connecticut | D59: 64662 | E59: 3.17 | F59: 36317.797 | G59: 36.318 | H59: 0.253 | I59: 2 | J59: 0.747 | K59: 4 | L59: 1594 | M59: 0.52668392 | N59: 0.872 | O59: 5 | P59: 0.387 | Q59: 2 | R59: 3 | S59: 1 | T59: 1 | U59: 5396 | V59: 0.35438543 | W59: 15226.36 | X59: 1 | Y59: 1363 | Z59: 24.209591 | AA59: 0.816 | AB59: 5 | AC59: 4 | AD59: 4 | AE59: No | AF59: No | AG59: 62912.309 | AH59: 15404.49 | AI59: 14 | AJ59: 12 | AK59: 2 | AL59: 0 | AM59: 7767.78 | AN59: 11 | AO59: 7 | AP59: 4 | AQ59: 0 | AR59: 7636.71 | AX59: 9001074400 | AY59: 54299.358 | AZ59: 20133.35 | BA59: 9 | BB59: 3501.35 | BC59: 25 | BD59: 6632 | BF59: same towns for shutoffs | BG59: 9091841.8 | BH59: 6667447.8 | BI59: 17547919 | BJ59: 11650461
A60: 1400000US09001072400 | B60: 9001072400 | C60: Census Tract 724, Fairfield County, Connecticut | D60: 59014 | E60: 3.24 | F60: 32785.556 | G60: 32.786 | H60: 0.21 | I60: 2 | J60: 0.79 | K60: 4 | L60: 1532 | M60: 0.56073474 | N60: 0.899 | O60: 5 | P60: 0.441 | Q60: 3 | R60: 4 | S60: 1 | T60: 1 | U60: 2836 | V60: 0.26395335 | W60: 10744.323 | X60: 1 | Y60: 928 | Z60: 30.697982 | AA60: 0.894 | AB60: 5 | AC60: 4.5 | AD60: 5 | AE60: No | AF60: Yes | AG60: 38727.082 | AH60: 29244.41 | AI60: 12 | AJ60: 11 | AK60: 1 | AL60: 0 | AM60: 5480.74 | AN60: 8 | AO60: 8 | AP60: 0 | AQ60: 0 | AR60: 23763.67 | AX60: 9001080100 | AY60: 59507.35 | AZ60: 22394.32 | BA60: 22 | BB60: 10764.21 | BC60: 19 | BD60: 11630.11
A61: 1400000US09001072500 | B61: 9001072500 | C61: Census Tract 725, Fairfield County, Connecticut | D61: 65113 | E61: 2.83 | F61: 38705.661 | G61: 38.706 | H61: 0.273 | I61: 2 | J61: 0.727 | K61: 4 | L61: 1492 | M61: 0.462568 | N61: 0.804 | O61: 5 | P61: 0.486 | Q61: 3 | R61: 4 | S61: 1 | T61: 1 | U61: 5726 | V61: 0.55808598 | W61: 10260.068 | X61: 1 | Y61: 1147 | Z61: 20.22571 | AA61: 0.754 | AB61: 4 | AC61: 4 | AD61: 4 | AE61: No | AF61: No | AG61: 78001.035 | AH61: 18716.64 | AI61: 31 | AJ61: 30 | AK61: 1 | AL61: 0 | AM61: 13275.87 | AN61: 14 | AO61: 12 | AP61: 2 | AQ61: 0 | AR61: 5440.77 | AX61: 9001080200 | AY61: 57737.786 | AZ61: 32132.8 | BA61: 17 | BB61: 4172.75 | BC61: 26 | BD61: 27960.05
A62: 1400000US09001072500 | B62: 9001072500 | C62: Census Tract 725, Fairfield County, Connecticut | D62: 65113 | E62: 2.83 | F62: 38705.661 | G62: 38.706 | H62: 0.273 | I62: 2 | J62: 0.727 | K62: 4 | L62: 1492 | M62: 0.462568 | N62: 0.804 | O62: 5 | P62: 0.486 | Q62: 3 | R62: 4 | S62: 1 | T62: 1 | U62: 5726 | V62: 0.55808598 | W62: 10260.068 | X62: 1 | Y62: 1147 | Z62: 20.22571 | AA62: 0.754 | AB62: 4 | AC62: 4 | AD62: 4 | AE62: No | AF62: No | AG62: 0 | AH62: 0 | AI62: 0 | AM62: 0 | AN62: 0 | AR62: 0 | AX62: 9001080400 | AY62: 78832.451 | AZ62: 18104.68 | BA62: 14 | BB62: 2705.27 | BC62: 27 | BD62: 15399.41 | BG62: % collections | BH62: % Disbursements
A63: 1400000US09001072600 | B63: 9001072600 | C63: Census Tract 726, Fairfield County, Connecticut | D63: 63141 | E63: 2.39 | F63: 40842.518 | G63: 40.843 | H63: 0.304 | I63: 2 | J63: 0.696 | K63: 4 | L63: 1526 | M63: 0.4483563 | N63: 0.782 | O63: 4 | P63: 0.447 | Q63: 3 | R63: 4 | S63: 1 | T63: 1 | U63: 7583 | V63: 1.1663131 | W63: 6501.6845 | X63: 1 | Y63: 905 | Z63: 12.338105 | AA63: 0.516 | AB63: 3 | AC63: 3.5 | AD63: 4 | AE63: No | AF63: No | AG63: 118351.09 | AH63: 43073.09 | AI63: 21 | AJ63: 20 | AK63: 1 | AL63: 0 | AM63: 16945 | AN63: 18 | AO63: 14 | AP63: 4 | AQ63: 0 | AR63: 26128.09 | AX63: 9001080500 | AY63: 67513.528 | AZ63: 10850.27 | BA63: 17 | BB63: 10150.45 | BC63: 1 | BD63: 699.82 | BG63: =BG59/BI59 -> 0.5181151 | BH63: =BH59/BJ59 -> 0.57229049
A64: 1400000US09001072600 | B64: 9001072600 | C64: Census Tract 726, Fairfield County, Connecticut | D64: 63141 | E64: 2.39 | F64: 40842.518 | G64: 40.843 | H64: 0.304 | I64: 2 | J64: 0.696 | K64: 4 | L64: 1526 | M64: 0.4483563 | N64: 0.782 | O64: 4 | P64: 0.447 | Q64: 3 | R64: 4 | S64: 1 | T64: 1 | U64: 7583 | V64: 1.1663131 | W64: 6501.6845 | X64: 1 | Y64: 905 | Z64: 12.338105 | AA64: 0.516 | AB64: 3 | AC64: 3.5 | AD64: 4 | AE64: No | AF64: No | AG64: 41.9796 | AH64: 0 | AI64: 0 | AM64: 0 | AN64: 0 | AR64: 0 | AX64: 9001080600 | AY64: 43535.778 | AZ64: 10265.38 | BA64: 8 | BB64: 2126.03 | BC64: 5 | BD64: 8139.35
A65: 1400000US09001072700 | B65: 9001072700 | C65: Census Tract 727, Fairfield County, Connecticut | D65: 75799 | E65: 3.16 | F65: 42640.269 | G65: 42.64 | H65: 0.334 | I65: 2 | J65: 0.666 | K65: 4 | L65: 1914 | M65: 0.53864576 | N65: 0.879 | O65: 5 | P65: 0.204 | Q65: 2 | R65: 3 | S65: 1 | T65: 1 | U65: 3726 | V65: 0.69267232 | W65: 5379.1669 | X65: 1 | Y65: 773 | Z65: 19.907288 | AA65: 0.75 | AB65: 4 | AC65: 3.5 | AD65: 4 | AE65: No | AF65: No | AG65: 59967.633 | AH65: 47344.93 | AI65: 15 | AJ65: 13 | AK65: 2 | AL65: 0 | AM65: 13515.44 | AN65: 22 | AO65: 19 | AP65: 3 | AQ65: 0 | AR65: 33829.49 | AX65: 9001080700 | AY65: 36457.739 | AZ65: 3191.4 | BA65: 12 | BB65: 3062.57 | BC65: 3 | BD65: 128.83
A66: 1400000US09001072700 | B66: 9001072700 | C66: Census Tract 727, Fairfield County, Connecticut | D66: 75799 | E66: 3.16 | F66: 42640.269 | G66: 42.64 | H66: 0.334 | I66: 2 | J66: 0.666 | K66: 4 | L66: 1914 | M66: 0.53864576 | N66: 0.879 | O66: 5 | P66: 0.204 | Q66: 2 | R66: 3 | S66: 1 | T66: 1 | U66: 3726 | V66: 0.69267232 | W66: 5379.1669 | X66: 1 | Y66: 773 | Z66: 19.907288 | AA66: 0.75 | AB66: 4 | AC66: 3.5 | AD66: 4 | AE66: No | AF66: No | AG66: 284.0528 | AH66: 0 | AI66: 0 | AM66: 0 | AN66: 0 | AR66: 0 | AX66: 9001080800 | AY66: 81784.641 | AZ66: 18364.76 | BA66: 32 | BB66: 12645.15 | BC66: 8 | BD66: 5719.61
A67: 1400000US09001072800 | B67: 9001072800 | C67: Census Tract 728, Fairfield County, Connecticut | D67: 52607 | E67: 3.26 | F67: 29136.323 | G67: 29.136 | H67: 0.155 | I67: 1 | J67: 0.845 | K67: 5 | L67: 1137 | M67: 0.46828147 | N67: 0.81 | O67: 5 | P67: 0.829 | Q67: 5 | R67: 5 | S67: 1 | T67: 1 | U67: 5469 | V67: 0.57813743 | W67: 9459.6885 | X67: 1 | Y67: 1924 | Z67: 34.308131 | AA67: 0.93 | AB67: 5 | AC67: 5 | AD67: 5 | AE67: No | AF67: Yes | AG67: 67221.614 | AH67: 239893.12 | AI67: 9 | AJ67: 9 | AK67: 0 | AL67: 0 | AM67: 5076.94 | AN67: 21 | AO67: 17 | AP67: 3 | AQ67: 1 | AR67: 234816.18 | AX67: 9001080900 | AY67: 79381.614 | AZ67: 46203.07 | BA67: 37 | BB67: 14290.38 | BC67: 13 | BD67: 31912.69
A68: 1400000US09001072900 | B68: 9001072900 | C68: Census Tract 729, Fairfield County, Connecticut | D68: 63618 | E68: 3.23 | F68: 35398.002 | G68: 35.398 | H68: 0.239 | I68: 2 | J68: 0.761 | K68: 4 | L68: 1641 | M68: 0.55630258 | N68: 0.892 | O68: 5 | P68: 0.356 | Q68: 2 | R68: 3 | S68: 1 | T68: 1 | U68: 4594 | V68: 0.79469596 | W68: 5780.8272 | X68: 1 | Y68: 979 | Z68: 21.535416 | AA68: 0.784 | AB68: 4 | AC68: 3.5 | AD68: 4 | AE68: No | AF68: No | AG68: 67436.168 | AH68: 53807.48 | AI68: 19 | AJ68: 18 | AK68: 1 | AL68: 0 | AM68: 8358.1 | AN68: 30 | AO68: 23 | AP68: 7 | AQ68: 0 | AR68: 45449.38 | AX68: 9001081000 | AY68: 69118.768 | AZ68: 32052.07 | BA68: 22 | BB68: 10665.09 | BC68: 24 | BD68: 21386.98
A69: 1400000US09001072900 | B69: 9001072900 | C69: Census Tract 729, Fairfield County, Connecticut | D69: 63618 | E69: 3.23 | F69: 35398.002 | G69: 35.398 | H69: 0.239 | I69: 2 | J69: 0.761 | K69: 4 | L69: 1641 | M69: 0.55630258 | N69: 0.892 | O69: 5 | P69: 0.356 | Q69: 2 | R69: 3 | S69: 1 | T69: 1 | U69: 4594 | V69: 0.79469596 | W69: 5780.8272 | X69: 1 | Y69: 979 | Z69: 21.535416 | AA69: 0.784 | AB69: 4 | AC69: 3.5 | AD69: 4 | AE69: No | AF69: No | AG69: 18.556 | AH69: 0 | AI69: 0 | AM69: 0 | AN69: 0 | AR69: 0 | AX69: 9001081100 | AY69: 78320.746 | AZ69: 38990.6 | BA69: 22 | BB69: 11901.5 | BC69: 11 | BD69: 27089.1
A70: 1400000US09001072900 | B70: 9001072900 | C70: Census Tract 729, Fairfield County, Connecticut | D70: 63618 | E70: 3.23 | F70: 35398.002 | G70: 35.398 | H70: 0.239 | I70: 2 | J70: 0.761 | K70: 4 | L70: 1641 | M70: 0.55630258 | N70: 0.892 | O70: 5 | P70: 0.356 | Q70: 2 | R70: 3 | S70: 1 | T70: 1 | U70: 4594 | V70: 0.79469596 | W70: 5780.8272 | X70: 1 | Y70: 979 | Z70: 21.535416 | AA70: 0.784 | AB70: 4 | AC70: 3.5 | AD70: 4 | AE70: No | AF70: No | AG70: 78.866 | AH70: 0 | AI70: 0 | AM70: 0 | AN70: 0 | AR70: 0 | AX70: 9001081200 | AY70: 102710.93 | AZ70: 41624.55 | BA70: 40 | BB70: 34781.2 | BC70: 4 | BD70: 6843.35
A71: 1400000US09001073000 | B71: 9001073000 | C71: Census Tract 730, Fairfield County, Connecticut | D71: 91500 | E71: 3.57 | F71: 48426.935 | G71: 48.427 | H71: 0.438 | I71: 3 | J71: 0.562 | K71: 3 | L71: 1696 | M71: 0.42026199 | N71: 0.726 | O71: 4 | P71: 0.313 | Q71: 2 | R71: 3 | S71: 1 | T71: 1 | U71: 1899 | V71: 0.46758904 | W71: 4061.2586 | X71: 1 | Y71: 432 | Z71: 20.532319 | AA71: 0.766 | AB71: 4 | AC71: 3.5 | AD71: 4 | AE71: No | AF71: No | AG71: 27045.102 | AH71: 17678.66 | AI71: 5 | AJ71: 5 | AK71: 0 | AL71: 0 | AM71: 2053.25 | AN71: 20 | AO71: 11 | AP71: 9 | AQ71: 0 | AR71: 15625.41 | AX71: 9001081300 | AY71: 100014.4 | AZ71: 16907.1 | BA71: 15 | BB71: 12536.06 | BC71: 6 | BD71: 4371.04
A72: 1400000US09001073000 | B72: 9001073000 | C72: Census Tract 730, Fairfield County, Connecticut | D72: 91500 | E72: 3.57 | F72: 48426.935 | G72: 48.427 | H72: 0.438 | I72: 3 | J72: 0.562 | K72: 3 | L72: 1696 | M72: 0.42026199 | N72: 0.726 | O72: 4 | P72: 0.313 | Q72: 2 | R72: 3 | S72: 1 | T72: 1 | U72: 1899 | V72: 0.46758904 | W72: 4061.2586 | X72: 1 | Y72: 432 | Z72: 20.532319 | AA72: 0.766 | AB72: 4 | AC72: 3.5 | AD72: 4 | AE72: No | AF72: No | AG72: 118.6635 | AH72: 0 | AI72: 0 | AM72: 0 | AN72: 0 | AR72: 0 | AX72: 9001090100 | AY72: 71716.851 | AZ72: 15275.41 | BA72: 20 | BB72: 13147.68 | BC72: 1 | BD72: 2127.73
A73: 1400000US09001073100 | B73: 9001073100 | C73: Census Tract 731, Fairfield County, Connecticut | D73: 37802 | E73: 2.34 | F73: 24711.94 | G73: 24.712 | H73: 0.11 | I73: 1 | J73: 0.89 | K73: 5 | L73: 1162 | M73: 0.56426164 | N73: 0.902 | O73: 5 | P73: 0.814 | Q73: 5 | R73: 5 | S73: 1 | T73: 1 | U73: 5853 | V73: 1.2706762 | W73: 4606.209 | X73: 1 | Y73: 1768 | Z73: 29.107672 | AA73: 0.874 | AB73: 5 | AC73: 5 | AD73: 5 | AE73: Yes | AF73: Yes | AG73: 0 | AH73: 34954.18 | AI73: 14 | AJ73: 13 | AK73: 1 | AL73: 0 | AM73: 8317.02 | AN73: 30 | AO73: 18 | AP73: 12 | AQ73: 0 | AR73: 26637.16 | AX73: 9001090200 | AY73: 141902.05 | AZ73: 33204.18 | BA73: 33 | BB73: 21080.72 | BC73: 8 | BD73: 12123.46
A74: 1400000US09001073100 | B74: 9001073100 | C74: Census Tract 731, Fairfield County, Connecticut | D74: 37802 | E74: 2.34 | F74: 24711.94 | G74: 24.712 | H74: 0.11 | I74: 1 | J74: 0.89 | K74: 5 | L74: 1162 | M74: 0.56426164 | N74: 0.902 | O74: 5 | P74: 0.814 | Q74: 5 | R74: 5 | S74: 1 | T74: 1 | U74: 5853 | V74: 1.2706762 | W74: 4606.209 | X74: 1 | Y74: 1768 | Z74: 29.107672 | AA74: 0.874 | AB74: 5 | AC74: 5 | AD74: 5 | AE74: Yes | AF74: Yes | AG74: 69620.792 | AH74: 0 | AI74: 0 | AM74: 0 | AN74: 0 | AR74: 0 | AX74: 9001090300 | AY74: 88833.686 | AZ74: 37237.23 | BA74: 19 | BB74: 9185.5 | BC74: 11 | BD74: 28051.73
A75: 1400000US09001073100 | B75: 9001073100 | C75: Census Tract 731, Fairfield County, Connecticut | D75: 37802 | E75: 2.34 | F75: 24711.94 | G75: 24.712 | H75: 0.11 | I75: 1 | J75: 0.89 | K75: 5 | L75: 1162 | M75: 0.56426164 | N75: 0.902 | O75: 5 | P75: 0.814 | Q75: 5 | R75: 5 | S75: 1 | T75: 1 | U75: 5853 | V75: 1.2706762 | W75: 4606.209 | X75: 1 | Y75: 1768 | Z75: 29.107672 | AA75: 0.874 | AB75: 5 | AC75: 5 | AD75: 5 | AE75: Yes | AF75: Yes | AG75: 99.9512 | AH75: 0 | AI75: 0 | AM75: 0 | AN75: 0 | AR75: 0 | AX75: 9001090400 | AY75: 107562.78 | AZ75: 26510.74 | BA75: 32 | BB75: 25623.02 | BC75: 2 | BD75: 887.72
A76: 1400000US09001073200 | B76: 9001073200 | C76: Census Tract 732, Fairfield County, Connecticut | D76: 49446 | E76: 2.31 | F76: 32533.08 | G76: 32.533 | H76: 0.205 | I76: 2 | J76: 0.795 | K76: 4 | L76: 730 | M76: 0.2692644 | N76: 0.062 | O76: 1 | P76: 0.991 | Q76: 5 | R76: 5 | S76: 1 | T76: 1 | U76: 2460 | V76: 0.15158989 | W76: 16227.995 | X76: 1 | Y76: 677 | Z76: 25.120594 | AA76: 0.834 | AB76: 5 | AC76: 5 | AD76: 5 | AE76: No | AF76: Yes | AG76: 24172.336 | AH76: 3053.03 | AI76: 3 | AJ76: 3 | AK76: 0 | AL76: 0 | AM76: 563.2 | AN76: 7 | AO76: 4 | AP76: 3 | AQ76: 0 | AR76: 2489.83 | AX76: 9001090500 | AY76: 88261.777 | AZ76: 47472.93 | BA76: 25 | BB76: 17328.66 | BC76: 7 | BD76: 30144.27
A77: 1400000US09001073200 | B77: 9001073200 | C77: Census Tract 732, Fairfield County, Connecticut | D77: 49446 | E77: 2.31 | F77: 32533.08 | G77: 32.533 | H77: 0.205 | I77: 2 | J77: 0.795 | K77: 4 | L77: 730 | M77: 0.2692644 | N77: 0.062 | O77: 1 | P77: 0.991 | Q77: 5 | R77: 5 | S77: 1 | T77: 1 | U77: 2460 | V77: 0.15158989 | W77: 16227.995 | X77: 1 | Y77: 677 | Z77: 25.120594 | AA77: 0.834 | AB77: 5 | AC77: 5 | AD77: 5 | AE77: No | AF77: Yes | AG77: 37.274 | AH77: 0 | AI77: 0 | AM77: 0 | AN77: 0 | AR77: 0 | AX77: 9001090600 | AY77: 74762.86 | AZ77: 30599.96 | BA77: 17 | BB77: 19410.51 | BC77: 3 | BD77: 3439.45
A78: 1400000US09001073300 | B78: 9001073300 | C78: Census Tract 733, Fairfield County, Connecticut | D78: 34172 | E78: 2.57 | F78: 21315.908 | G78: 21.316 | H78: 0.075 | I78: 1 | J78: 0.925 | K78: 5 | L78: 1125 | M78: 0.63332981 | N78: 0.94 | O78: 5 | P78: 0.845 | Q78: 5 | R78: 5 | S78: 1 | T78: 1 | U78: 3351 | V78: 0.19406152 | W78: 17267.72 | X78: 1 | Y78: 846 | Z78: 23.710762 | AA78: 0.815 | AB78: 5 | AC78: 5 | AD78: 5 | AE78: Yes | AF78: Yes | AG78: 0 | AH78: 21408.65 | AI78: 3 | AJ78: 3 | AK78: 0 | AL78: 0 | AM78: 1427.69 | AN78: 22 | AO78: 19 | AP78: 2 | AQ78: 1 | AR78: 19980.96 | AX78: 9001090700 | AY78: 110188.03 | AZ78: 35274.04 | BA78: 25 | BB78: 19809.03 | BC78: 4 | BD78: 16665.01
A79: 1400000US09001073300 | B79: 9001073300 | C79: Census Tract 733, Fairfield County, Connecticut | D79: 34172 | E79: 2.57 | F79: 21315.908 | G79: 21.316 | H79: 0.075 | I79: 1 | J79: 0.925 | K79: 5 | L79: 1125 | M79: 0.63332981 | N79: 0.94 | O79: 5 | P79: 0.845 | Q79: 5 | R79: 5 | S79: 1 | T79: 1 | U79: 3351 | V79: 0.19406152 | W79: 17267.72 | X79: 1 | Y79: 846 | Z79: 23.710762 | AA79: 0.815 | AB79: 5 | AC79: 5 | AD79: 5 | AE79: Yes | AF79: Yes | AG79: 49786.05 | AH79: 0 | AI79: 0 | AM79: 0 | AN79: 0 | AR79: 0 | AX79: 9001100100 | AY79: 362.5888 | AZ79: 0 | BA79: 0 | BB79: 0 | BC79: 0 | BD79: 0
A80: 1400000US09001073400 | B80: 9001073400 | C80: Census Tract 734, Fairfield County, Connecticut | D80: 52917 | E80: 2.95 | F80: 30809.469 | G80: 30.809 | H80: 0.182 | I80: 1 | J80: 0.818 | K80: 5 | L80: 1497 | M80: 0.58306751 | N80: 0.911 | O80: 5 | P80: 0.474 | Q80: 3 | R80: 4 | S80: 1 | T80: 1 | U80: 4113 | V80: 0.51059155 | W80: 8055.3624 | X80: 1 | Y80: 1482 | Z80: 36.819876 | AA80: 0.947 | AB80: 5 | AC80: 4.5 | AD80: 5 | AE80: No | AF80: Yes | AG80: 0 | AH80: 48424.62 | AI80: 9 | AJ80: 7 | AK80: 2 | AL80: 0 | AM80: 4874.45 | AN80: 29 | AO80: 7 | AP80: 22 | AQ80: 0 | AR80: 43550.17 | AX80: 9001100200 | AY80: 569.35 | AZ80: 0 | BA80: 0 | BB80: 0 | BC80: 0 | BD80: 0
A81: 1400000US09001073400 | B81: 9001073400 | C81: Census Tract 734, Fairfield County, Connecticut | D81: 52917 | E81: 2.95 | F81: 30809.469 | G81: 30.809 | H81: 0.182 | I81: 1 | J81: 0.818 | K81: 5 | L81: 1497 | M81: 0.58306751 | N81: 0.911 | O81: 5 | P81: 0.474 | Q81: 3 | R81: 4 | S81: 1 | T81: 1 | U81: 4113 | V81: 0.51059155 | W81: 8055.3624 | X81: 1 | Y81: 1482 | Z81: 36.819876 | AA81: 0.947 | AB81: 5 | AC81: 4.5 | AD81: 5 | AE81: No | AF81: Yes | AG81: 53978.009 | AH81: 0 | AI81: 0 | AM81: 0 | AN81: 0 | AR81: 0 | AX81: 9001105100 | AY81: 107920.95 | AZ81: 42369.84 | BA81: 23 | BB81: 41169.84 | BC81: 0 | BD81: 0
A82: 1400000US09001073500 | B82: 9001073500 | C82: Census Tract 735, Fairfield County, Connecticut | D82: 38560 | E82: 2.97 | F82: 22374.781 | G82: 22.375 | H82: 0.086 | I82: 1 | J82: 0.914 | K82: 5 | L82: 1230 | M82: 0.65967125 | N82: 0.948 | O82: 5 | P82: 0.735 | Q82: 4 | R82: 5 | S82: 1 | T82: 1 | U82: 3456 | V82: 0.17150659 | W82: 20150.83 | X82: 1 | Y82: 1398 | Z82: 40.734266 | AA82: 0.969 | AB82: 5 | AC82: 5 | AD82: 5 | AE82: Yes | AF82: Yes | AG82: 0 | AH82: 7178.22 | AI82: 5 | AJ82: 4 | AK82: 1 | AL82: 0 | AM82: 501.38 | AN82: 17 | AO82: 4 | AP82: 13 | AQ82: 0 | AR82: 6676.84 | AX82: 9001105200 | AY82: 95286.73 | AZ82: 23739.83 | BA82: 17 | BB82: 22428.72 | BC82: 1 | BD82: 1311.11
A83: 1400000US09001073500 | B83: 9001073500 | C83: Census Tract 735, Fairfield County, Connecticut | D83: 38560 | E83: 2.97 | F83: 22374.781 | G83: 22.375 | H83: 0.086 | I83: 1 | J83: 0.914 | K83: 5 | L83: 1230 | M83: 0.65967125 | N83: 0.948 | O83: 5 | P83: 0.735 | Q83: 4 | R83: 5 | S83: 1 | T83: 1 | U83: 3456 | V83: 0.17150659 | W83: 20150.83 | X83: 1 | Y83: 1398 | Z83: 40.734266 | AA83: 0.969 | AB83: 5 | AC83: 5 | AD83: 5 | AE83: Yes | AF83: Yes | AG83: 38030.339 | AH83: 0 | AI83: 0 | AM83: 0 | AN83: 0 | AR83: 0 | AX83: 9001110100 | AY83: 47814.026 | AZ83: -4972.11 | BA83: 2 | BB83: 4192.89 | BC83: 0 | BD83: 0
A84: 1400000US09001073600 | B84: 9001073600 | C84: Census Tract 736, Fairfield County, Connecticut | D84: 34450 | E84: 3.53 | F84: 18335.885 | G84: 18.336 | H84: 0.041 | I84: 1 | J84: 0.959 | K84: 5 | L84: 1202 | M84: 0.78665415 | N84: 0.982 | O84: 5 | P84: 0.761 | Q84: 4 | R84: 5 | S84: 1 | T84: 1 | U84: 2304 | V84: 0.10411129 | W84: 22130.164 | X84: 1 | Y84: 1028 | Z84: 42.426744 | AA84: 0.975 | AB84: 5 | AC84: 5 | AD84: 5 | AE84: Yes | AF84: Yes | AG84: 0 | AH84: 846.37 | AI84: 1 | AJ84: 1 | AK84: 0 | AL84: 0 | AM84: 134.5 | AN84: 7 | AO84: 1 | AP84: 6 | AQ84: 0 | AR84: 711.87 | AX84: 9001110201 | AY84: 91460.939 | AZ84: 53772.12 | BA84: 24 | BB84: 27166.02 | BC84: 6 | BD84: 17461.1
A85: 1400000US09001073600 | B85: 9001073600 | C85: Census Tract 736, Fairfield County, Connecticut | D85: 34450 | E85: 3.53 | F85: 18335.885 | G85: 18.336 | H85: 0.041 | I85: 1 | J85: 0.959 | K85: 5 | L85: 1202 | M85: 0.78665415 | N85: 0.982 | O85: 5 | P85: 0.761 | Q85: 4 | R85: 5 | S85: 1 | T85: 1 | U85: 2304 | V85: 0.10411129 | W85: 22130.164 | X85: 1 | Y85: 1028 | Z85: 42.426744 | AA85: 0.975 | AB85: 5 | AC85: 5 | AD85: 5 | AE85: Yes | AF85: Yes | AG85: 24351.613 | AH85: 0 | AI85: 0 | AM85: 0 | AN85: 0 | AR85: 0 | AX85: 9001110202 | AY85: 89045.298 | AZ85: 62510.7 | BA85: 25 | BB85: 39263.41 | BC85: 6 | BD85: 23247.29
A86: 1400000US09001073700 | B86: 9001073700 | C86: Census Tract 737, Fairfield County, Connecticut | D86: 40075 | E86: 2.66 | F86: 24571.559 | G86: 24.572 | H86: 0.106 | I86: 1 | J86: 0.894 | K86: 5 | L86: 1314 | M86: 0.64171752 | N86: 0.945 | O86: 5 | P86: 0.64 | Q86: 4 | R86: 5 | S86: 1 | T86: 1 | U86: 4824 | V86: 0.34029887 | W86: 14175.774 | X86: 1 | Y86: 1102 | Z86: 25.096789 | AA86: 0.837 | AB86: 5 | AC86: 5 | AD86: 5 | AE86: Yes | AF86: Yes | AG86: 0 | AH86: 24518.83 | AI86: 3 | AJ86: 3 | AK86: 0 | AL86: 0 | AM86: 3732.6 | AN86: 29 | AO86: 13 | AP86: 16 | AQ86: 0 | AR86: 20786.23 | AX86: 9001110301 | AY86: 119373 | AZ86: 26013.5 | BA86: 25 | BB86: 20382.53 | BC86: 5 | BD86: 5630.97
A87: 1400000US09001073700 | B87: 9001073700 | C87: Census Tract 737, Fairfield County, Connecticut | D87: 40075 | E87: 2.66 | F87: 24571.559 | G87: 24.572 | H87: 0.106 | I87: 1 | J87: 0.894 | K87: 5 | L87: 1314 | M87: 0.64171752 | N87: 0.945 | O87: 5 | P87: 0.64 | Q87: 4 | R87: 5 | S87: 1 | T87: 1 | U87: 4824 | V87: 0.34029887 | W87: 14175.774 | X87: 1 | Y87: 1102 | Z87: 25.096789 | AA87: 0.837 | AB87: 5 | AC87: 5 | AD87: 5 | AE87: Yes | AF87: Yes | AG87: 64008.136 | AH87: 0 | AI87: 0 | AM87: 0 | AN87: 0 | AR87: 0 | AX87: 9001110302 | AY87: 65422.317 | AZ87: 23476.27 | BA87: 11 | BB87: 12868.09 | BC87: 1 | BD87: 10608.18
A88: 1400000US09001073700 | B88: 9001073700 | C88: Census Tract 737, Fairfield County, Connecticut | D88: 40075 | E88: 2.66 | F88: 24571.559 | G88: 24.572 | H88: 0.106 | I88: 1 | J88: 0.894 | K88: 5 | L88: 1314 | M88: 0.64171752 | N88: 0.945 | O88: 5 | P88: 0.64 | Q88: 4 | R88: 5 | S88: 1 | T88: 1 | U88: 4824 | V88: 0.34029887 | W88: 14175.774 | X88: 1 | Y88: 1102 | Z88: 25.096789 | AA88: 0.837 | AB88: 5 | AC88: 5 | AD88: 5 | AE88: Yes | AF88: Yes | AG88: 0 | AH88: 0 | AI88: 0 | AM88: 0 | AN88: 0 | AR88: 0 | AX88: 9001110400 | AY88: 94505.718 | AZ88: 30417.33 | BA88: 19 | BB88: 26304.36 | BC88: 1 | BD88: 4112.97
A89: 1400000US09001073800 | B89: 9001073800 | C89: Census Tract 738, Fairfield County, Connecticut | D89: 21851 | E89: 2.69 | F89: 13322.79 | G89: 13.323 | H89: 0.008 | I89: 1 | J89: 0.992 | K89: 5 | L89: 1109 | M89: 0.99888988 | N89: 0.997 | O89: 5 | P89: 0.865 | Q89: 5 | R89: 5 | S89: 1 | T89: 1 | U89: 2274 | V89: 0.20379013 | W89: 11158.538 | X89: 1 | Y89: 982 | Z89: 44.738041 | AA89: 0.982 | AB89: 5 | AC89: 5 | AD89: 5 | AE89: Yes | AF89: Yes | AG89: 0 | AH89: 2512.29 | AI89: 1 | AJ89: 1 | AK89: 0 | AL89: 0 | AM89: 2.34 | AN89: 4 | AO89: 1 | AP89: 3 | AQ89: 0 | AR89: 447.45 | AX89: 9001110500 | AY89: 117798.05 | AZ89: 41521.48 | BA89: 27 | BB89: 33014.09 | BC89: 2 | BD89: 7307.39
A90: 1400000US09001073800 | B90: 9001073800 | C90: Census Tract 738, Fairfield County, Connecticut | D90: 21851 | E90: 2.69 | F90: 13322.79 | G90: 13.323 | H90: 0.008 | I90: 1 | J90: 0.992 | K90: 5 | L90: 1109 | M90: 0.99888988 | N90: 0.997 | O90: 5 | P90: 0.865 | Q90: 5 | R90: 5 | S90: 1 | T90: 1 | U90: 2274 | V90: 0.20379013 | W90: 11158.538 | X90: 1 | Y90: 982 | Z90: 44.738041 | AA90: 0.982 | AB90: 5 | AC90: 5 | AD90: 5 | AE90: Yes | AF90: Yes | AG90: 25510.302 | AH90: 0 | AI90: 0 | AM90: 0 | AN90: 0 | AR90: 0 | AX90: 9001110600 | AY90: 152617.04 | AZ90: 38865.54 | BA90: 29 | BB90: 28663.75 | BC90: 4 | BD90: 9301.79
A91: 1400000US09001073900 | B91: 9001073900 | C91: Census Tract 739, Fairfield County, Connecticut | D91: 35163 | E91: 3.27 | F91: 19445.183 | G91: 19.445 | H91: 0.052 | I91: 1 | J91: 0.948 | K91: 5 | L91: 1256 | M91: 0.77510197 | N91: 0.981 | O91: 5 | P91: 0.707 | Q91: 4 | R91: 5 | S91: 1 | T91: 1 | U91: 3395 | V91: 0.19696925 | W91: 17236.193 | X91: 1 | Y91: 1475 | Z91: 38.094008 | AA91: 0.958 | AB91: 5 | AC91: 5 | AD91: 5 | AE91: Yes | AF91: Yes | AG91: 0 | AH91: 106775.64 | AI91: 2 | AJ91: 2 | AK91: 0 | AL91: 0 | AM91: 170.07 | AN91: 24 | AO91: 5 | AP91: 17 | AQ91: 2 | AR91: 106605.57 | AX91: 9001240200 | AY91: 1588.1765 | AZ91: 0 | BA91: 0 | BB91: 0 | BC91: 0 | BD91: 0
A92: 1400000US09001073900 | B92: 9001073900 | C92: Census Tract 739, Fairfield County, Connecticut | D92: 35163 | E92: 3.27 | F92: 19445.183 | G92: 19.445 | H92: 0.052 | I92: 1 | J92: 0.948 | K92: 5 | L92: 1256 | M92: 0.77510197 | N92: 0.981 | O92: 5 | P92: 0.707 | Q92: 4 | R92: 5 | S92: 1 | T92: 1 | U92: 3395 | V92: 0.19696925 | W92: 17236.193 | X92: 1 | Y92: 1475 | Z92: 38.094008 | AA92: 0.958 | AB92: 5 | AC92: 5 | AD92: 5 | AE92: Yes | AF92: Yes | AG92: 35070.079 | AH92: 0 | AI92: 0 | AM92: 0 | AN92: 0 | AR92: 0 | AX92: 9001257200 | AY92: 46248.605 | AZ92: 7200.74 | BA92: 1 | BB92: 481.19 | BC92: 15 | BD92: 6719.55
A93: 1400000US09001074000 | B93: 9001074000 | C93: Census Tract 740, Fairfield County, Connecticut | D93: 39737 | E93: 3.21 | F93: 22179.031 | G93: 22.179 | H93: 0.083 | I93: 1 | J93: 0.917 | K93: 5 | L93: 1228 | M93: 0.66441137 | N93: 0.952 | O93: 5 | P93: 0.739 | Q93: 4 | R93: 5 | S93: 1 | T93: 1 | U93: 1919 | V93: 0.36570324 | W93: 5247.4241 | X93: 1 | Y93: 824 | Z93: 38.558727 | AA93: 0.961 | AB93: 5 | AC93: 5 | AD93: 5 | AE93: Yes | AF93: Yes | AG93: 0 | AH93: 13413.06 | AI93: 1 | AJ93: 1 | AK93: 0 | AL93: 0 | AM93: 183.09 | AN93: 15 | AO93: 2 | AP93: 13 | AQ93: 0 | AR93: 13229.97 | AX93: 9009120100 | AY93: 114222.3 | AZ93: 39504.98 | BA93: 33 | BB93: 26591.68 | BC93: 9 | BD93: 12913.3
A94: 1400000US09001074000 | B94: 9001074000 | C94: Census Tract 740, Fairfield County, Connecticut | D94: 39737 | E94: 3.21 | F94: 22179.031 | G94: 22.179 | H94: 0.083 | I94: 1 | J94: 0.917 | K94: 5 | L94: 1228 | M94: 0.66441137 | N94: 0.952 | O94: 5 | P94: 0.739 | Q94: 4 | R94: 5 | S94: 1 | T94: 1 | U94: 1919 | V94: 0.36570324 | W94: 5247.4241 | X94: 1 | Y94: 824 | Z94: 38.558727 | AA94: 0.961 | AB94: 5 | AC94: 5 | AD94: 5 | AE94: Yes | AF94: Yes | AG94: 26942.261 | AH94: 0 | AI94: 0 | AM94: 0 | AN94: 0 | AR94: 0 | AX94: 9009120200 | AY94: 98996.496 | AZ94: 18704.38 | BA94: 16 | BB94: 9845.58 | BC94: 9 | BD94: 8858.8
A95: 1400000US09001074300 | B95: 9001074300 | C95: Census Tract 743, Fairfield County, Connecticut | D95: 40637 | E95: 3.2 | F95: 22716.774 | G95: 22.717 | H95: 0.091 | I95: 1 | J95: 0.909 | K95: 5 | L95: 1182 | M95: 0.62438444 | N95: 0.934 | O95: 5 | P95: 0.792 | Q95: 4 | R95: 5 | S95: 1 | T95: 1 | U95: 4267 | V95: 0.54178745 | W95: 7875.7822 | X95: 1 | Y95: 1825 | Z95: 36.66131 | AA95: 0.952 | AB95: 5 | AC95: 5 | AD95: 5 | AE95: Yes | AF95: Yes | AG95: 0 | AH95: 8289.77 | AI95: 2 | AJ95: 0 | AK95: 2 | AL95: 0 | AM95: 550.87 | AN95: 26 | AO95: 4 | AP95: 22 | AQ95: 0 | AR95: 7738.9 | AX95: 9009125100 | AY95: 74797.085 | AZ95: 37210.91 | BA95: 38 | BB95: 29673.11 | BC95: 6 | BD95: 7537.8
A96: 1400000US09001074300 | B96: 9001074300 | C96: Census Tract 743, Fairfield County, Connecticut | D96: 40637 | E96: 3.2 | F96: 22716.774 | G96: 22.717 | H96: 0.091 | I96: 1 | J96: 0.909 | K96: 5 | L96: 1182 | M96: 0.62438444 | N96: 0.934 | O96: 5 | P96: 0.792 | Q96: 4 | R96: 5 | S96: 1 | T96: 1 | U96: 4267 | V96: 0.54178745 | W96: 7875.7822 | X96: 1 | Y96: 1825 | Z96: 36.66131 | AA96: 0.952 | AB96: 5 | AC96: 5 | AD96: 5 | AE96: Yes | AF96: Yes | AG96: 51549.296 | AH96: 0 | AI96: 0 | AM96: 0 | AN96: 0 | AR96: 0 | AX96: 9009125200 | AY96: 85166.804 | AZ96: 22374.48 | BA96: 19 | BB96: 13864.58 | BC96: 6 | BD96: 6259.9
A97: 1400000US09001074300 | B97: 9001074300 | C97: Census Tract 743, Fairfield County, Connecticut | D97: 40637 | E97: 3.2 | F97: 22716.774 | G97: 22.717 | H97: 0.091 | I97: 1 | J97: 0.909 | K97: 5 | L97: 1182 | M97: 0.62438444 | N97: 0.934 | O97: 5 | P97: 0.792 | Q97: 4 | R97: 5 | S97: 1 | T97: 1 | U97: 4267 | V97: 0.54178745 | W97: 7875.7822 | X97: 1 | Y97: 1825 | Z97: 36.66131 | AA97: 0.952 | AB97: 5 | AC97: 5 | AD97: 5 | AE97: Yes | AF97: Yes | AG97: 69.1943 | AH97: 0 | AI97: 0 | AM97: 0 | AN97: 0 | AR97: 0 | AX97: 9009125300 | AY97: 72329.134 | AZ97: 19316.36 | BA97: 19 | BB97: 16421.01 | BC97: 4 | BD97: 2895.35
A98: 1400000US09001074400 | B98: 9001074400 | C98: Census Tract 744, Fairfield County, Connecticut | D98: 46716 | E98: 3.11 | F98: 26490.213 | G98: 26.49 | H98: 0.127 | I98: 1 | J98: 0.873 | K98: 5 | L98: 1203 | M98: 0.54495597 | N98: 0.884 | O98: 5 | P98: 0.76 | Q98: 4 | R98: 5 | S98: 1 | T98: 1 | U98: 4168 | V98: 0.74169031 | W98: 5619.5961 | X98: 1 | Y98: 1817 | Z98: 40.057319 | AA98: 0.969 | AB98: 5 | AC98: 5 | AD98: 5 | AE98: Yes | AF98: Yes | AG98: 0 | AH98: 20133.35 | AI98: 9 | AJ98: 5 | AK98: 4 | AL98: 0 | AM98: 3501.35 | AN98: 25 | AO98: 7 | AP98: 17 | AQ98: 1 | AR98: 6632 | AX98: 9009125400 | AY98: 50934.989 | AZ98: 19181.37 | BA98: 13 | BB98: 9683.37 | BC98: 9 | BD98: 9498
A99: 1400000US09001074400 | B99: 9001074400 | C99: Census Tract 744, Fairfield County, Connecticut | D99: 46716 | E99: 3.11 | F99: 26490.213 | G99: 26.49 | H99: 0.127 | I99: 1 | J99: 0.873 | K99: 5 | L99: 1203 | M99: 0.54495597 | N99: 0.884 | O99: 5 | P99: 0.76 | Q99: 4 | R99: 5 | S99: 1 | T99: 1 | U99: 4168 | V99: 0.74169031 | W99: 5619.5961 | X99: 1 | Y99: 1817 | Z99: 40.057319 | AA99: 0.969 | AB99: 5 | AC99: 5 | AD99: 5 | AE99: Yes | AF99: Yes | AG99: 54299.358 | AH99: 0 | AI99: 0 | AM99: 0 | AN99: 0 | AR99: 0 | AX99: 9009130101 | AY99: 226.7872 | AZ99: 0 | BA99: 0 | BB99: 0 | BC99: 0 | BD99: 0
A100: 1400000US09001080100 | B100: 9001080100 | C100: Census Tract 801, Fairfield County, Connecticut | D100: 72464 | E100: 2.97 | F100: 42047.878 | G100: 42.048 | H100: 0.323 | I100: 2 | J100: 0.677 | K100: 4 | L100: 1368 | M100: 0.3904121 | N100: 0.665 | O100: 4 | P100: 0.589 | Q100: 3 | R100: 4 | S100: 1 | T100: 1 | U100: 4843 | V100: 0.46095001 | W100: 10506.562 | X100: 1 | Y100: 1221 | Z100: 23.507894 | AA100: 0.824 | AB100: 5 | AC100: 4.5 | AD100: 5 | AE100: No | AF100: No | AG100: 255.449 | AH100: 0 | AI100: 0 | AM100: 0 | AN100: 0 | AR100: 0 | AX100: 9009130102 | AY100: 151.18 | AZ100: 0 | BA100: 0 | BB100: 0 | BC100: 0 | BD100: 0
...

Sheet Sheet2
A1: id | B1: tract | C1: Geographic Area Name | D1: Income <=60 %SMI? | E1: Income <=80% SMI
A2: 1400000US09001010101 | B2: 9001010101 | C2: Census Tract 101.01, Fairfield County, Connecticut | D2: No | E2: No
A3: 1400000US09001010102 | B3: 9001010102 | C3: Census Tract 101.02, Fairfield County, Connecticut | D3: No | E3: No
A4: 1400000US09001010201 | B4: 9001010201 | C4: Census Tract 102.01, Fairfield County, Connecticut | D4: No | E4: No
A5: 1400000US09001010202 | B5: 9001010202 | C5: Census Tract 102.02, Fairfield County, Connecticut | D5: No | E5: No
A6: 1400000US09001010300 | B6: 9001010300 | C6: Census Tract 103, Fairfield County, Connecticut | D6: No | E6: No
A7: 1400000US09001010400 | B7: 9001010400 | C7: Census Tract 104, Fairfield County, Connecticut | D7: No | E7: No
A8: 1400000US09001010500 | B8: 9001010500 | C8: Census Tract 105, Fairfield County, Connecticut | D8: No | E8: No
A9: 1400000US09001010600 | B9: 9001010600 | C9: Census Tract 106, Fairfield County, Connecticut | D9: No | E9: No
A10: 1400000US09001010700 | B10: 9001010700 | C10: Census Tract 107, Fairfield County, Connecticut | D10: No | E10: Yes
A11: 1400000US09001010800 | B11: 9001010800 | C11: Census Tract 108, Fairfield County, Connecticut | D11: No | E11: No
A12: 1400000US09001010900 | B12: 9001010900 | C12: Census Tract 109, Fairfield County, Connecticut | D12: No | E12: No
A13: 1400000US09001011000 | B13: 9001011000 | C13: Census Tract 110, Fairfield County, Connecticut | D13: No | E13: No
... A823: 1400000US09015907300 | B823: 9015907300 | C823: Census Tract 9073, Windham County, Connecticut | D823: No | E823: No

Sheet Diversity index Calcs
A1: id | B1: tract | C1: Geographic Area Name | D1: Estimate!!Occupied housing units!!Occupied housing units!!HOUSEHOLD INCOME IN THE PAST 12 MONTHS (IN 2019 INFLATION-ADJUSTED DOLLARS)!!Median household income (dollars) 250000 = 250000+ | E1: Estimate!!HOUSEHOLDS BY TYPE!!Total households!!Average household size | F1: Household Size Adjusted income = (Household Income)/(Household Size)^N N =1/2 | G1: adjusted income (thousands of $) | H1: incomee percentile | I1: Income Rank | J1: reverse income percentile | K1: REVERSE income Rank | L1: median census housing cost | M1: housing cost as percentage of income | N1: Housing cost rank as fraction of median income percentile | O1: housing cost rank | P1: Housing cost percentile | Q1: Housing cost rank on absolute housing cost | R1: Combined affluence rank | S1: CTRUCA.Primary RUCA Code 2010 | T1: CTRUCA.Secondary RUCA Code, 2010 (see errata) | U1: CTRUCA.Tract Population, 2010 | V1: CTRUCA.Land Area (square miles), 2010 | W1: CTRUCA.Population Density (per square mile), 2010 | X1: rural rank | Y1: racialdiversitytable.POC population | Z1: racialdiversitytable.POC % of population | AA1: racialdiversitytable.percentile rank | AB1: racial diversity index | AC1: composit index | AD1: rounded composite | AE1: Income <=60 %SMI? | AF1: Income <=80% SMI
A2: 1400000US09001010101 | B2: 9001010101 | C2: Census Tract 101.01, Fairfield County, Connecticut | D2: 176875 | E2: 2.93 | F2: 103331.48 | G2: 103.331 | H2: 0.95 | I2: 5 | J2: 0.05 | K2: 1 | L2: 3267 | M2: 0.37940036 | N2: 0.63 | O2: 4 | P2: 0.036 | Q2: 1 | R2: 1 | S2: 1 | T2: 1 | U2: 4476 | V2: 12.643857 | W2: 354.00589 | X2: 1 | Y2: 281 | Z2: 6.7629362 | AA2: 0.218 | AB2: 2 | AC2: 1.5 | AD2: =ROUNDUP(AC2,0) -> 2 | AE2: =IF(Table4[[#This Row],[Estimate!!Occupied housing units!!Occupied housing units!!HOUSEHOLD INCOME IN THE PAST 12 MONTHS (IN 2019 INFLATION-ADJUSTED DOLLARS)!!Median household income (dollars) 250000 = 250000+]] <= 0.6 * 78444, "Yes", "No") -> No | AF2: =IF(Table4[[#This Row],[Estimate!!Occupied housing units!!Occupied housing units!!HOUSEHOLD INCOME IN THE PAST 12 MONTHS (IN 2019 INFLATION-ADJUSTED DOLLARS)!!Median household income (dollars) 250000 = 250000+]] <= 0.8 * 78444, "Yes", "No") -> No
A3: 1400000US09001010102 | B3: 9001010102 | C3: Census Tract 101.02, Fairfield County, Connecticut | D3: 250000 | E3: 3.16 | F3: 140635.99 | G3: 140.636 | H3: 0.987 | I3: 5 | J3: 0.013 | K3: 1 | L3: 4000 | M3: 0.34130667 | N3: 0.427 | O3: 3 | P3: 0.011 | Q3: 1 | R3: 1 | S3: 1 | T3: 1 | U3: 4330 | V3: 12.579912 | W3: 344.19955 | X3: 1 | Y3: 523 | Z3: 12.020225 | AA3: 0.485 | AB3: 3 | AC3: 2 | AD3: =ROUNDUP(AC3,0) -> 2 | AE3: =IF(Table4[[#This Row],[Estimate!!Occupied housing units!!Occupied housing units!!HOUSEHOLD INCOME IN THE PAST 12 MONTHS (IN 2019 INFLATION-ADJUSTED DOLLARS)!!Median household income (dollars) 250000 = 250000+]] <= 0.6 * 78444, "Yes", "No") -> No | AF3: =IF(Table4[[#This Row],[Estimate!!Occupied housing units!!Occupied housing units!!HOUSEHOLD INCOME IN THE PAST 12 MONTHS (IN 2019 INFLATION-ADJUSTED DOLLARS)!!Median household income (dollars) 250000 = 250000+]] <= 0.8 * 78444, "Yes", "No") -> No
A4: 1400000US09001010201 | B4: 9001010201 | C4: Census Tract 102.01, Fairfield County, Connecticut | D4: 250000 | E4: 3.16 | F4: 140635.99 | G4: 140.636 | H4: 0.987 | I4: 5 | J4: 0.013 | K4: 1 | L4: 3523 | M4: 0.30060585 | N4: 0.173 | O4: 1 | P4: 0.025 | Q4: 1 | R4: 1 | S4: 1 | T4: 1 | U4: 3421 | V4: 4.3448549 | W4: 787.36807 | X4: 1 | Y4: 364 | Z4: 10.441767 | AA4: 0.404 | AB4: 3 | AC4: 2 | AD4: =ROUNDUP(AC4,0) -> 2 | AE4: =IF(Table4[[#This Row],[Estimate!!Occupied housing units!!Occupied housing units!!HOUSEHOLD INCOME IN THE PAST 12 MONTHS (IN 2019 INFLATION-ADJUSTED DOLLARS)!!Median household income (dollars) 250000 = 250000+]] <= 0.6 * 78444, "Yes", "No") -> No | AF4: =IF(Table4[[#This Row],[Estimate!!Occupied housing units!!Occupied housing units!!HOUSEHOLD INCOME IN THE PAST 12 MONTHS (IN 2019 INFLATION-ADJUSTED DOLLARS)!!Median household income (dollars) 250000 = 250000+]] <= 0.8 * 78444, "Yes", "No") -> No
A5: 1400000US09001010202 | B5: 9001010202 | C5: Census Tract 102.02, Fairfield County, Connecticut | D5: 222839 | E5: 2.91 | F5: 130630.54 | G5: 130.631 | H5: 0.976 | I5: 5 | J5: 0.024 | K5: 1 | L5: 3250 | M5: 0.29855194 | N5: 0.164 | O5: 1 | P5: 0.037 | Q5: 1 | R5: 1 | S5: 1 | T5: 1 | U5: 5359 | V5: 3.7611201 | W5: 1424.8415 | X5: 1 | Y5: 1002 | Z5: 18.771075 | AA5: 0.712 | AB5: 4 | AC5: 2.5 | AD5: =ROUNDUP(AC5,0) -> 3 | AE5: =IF(Table4[[#This Row],[Estimate!!Occupied housing units!!Occupied housing units!!HOUSEHOLD INCOME IN THE PAST 12 MONTHS (IN 2019 INFLATION-ADJUSTED DOLLARS)!!Median household income (dollars) 250000 = 250000+]] <= 0.6 * 78444, "Yes", "No") -> No | AF5: =IF(Table4[[#This Row],[Estimate!!Occupied housing units!!Occupied housing units!!HOUSEHOLD INCOME IN THE PAST 12 MONTHS (IN 2019 INFLATION-ADJUSTED DOLLARS)!!Median household income (dollars) 250000 = 250000+]] <= 0.8 * 78444, "Yes", "No") -> No
A6: 1400000US09001010300 | B6: 9001010300 | C6: Census Tract 103, Fairfield County, Connecticut | D6: 238750 | E6: 2.72 | F6: 144763.45 | G6: 144.763 | H6: 0.998 | I6: 5 | J6: 0.002 | K6: 1 | L6: 3541 | M6: 0.29352713 | N6: 0.138 | O6: 1 | P6: 0.024 | Q6: 1 | R6: 1 | S6: 1 | T6: 1 | U6: 4010 | V6: 3.7096655 | W6: 1080.96 | X6: 1 | Y6: 382 | Z6: 10.10582 | AA6: 0.387 | AB6: 2 | AC6: 1.5 | AD6: =ROUNDUP(AC6,0) -> 2 | AE6: =IF(Table4[[#This Row],[Estimate!!Occupied housing units!!Occupied housing units!!HOUSEHOLD INCOME IN THE PAST 12 MONTHS (IN 2019 INFLATION-ADJUSTED DOLLARS)!!Median household income (dollars) 250000 = 250000+]] <= 0.6 * 78444, "Yes", "No") -> No | AF6: =IF(Table4[[#This Row],[Estimate!!Occupied housing units!!Occupied housing units!!HOUSEHOLD INCOME IN THE PAST 12 MONTHS (IN 2019 INFLATION-ADJUSTED DOLLARS)!!Median household income (dollars) 250000 = 250000+]] <= 0.8 * 78444, "Yes", "No") -> No
A7: 1400000US09001010400 | B7: 9001010400 | C7: Census Tract 104, Fairfield County, Connecticut | D7: 116222 | E7: 2.77 | F7: 69831.032 | G7: 69.831 | H7: 0.801 | I7: 5 | J7: 0.199 | K7: 1 | L7: 1923 | M7: 0.3304548 | N7: 0.362 | O7: 2 | P7: 0.198 | Q7: 1 | R7: 1 | S7: 1 | T7: 1 | U7: 5290 | V7: 1.04174 | W7: 5078.0427 | X7: 1 | Y7: 622 | Z7: 10.725987 | AA7: 0.413 | AB7: 3 | AC7: 2 | AD7: =ROUNDUP(AC7,0) -> 2 | AE7: =IF(Table4[[#This Row],[Estimate!!Occupied housing units!!Occupied housing units!!HOUSEHOLD INCOME IN THE PAST 12 MONTHS (IN 2019 INFLATION-ADJUSTED DOLLARS)!!Median household income (dollars) 250000 = 250000+]] <= 0.6 * 78444, "Yes", "No") -> No | AF7: =IF(Table4[[#This Row],[Estimate!!Occupied housing units!!Occupied housing units!!HOUSEHOLD INCOME IN THE PAST 12 MONTHS (IN 2019 INFLATION-ADJUSTED DOLLARS)!!Median household income (dollars) 250000 = 250000+]] <= 0.8 * 78444, "Yes", "No") -> No
A8: 1400000US09001010500 | B8: 9001010500 | C8: Census Tract 105, Fairfield County, Connecticut | D8: 91556 | E8: 2.55 | F8: 57334.591 | G8: 57.335 | H8: 0.6 | I8: 3 | J8: 0.4 | K8: 2 | L8: 1979 | M8: 0.41420022 | N8: 0.71 | O8: 4 | P8: 0.171 | Q8: 1 | R8: 2 | S8: 1 | T8: 1 | U8: 5494 | V8: 0.70141483 | W8: 7832.74 | X8: 1 | Y8: 876 | Z8: 14.897959 | AA8: 0.59 | AB8: 3 | AC8: 2.5 | AD8: =ROUNDUP(AC8,0) -> 3 | AE8: =IF(Table4[[#This Row],[Estimate!!Occupied housing units!!Occupied housing units!!HOUSEHOLD INCOME IN THE PAST 12 MONTHS (IN 2019 INFLATION-ADJUSTED DOLLARS)!!Median household income (dollars) 250000 = 250000+]] <= 0.6 * 78444, "Yes", "No") -> No | AF8: =IF(Table4[[#This Row],[Estimate!!Occupied housing units!!Occupied housing units!!HOUSEHOLD INCOME IN THE PAST 12 MONTHS (IN 2019 INFLATION-ADJUSTED DOLLARS)!!Median household income (dollars) 250000 = 250000+]] <= 0.8 * 78444, "Yes", "No") -> No
A9: 1400000US09001010600 | B9: 9001010600 | C9: Census Tract 106, Fairfield County, Connecticut | D9: 104868 | E9: 1.94 | F9: 75290.836 | G9: 75.291 | H9: 0.852 | I9: 5 | J9: 0.148 | K9: 1 | L9: 2018 | M9: 0.32163277 | N9: 0.311 | O9: 2 | P9: 0.16 | Q9: 1 | R9: 1 | S9: 1 | T9: 1 | U9: 1845 | V9: 0.34099849 | W9: 5410.5811 | X9: 1 | Y9: 284 | Z9: 13.773036 | AA9: 0.56 | AB9: 3 | AC9: 2 | AD9: =ROUNDUP(AC9,0) -> 2 | AE9: =IF(Table4[[#This Row],[Estimate!!Occupied housing units!!Occupied housing units!!HOUSEHOLD INCOME IN THE PAST 12 MONTHS (IN 2019 INFLATION-ADJUSTED DOLLARS)!!Median household income (dollars) 250000 = 250000+]] <= 0.6 * 78444, "Yes", "No") -> No | AF9: =IF(Table4[[#This Row],[Estimate!!Occupied housing units!!Occupied housing units!!HOUSEHOLD INCOME IN THE PAST 12 MONTHS (IN 2019 INFLATION-ADJUSTED DOLLARS)!!Median household income (dollars) 250000 = 250000+]] <= 0.8 * 78444, "Yes", "No") -> No
A10: 1400000US09001010700 | B10: 9001010700 | C10: Census Tract 107, Fairfield County, Connecticut | D10: 61667 | E10: 2.13 | F10: 42253.532 | G10: 42.254 | H10: 0.325 | I10: 2 | J10: 0.675 | K10: 4 | L10: 1586 | M10: 0.45042388 | N10: 0.785 | O10: 4 | P10: 0.401 | Q10: 3 | R10: 4 | S10: 1 | T10: 1 | U10: 3579 | V10: 0.71631143 | W10: 4996.4301 | X10: 1 | Y10: 526 | Z10: 14.590846 | AA10: 0.583 | AB10: 3 | AC10: 3.5 | AD10: =ROUNDUP(AC10,0) -> 4 | AE10: =IF(Table4[[#This Row],[Estimate!!Occupied housing units!!Occupied housing units!!HOUSEHOLD INCOME IN THE PAST 12 MONTHS (IN 2019 INFLATION-ADJUSTED DOLLARS)!!Median household income (dollars) 250000 = 250000+]] <= 0.6 * 78444, "Yes", "No") -> No | AF10: =IF(Table4[[#This Row],[Estimate!!Occupied housing units!!Occupied housing units!!HOUSEHOLD INCOME IN THE PAST 12 MONTHS (IN 2019 INFLATION-ADJUSTED DOLLARS)!!Median household income (dollars) 250000 = 250000+]] <= 0.8 * 78444, "Yes", "No") -> Yes
A11: 1400000US09001010800 | B11: 9001010800 | C11: Census Tract 108, Fairfield County, Connecticut | D11: 136495 | E11: 2.6 | F11: 84650.605 | G11: 84.651 | H11: 0.905 | I11: 5 | J11: 0.095 | K11: 1 | L11: 2403 | M11: 0.3406473 | N11: 0.419 | O11: 3 | P11: 0.089 | Q11: 1 | R11: 1 | S11: 1 | T11: 1 | U11: 3388 | V11: 0.75104402 | W11: 4511.0538 | X11: 1 | Y11: 421 | Z11: 11.855815 | AA11: 0.473 | AB11: 3 | AC11: 2 | AD11: =ROUNDUP(AC11,0) -> 2 | AE11: =IF(Table4[[#This Row],[Estimate!!Occupied housing units!!Occupied housing units!!HOUSEHOLD INCOME IN THE PAST 12 MONTHS (IN 2019 INFLATION-ADJUSTED DOLLARS)!!Median household income (dollars) 250000 = 250000+]] <= 0.6 * 78444, "Yes", "No") -> No | AF11: =IF(Table4[[#This Row],[Estimate!!Occupied housing units!!Occupied housing units!!HOUSEHOLD INCOME IN THE PAST 12 MONTHS (IN 2019 INFLATION-ADJUSTED DOLLARS)!!Median household income (dollars) 250000 = 250000+]] <= 0.8 * 78444, "Yes", "No") -> No
A12: 1400000US09001010900 | B12: 9001010900 | C12: Census Tract 109, Fairfield County, Connecticut | D12: 164063 | E12: 2.89 | F12: 96507.647 | G12: 96.508 | H12: 0.939 | I12: 5 | J12: 0.061 | K12: 1 | L12: 2436 | M12: 0.30289828 | N12: 0.19 | O12: 1 | P12: 0.084 | Q12: 1 | R12: 1 | S12: 1 | T12: 1 | U12: 4870 | V12: 0.99412352 | W12: 4898.7876 | X12: 1 | Y12: 1291 | Z12: 24.427625 | AA12: 0.815 | AB12: 5 | AC12: 3 | AD12: =ROUNDUP(AC12,0) -> 3 | AE12: =IF(Table4[[#This Row],[Estimate!!Occupied housing units!!Occupied housing units!!HOUSEHOLD INCOME IN THE PAST 12 MONTHS (IN 2019 INFLATION-ADJUSTED DOLLARS)!!Median household income (dollars) 250000 = 250000+]] <= 0.6 * 78444, "Yes", "No") -> No | AF12: =IF(Table4[[#This Row],[Estimate!!Occupied housing units!!Occupied housing units!!HOUSEHOLD INCOME IN THE PAST 12 MONTHS (IN 2019 INFLATION-ADJUSTED DOLLARS)!!Median household income (dollars) 250000 = 250000+]] <= 0.8 * 78444, "Yes", "No") -> No
A13: 1400000US09001011000 | B13: 9001011000 | C13: Census Tract 110, Fairfield County, Connecticut | D13: 236000 | E13: 3.19 | F13: 132134.63 | G13: 132.135 | H13: 0.978 | I13: 5 | J13: 0.022 | K13: 1 | L13: 3348 | M13: 0.30405352 | N13: 0.195 | O13: 1 | P13: 0.028 | Q13: 1 | R13: 1 | S13: 1 | T13: 1 | U13: 5263 | V13: 1.7178944 | W13: 3063.6341 | X13: 1 | Y13: 543 | Z13: 9.7767375 | AA13: 0.373 | AB13: 2 | AC13: 1.5 | AD13: =ROUNDUP(AC13,0) -> 2 | AE13: =IF(Table4[[#This Row],[Estimate!!Occupied housing units!!Occupied housing units!!HOUSEHOLD INCOME IN THE PAST 12 MONTHS (IN 2019 INFLATION-ADJUSTED DOLLARS)!!Median household income (dollars) 250000 = 250000+]] <= 0.6 * 78444, "Yes", "No") -> No | AF13: =IF(Table4[[#This Row],[Estimate!!Occupied housing units!!Occupied housing units!!HOUSEHOLD INCOME IN THE PAST 12 MONTHS (IN 2019 INFLATION-ADJUSTED DOLLARS)!!Median household income (dollars) 250000 = 250000+]] <= 0.8 * 78444, "Yes", "No") -> No
... A823: 1400000US09015907300 | B823: 9015907300 | C823: Census Tract 9073, Windham County, Connecticut | D823: 69167 | E823: 2.51 | F823: 43657.823 | G823: 43.658 | H823: 0.347 | I823: 2 | J823: 0.653 | K823: 4 | L823: 1138 | M823: 0.31279617 | N823: 0.24 | O823: 2 | P823: 0.828 | Q823: 5 | R823: 5 | S823: 2 | T823: 2 | U823: 5486 | V823: 15.633348 | W823: 350.91652 | X823: 2 | Y823: 541 | Z823: 10.964734 | AA823: 1 | AB823: 5 | AC823: 5 | AD823: =ROUNDUP(AC823,0) -> 5 | AE823: =IF(Table4[[#This Row],[Estimate!!Occupied housing units!!Occupied housing units!!HOUSEHOLD INCOME IN THE PAST 12 MONTHS (IN 2019 INFLATION-ADJUSTED DOLLARS)!!Median household income (dollars) 250000 = 250000+]] <= 0.6 * 78444, "Yes", "No") -> No | AF823: =IF(Table4[[#This Row],[Estimate!!Occupied housing units!!Occupied housing units!!HOUSEHOLD INCOME IN THE PAST 12 MONTHS (IN 2019 INFLATION-ADJUSTED DOLLARS)!!Median household income (dollars) 250000 = 250000+]] <= 0.8 * 78444, "Yes", "No") -> No

Sheet Cover Page
A1: CGS 16-245(m) Section 101
A2: C&LM Compliance Items 8 and 9
A3: Equitable Distribution
A5: Instructions: | B5: 1.) Please fill out the yellow highlighted sections below
B7: 2.) Please fill out the tabs in order of occurrence
A9: Contact: | B9: Julia Dumaine
B10: Bureau of Energy and Technology Policy
B11: julia.dumaine@ct.gov
B12: (860)827-2869
A15: Company: | B15: The United Illuminating Company
A17: Year: | B17: 2019
A19: Submission Date: | B19: 44012

Sheet 1.) CLM Reference
A1: UI 2019
A2: Totals | B2: All Customers | E2: Customers < 100kW | H2: Customers > 100kW
B3: Combined | C3: Residential | D3: C&I | E3: Combined | F3: Residential | G3: C&I | H3: Combined | I3: Residential | J3: C&I
A4: CLM Collections | B4: =SUM(C4:D4) -> 29100613 | C4: =F4+I4 -> 12285079 | D4: =G4+J4 -> 16815533 | E4: =SUM(F4:G4) -> 17547919 | F4: ='2.) Small Load'!J423 -> 12129793 | G4: ='2.) Small Load'!O423 -> 5418126 | H4: =SUM(I4:J4) -> 11552694 | I4: ='3.) Large Load'!I346 -> 155286.23 | J4: ='3.) Large Load'!M346 -> 11397407
A5: Incentives Disbursements | B5: =SUM(C5:D5) -> 16800988 | C5: =F5+I5 -> 8495344.3 | D5: =G5+J5 -> 8305643.7 | E5: =SUM(F5:G5) -> 11650461 | F5: ='2.) Small Load'!L423 -> 8494544.3 | G5: ='2.) Small Load'!Q423 -> 3155916.3 | H5: =SUM(I5:J5) -> 5150527.4 | I5: ='3.) Large Load'!K346 -> 800 | J5: ='3.) Large Load'!O346 -> 5149727.4
A7: Note
A8: 2018: Total CLM Collections were $30M, but $11.7M of that was earmarked for the diversions to the CT General Fund.

Sheet Sheet1
A1: Distressed Tract1 | B1: (Multiple Items)
A2: Equitable | B2: N/A
A4: Row Labels | B4: Count of Census Tract | C4: Sum of CLM $ Collected | D4: Sum of % of Total CLM $ Collected | E4: Sum of Incentive Disbursements | F4: Sum of % of Total Incentive Disbursements
A5: 09001060100 | B5: 2 | C5: 106.9083 | D5: 3.6737474e-06 | E5: 0 | F5: 0
A6: 09001070100 | B6: 1 | C6: 0 | D6: 0 | E6: 11586.15 | F6: 0.00068961123
A7: 09001070200 | B7: 2 | C7: 0 | D7: 0 | E7: 9420.39 | F7: 0.00056070453
A8: 09001070300 | B8: 1 | C8: 0 | D8: 0 | E8: 213519.3 | F8: 0.012708735
A9: 09001070400 | B9: 2 | C9: 50.8641 | D9: 1.7478704e-06 | E9: 2503.53 | F9: 0.00014901088
A10: 09001070500 | B10: 1 | C10: 0 | D10: 0 | E10: 16596.99 | F10: 0.00098785798
A11: 09001070600 | B11: 1 | C11: 0 | D11: 0 | E11: 110631.34 | F11: 0.0065848116
A12: 09001070900 | B12: 1 | C12: 0 | D12: 0 | E12: 30327.01 | F12: 0.001805073
A13: 09001071000 | B13: 1 | C13: 0 | D13: 0 | E13: 17169.5 | F13: 0.0010219339
A14: 09001071200 | B14: 1 | C14: 0 | D14: 0 | E14: 20104.86 | F14: 0.0011966475
A15: 09001071300 | B15: 1 | C15: 0 | D15: 0 | E15: 2772.32 | F15: 0.00016500934
A16: 09001071600 | B16: 1 | C16: 0 | D16: 0 | E16: 1330.85 | F16: 7.9212604e-05
... A102: Grand Total | B102: 155 | C102: 3269.2545 | D102: 0.00011234315 | E102: 5705799.2 | F102: 0.33961094

Sheet 2.) Small Load
A1: EQUITABLE DISTRIBUTION OF FUNDS
A3: UI 2019 | D3: Customers < 100kW
D4: Combined | J4: Residential | O4: C&I
A5: Census Tract | B5: Town | C5: Distressed Tract1 | D5: CLM $ Collected | E5: % of Total CLM $ Collected | F5: Incentive Disbursements | G5: % of Total Incentive Disbursements | H5: Column1 | I5: Equitable | J5: Residential CLM $ Collected | K5: % of Total Residential CLM $ Collected | L5: Residential Incentive Disbursements | M5: % of Total Residential Incentive Disbursements | N5: Equitable 2 | O5: C&I CLM $ Collected | P5: % of Total C&I CLM $ Collected | Q5: C&I Incentive Disbursements | R5: % of TotalC&I Incentive Disbursements | S5: Equitable 3 | U5: Census Tract | V5: tract | W5: Town | X5: Distressed Tract1 | Y5: CLM $ Collected | Z5: % of Total CLM $ Collected | AA5: Incentive Disbursements | AB5: % of Total Incentive Disbursements | AC5: Column1 | AD5: Equitable | AE5: Residential CLM $ Collected | AF5: % of Total Residential CLM $ Collected | AG5: Residential Incentive Disbursements | AH5: % of Total Residential Incentive Disbursements | AI5: Equitable 2 | AJ5: C&I CLM $ Collected | AK5: % of Total C&I CLM $ Collected | AL5: C&I Incentive Disbursements | AM5: % of TotalC&I Incentive Disbursements | AN5: Equitable 3
A6: 09001055100 | B6: Easton | C6: No | D6: =Table3[[#This Row],[Residential CLM $ Collected]]+Table3[[#This Row],[C&I CLM $ Collected]] -> 394.428 | E6: =Table3[[#This Row],[CLM $ Collected ]]/'1.) CLM Reference'!$B$4 -> 1.3553941e-05 | F6: =Table3[[#This Row],[Residential Incentive Disbursements]]+Table3[[#This Row],[C&I Incentive Disbursements]] -> 0 | G6: =Table3[[#This Row],[Incentive Disbursements]]/'1.) CLM Reference'!$B$5 -> 0 | H6: =IF((Table3[[#This Row],[Incentive Disbursements]]>=0.5*Table3[[#This Row],[CLM $ Collected ]]),"YES",IF(Table3[[#This Row],[Incentive Disbursements]]<=1, "N/A", "NO")) -> N/A | I6: =IF(ROUND(E6,5)<0.00001,"N/A",IF(ROUND(E6,5)<=ROUND(G6,5),"YES","NO")) -> NO | J6: 394.428 | K6: =Table3[[#This Row],[CLM $ Collected ]]/'1.) CLM Reference'!$B$4 -> 1.3553941e-05 | L6: 0 | M6: =Table3[[#This Row],[Incentive Disbursements]]/'1.) CLM Reference'!$B$5 -> 0 | N6: =IF(ROUND(K6,5)<0.00001,"N/A",IF(ROUND(K6,5)<=ROUND(M6,5),"YES","NO")) -> NO | O6: 0 | P6: =Table3[[#This Row],[CLM $ Collected ]]/'1.) CLM Reference'!$B$4 -> 1.3553941e-05 | Q6: 0 | R6: =Table3[[#This Row],[Incentive Disbursements]]/'1.) CLM Reference'!$B$5 -> 0 | S6: =IF(ROUND(P6,5)<0.00001,"N/A",IF(ROUND(P6,5)<=ROUND(R6,5),"YES","NO")) -> NO | U6: 09001055100 | V6: =RIGHT(Table5[[#This Row],[Census Tract]],10) -> 9001055100 | W6: Easton | X6: No | Y6: 394.428 | Z6: 1.3553941e-05 | AA6: 0 | AB6: 0 | AC6: N/A | AD6: NO | AE6: 394.428 | AF6: 1.3553941e-05 | AG6: 0 | AH6: 0 | AI6: NO | AJ6: 0 | AK6: 1.3553941e-05 | AL6: 0 | AM6: 0 | AN6: NO
A7: 09001055200 | B7: Easton | C7: No | D7: =Table3[[#This Row],[Residential CLM $ Collected]]+Table3[[#This Row],[C&I CLM $ Collected]] -> 887.5106 | E7: =Table3[[#This Row],[CLM $ Collected ]]/'1.) CLM Reference'!$B$4 -> 3.0498004e-05 | F7: =Table3[[#This Row],[Residential Incentive Disbursements]]+Table3[[#This Row],[C&I Incentive Disbursements]] -> 0 | G7: =Table3[[#This Row],[Incentive Disbursements]]/'1.) CLM Reference'!$B$5 -> 0 | H7: =IF((Table3[[#This Row],[Incentive Disbursements]]>=0.5*Table3[[#This Row],[CLM $ Collected ]]),"YES",IF(Table3[[#This Row],[Incentive Disbursements]]<=1, "N/A", "NO")) -> N/A | I7: =IF(ROUND(E7,5)<0.00001,"N/A",IF(ROUND(E7,5)<=ROUND(G7,5),"YES","NO")) -> NO | J7: 887.5106 | K7: =Table3[[#This Row],[CLM $ Collected ]]/'1.) CLM Reference'!$B$4 -> 3.0498004e-05 | L7: 0 | M7: =Table3[[#This Row],[Incentive Disbursements]]/'1.) CLM Reference'!$B$5 -> 0 | N7: =IF(ROUND(K7,5)<0.00001,"N/A",IF(ROUND(K7,5)<=ROUND(M7,5),"YES","NO")) -> NO | O7: 0 | P7: =Table3[[#This Row],[CLM $ Collected ]]/'1.) CLM Reference'!$B$4 -> 3.0498004e-05 | Q7: 0 | R7: =Table3[[#This Row],[Incentive Disbursements]]/'1.) CLM Reference'!$B$5 -> 0 | S7: =IF(ROUND(P7,5)<0.00001,"N/A",IF(ROUND(P7,5)<=ROUND(R7,5),"YES","NO")) -> NO | U7: 09001055200 | V7: =RIGHT(Table5[[#This Row],[Census Tract]],10) -> 9001055200 | W7: Easton | X7: No | Y7: 887.5106 | Z7: 3.0498004e-05 | AA7: 0 | AB7: 0 | AC7: N/A | AD7: NO | AE7: 887.5106 | AF7: 3.0498004e-05 | AG7: 0 | AH7: 0 | AI7: NO | AJ7: 0 | AK7: 3.0498004e-05 | AL7: 0 | AM7: 0 | AN7: NO
A8: 09001060100 | B8: Bridgeport | C8: No | D8: =Table3[[#This Row],[Residential CLM $ Collected]]+Table3[[#This Row],[C&I CLM $ Collected]] -> 0.9029 | E8: =Table3[[#This Row],[CLM $ Collected ]]/'1.) CLM Reference'!$B$4 -> 3.1026838e-08 | F8: =Table3[[#This Row],[Residential Incentive Disbursements]]+Table3[[#This Row],[C&I Incentive Disbursements]] -> 0 | G8: =Table3[[#This Row],[Incentive Disbursements]]/'1.) CLM Reference'!$B$5 -> 0 | H8: =IF((Table3[[#This Row],[Incentive Disbursements]]>=0.5*Table3[[#This Row],[CLM $ Collected ]]),"YES",IF(Table3[[#This Row],[Incentive Disbursements]]<=1, "N/A", "NO")) -> N/A | I8: =IF(ROUND(E8,5)<0.00001,"N/A",IF(ROUND(E8,5)<=ROUND(G8,5),"YES","NO")) -> N/A | J8: 0 | K8: =Table3[[#This Row],[CLM $ Collected ]]/'1.) CLM Reference'!$B$4 -> 3.1026838e-08 | L8: 0 | M8: =Table3[[#This Row],[Incentive Disbursements]]/'1.) CLM Reference'!$B$5 -> 0 | N8: =IF(ROUND(K8,5)<0.00001,"N/A",IF(ROUND(K8,5)<=ROUND(M8,5),"YES","NO")) -> N/A | O8: 0.9029 | P8: =Table3[[#This Row],[CLM $ Collected ]]/'1.) CLM Reference'!$B$4 -> 3.1026838e-08 | Q8: 0 | R8: =Table3[[#This Row],[Incentive Disbursements]]/'1.) CLM Reference'!$B$5 -> 0 | S8: =IF(ROUND(P8,5)<0.00001,"N/A",IF(ROUND(P8,5)<=ROUND(R8,5),"YES","NO")) -> N/A | U8: 09001060100 | V8: =RIGHT(Table5[[#This Row],[Census Tract]],10) -> 9001060100 | W8: Bridgeport | X8: No | Y8: 0.9029 | Z8: 3.1026838e-08 | AA8: 0 | AB8: 0 | AC8: N/A | AD8: N/A | AE8: 0 | AF8: 3.1026838e-08 | AG8: 0 | AH8: 0 | AI8: N/A | AJ8: 0.9029 | AK8: 3.1026838e-08 | AL8: 0 | AM8: 0 | AN8: N/A
A9: 09001060100 | B9: Fairfield | C9: No | D9: =Table3[[#This Row],[Residential CLM $ Collected]]+Table3[[#This Row],[C&I CLM $ Collected]] -> 71392.777 | E9: =Table3[[#This Row],[CLM $ Collected ]]/'1.) CLM Reference'!$B$4 -> 0.0024533084 | F9: =Table3[[#This Row],[Residential Incentive Disbursements]]+Table3[[#This Row],[C&I Incentive Disbursements]] -> 20104.8 | G9: =Table3[[#This Row],[Incentive Disbursements]]/'1.) CLM Reference'!$B$5 -> 0.0011966439 | H9: =IF((Table3[[#This Row],[Incentive Disbursements]]>=0.5*Table3[[#This Row],[CLM $ Collected ]]),"YES",IF(Table3[[#This Row],[Incentive Disbursements]]<=1, "N/A", "NO")) -> NO | I9: =IF(ROUND(E9,5)<0.00001,"N/A",IF(ROUND(E9,5)<=ROUND(G9,5),"YES","NO")) -> NO | J9: 58128.328 | K9: =Table3[[#This Row],[CLM $ Collected ]]/'1.) CLM Reference'!$B$4 -> 0.0024533084 | L9: 19857.8 | M9: =Table3[[#This Row],[Incentive Disbursements]]/'1.) CLM Reference'!$B$5 -> 0.0011966439 | N9: =IF(ROUND(K9,5)<0.00001,"N/A",IF(ROUND(K9,5)<=ROUND(M9,5),"YES","NO")) -> NO | O9: 13264.449 | P9: =Table3[[#This Row],[CLM $ Collected ]]/'1.) CLM Reference'!$B$4 -> 0.0024533084 | Q9: 247 | R9: =Table3[[#This Row],[Incentive Disbursements]]/'1.) CLM Reference'!$B$5 -> 0.0011966439 | S9: =IF(ROUND(P9,5)<0.00001,"N/A",IF(ROUND(P9,5)<=ROUND(R9,5),"YES","NO")) -> NO | U9: 09001060100 | V9: =RIGHT(Table5[[#This Row],[Census Tract]],10) -> 9001060100 | W9: Fairfield | X9: No | Y9: 71392.777 | Z9: 0.0024533084 | AA9: 20104.8 | AB9: 0.0011966439 | AC9: NO | AD9: NO | AE9: 58128.328 | AF9: 0.0024533084 | AG9: 19857.8 | AH9: 0.0011966439 | AI9: NO | AJ9: 13264.449 | AK9: 0.0024533084 | AL9: 247 | AM9: 0.0011966439 | AN9: NO
A10: 09001060100 | B10: Trumbull | C10: No | D10: =Table3[[#This Row],[Residential CLM $ Collected]]+Table3[[#This Row],[C&I CLM $ Collected]] -> 106.0054 | E10: =Table3[[#This Row],[CLM $ Collected ]]/'1.) CLM Reference'!$B$4 -> 3.6427206e-06 | F10: =Table3[[#This Row],[Residential Incentive Disbursements]]+Table3[[#This Row],[C&I Incentive Disbursements]] -> 0 | G10: =Table3[[#This Row],[Incentive Disbursements]]/'1.) CLM Reference'!$B$5 -> 0 | H10: =IF((Table3[[#This Row],[Incentive Disbursements]]>=0.5*Table3[[#This Row],[CLM $ Collected ]]),"YES",IF(Table3[[#This Row],[Incentive Disbursements]]<=1, "N/A", "NO")) -> N/A | I10: =IF(ROUND(E10,5)<0.00001,"N/A",IF(ROUND(E10,5)<=ROUND(G10,5),"YES","NO")) -> N/A | J10: 0 | K10: =Table3[[#This Row],[CLM $ Collected ]]/'1.) CLM Reference'!$B$4 -> 3.6427206e-06 | L10: 0 | M10: =Table3[[#This Row],[Incentive Disbursements]]/'1.) CLM Reference'!$B$5 -> 0 | N10: =IF(ROUND(K10,5)<0.00001,"N/A",IF(ROUND(K10,5)<=ROUND(M10,5),"YES","NO")) -> N/A | O10: 106.0054 | P10: =Table3[[#This Row],[CLM $ Collected ]]/'1.) CLM Reference'!$B$4 -> 3.6427206e-06 | Q10: 0 | R10: =Table3[[#This Row],[Incentive Disbursements]]/'1.) CLM Reference'!$B$5 -> 0 | S10: =IF(ROUND(P10,5)<0.00001,"N/A",IF(ROUND(P10,5)<=ROUND(R10,5),"YES","NO")) -> N/A | U10: 09001060100 | V10: =RIGHT(Table5[[#This Row],[Census Tract]],10) -> 9001060100 | W10: Trumbull | X10: No | Y10: 106.0054 | Z10: 3.6427206e-06 | AA10: 0 | AB10: 0 | AC10: N/A | AD10: N/A | AE10: 0 | AF10: 3.6427206e-06 | AG10: 0 | AH10: 0 | AI10: N/A | AJ10: 106.0054 | AK10: 3.6427206e-06 | AL10: 0 | AM10: 0 | AN10: N/A
A11: 09001060200 | B11: Fairfield | C11: No | D11: =Table3[[#This Row],[Residential CLM $ Collected]]+Table3[[#This Row],[C&I CLM $ Collected]] -> 96972.012 | E11: =Table3[[#This Row],[CLM $ Collected ]]/'1.) CLM Reference'!$B$4 -> 0.0033323014 | F11: =Table3[[#This Row],[Residential Incentive Disbursements]]+Table3[[#This Row],[C&I Incentive Disbursements]] -> 31534.58 | G11: =Table3[[#This Row],[Incentive Disbursements]]/'1.) CLM Reference'!$B$5 -> 0.001876948 | H11: =IF((Table3[[#This Row],[Incentive Disbursements]]>=0.5*Table3[[#This Row],[CLM $ Collected ]]),"YES",IF(Table3[[#This Row],[Incentive Disbursements]]<=1, "N/A", "NO")) -> NO | I11: =IF(ROUND(E11,5)<0.00001,"N/A",IF(ROUND(E11,5)<=ROUND(G11,5),"YES","NO")) -> NO | J11: 78630.955 | K11: =Table3[[#This Row],[CLM $ Collected ]]/'1.) CLM Reference'!$B$4 -> 0.0033323014 | L11: 29656.58 | M11: =Table3[[#This Row],[Incentive Disbursements]]/'1.) CLM Reference'!$B$5 -> 0.001876948 | N11: =IF(ROUND(K11,5)<0.00001,"N/A",IF(ROUND(K11,5)<=ROUND(M11,5),"YES","NO")) -> NO | O11: 18341.057 | P11: =Table3[[#This Row],[CLM $ Collected ]]/'1.) CLM Reference'!$B$4 -> 0.0033323014 | Q11: 1878 | R11: =Table3[[#This Row],[Incentive Disbursements]]/'1.) CLM Reference'!$B$5 -> 0.001876948 | S11: =IF(ROUND(P11,5)<0.00001,"N/A",IF(ROUND(P11,5)<=ROUND(R11,5),"YES","NO")) -> NO | U11: 09001060200 | V11: =RIGHT(Table5[[#This Row],[Census Tract]],10) -> 9001060200 | W11: Fairfield | X11: No | Y11: 96972.012 | Z11: 0.0033323014 | AA11: 31534.58 | AB11: 0.001876948 | AC11: NO | AD11: NO | AE11: 78630.955 | AF11: 0.0033323014 | AG11: 29656.58 | AH11: 0.001876948 | AI11: NO | AJ11: 18341.057 | AK11: 0.0033323014 | AL11: 1878 | AM11: 0.001876948 | AN11: NO
A12: 09001060300 | B12: Fairfield | C12: No | D12: =Table3[[#This Row],[Residential CLM $ Collected]]+Table3[[#This Row],[C&I CLM $ Collected]] -> 100651.49 | E12: =Table3[[#This Row],[CLM $ Collected ]]/'1.) CLM Reference'!$B$4 -> 0.0034587413 | F12: =Table3[[#This Row],[Residential Incentive Disbursements]]+Table3[[#This Row],[C&I Incentive Disbursements]] -> 19540.71 | G12: =Table3[[#This Row],[Incentive Disbursements]]/'1.) CLM Reference'!$B$5 -> 0.0011630691 | H12: =IF((Table3[[#This Row],[Incentive Disbursements]]>=0.5*Table3[[#This Row],[CLM $ Collected ]]),"YES",IF(Table3[[#This Row],[Incentive Disbursements]]<=1, "N/A", "NO")) -> NO | I12: =IF(ROUND(E12,5)<0.00001,"N/A",IF(ROUND(E12,5)<=ROUND(G12,5),"YES","NO")) -> NO | J12: 92872.917 | K12: =Table3[[#This Row],[CLM $ Collected ]]/'1.) CLM Reference'!$B$4 -> 0.0034587413 | L12: 19540.71 | M12: =Table3[[#This Row],[Incentive Disbursements]]/'1.) CLM Reference'!$B$5 -> 0.0011630691 | N12: =IF(ROUND(K12,5)<0.00001,"N/A",IF(ROUND(K12,5)<=ROUND(M12,5),"YES","NO")) -> NO | O12: 7778.5729 | P12: =Table3[[#This Row],[CLM $ Collected ]]/'1.) CLM Reference'!$B$4 -> 0.0034587413 | Q12: 0 | R12: =Table3[[#This Row],[Incentive Disbursements]]/'1.) CLM Reference'!$B$5 -> 0.0011630691 | S12: =IF(ROUND(P12,5)<0.00001,"N/A",IF(ROUND(P12,5)<=ROUND(R12,5),"YES","NO")) -> NO | U12: 09001060300 | V12: =RIGHT(Table5[[#This Row],[Census Tract]],10) -> 9001060300 | W12: Fairfield | X12: No | Y12: 100651.49 | Z12: 0.0034587413 | AA12: 19540.71 | AB12: 0.0011630691 | AC12: NO | AD12: NO | AE12: 92872.917 | AF12: 0.0034587413 | AG12: 19540.71 | AH12: 0.0011630691 | AI12: NO | AJ12: 7778.5729 | AK12: 0.0034587413 | AL12: 0 | AM12: 0.0011630691 | AN12: NO
A13: 09001060400 | B13: Fairfield | C13: No | D13: =Table3[[#This Row],[Residential CLM $ Collected]]+Table3[[#This Row],[C&I CLM $ Collected]] -> 167953.61 | E13: =Table3[[#This Row],[CLM $ Collected ]]/'1.) CLM Reference'!$B$4 -> 0.0057714803 | F13: =Table3[[#This Row],[Residential Incentive Disbursements]]+Table3[[#This Row],[C&I Incentive Disbursements]] -> 16361.63 | G13: =Table3[[#This Row],[Incentive Disbursements]]/'1.) CLM Reference'!$B$5 -> 0.00097384928 | H13: =IF((Table3[[#This Row],[Incentive Disbursements]]>=0.5*Table3[[#This Row],[CLM $ Collected ]]),"YES",IF(Table3[[#This Row],[Incentive Disbursements]]<=1, "N/A", "NO")) -> NO | I13: =IF(ROUND(E13,5)<0.00001,"N/A",IF(ROUND(E13,5)<=ROUND(G13,5),"YES","NO")) -> NO | J13: 158569.58 | K13: =Table3[[#This Row],[CLM $ Collected ]]/'1.) CLM Reference'!$B$4 -> 0.0057714803 | L13: 16361.63 | M13: =Table3[[#This Row],[Incentive Disbursements]]/'1.) CLM Reference'!$B$5 -> 0.00097384928 | N13: =IF(ROUND(K13,5)<0.00001,"N/A",IF(ROUND(K13,5)<=ROUND(M13,5),"YES","NO")) -> NO | O13: 9384.0322 | P13: =Table3[[#This Row],[CLM $ Collected ]]/'1.) CLM Reference'!$B$4 -> 0.0057714803 | Q13: 0 | R13: =Table3[[#This Row],[Incentive Disbursements]]/'1.) CLM Reference'!$B$5 -> 0.00097384928 | S13: =IF(ROUND(P13,5)<0.00001,"N/A",IF(ROUND(P13,5)<=ROUND(R13,5),"YES","NO")) -> NO | U13: 09001060400 | V13: =RIGHT(Table5[[#This Row],[Census Tract]],10) -> 9001060400 | W13: Fairfield | X13: No | Y13: 167953.61 | Z13: 0.0057714803 | AA13: 16361.63 | AB13: 0.00097384928 | AC13: NO | AD13: NO | AE13: 158569.58 | AF13: 0.0057714803 | AG13: 16361.63 | AH13: 0.00097384928 | AI13: NO | AJ13: 9384.0322 | AK13: 0.0057714803 | AL13: 0 | AM13: 0.00097384928 | AN13: NO
A14: 09001060500 | B14: Fairfield | C14: No | D14: =Table3[[#This Row],[Residential CLM $ Collected]]+Table3[[#This Row],[C&I CLM $ Collected]] -> 77707.49 | E14: =Table3[[#This Row],[CLM $ Collected ]]/'1.) CLM Reference'!$B$4 -> 0.0026703043 | F14: =Table3[[#This Row],[Residential Incentive Disbursements]]+Table3[[#This Row],[C&I Incentive Disbursements]] -> 7351.8 | G14: =Table3[[#This Row],[Incentive Disbursements]]/'1.) CLM Reference'!$B$5 -> 0.00043758141 | H14: =IF((Table3[[#This Row],[Incentive Disbursements]]>=0.5*Table3[[#This Row],[CLM $ Collected ]]),"YES",IF(Table3[[#This Row],[Incentive Disbursements]]<=1, "N/A", "NO")) -> NO | I14: =IF(ROUND(E14,5)<0.00001,"N/A",IF(ROUND(E14,5)<=ROUND(G14,5),"YES","NO")) -> NO | J14: 71345.134 | K14: =Table3[[#This Row],[CLM $ Collected ]]/'1.) CLM Reference'!$B$4 -> 0.0026703043 | L14: 7351.8 | M14: =Table3[[#This Row],[Incentive Disbursements]]/'1.) CLM Reference'!$B$5 -> 0.00043758141 | N14: =IF(ROUND(K14,5)<0.00001,"N/A",IF(ROUND(K14,5)<=ROUND(M14,5),"YES","NO")) -> NO | O14: 6362.3551 | P14: =Table3[[#This Row],[CLM $ Collected ]]/'1.) CLM Reference'!$B$4 -> 0.0026703043 | Q14: 0 | R14: =Table3[[#This Row],[Incentive Disbursements]]/'1.) CLM Reference'!$B$5 -> 0.00043758141 | S14: =IF(ROUND(P14,5)<0.00001,"N/A",IF(ROUND(P14,5)<=ROUND(R14,5),"YES","NO")) -> NO | U14: 09001060500 | V14: =RIGHT(Table5[[#This Row],[Census Tract]],10) -> 9001060500 | W14: Fairfield | X14: No | Y14: 77707.49 | Z14: 0.0026703043 | AA14: 7351.8 | AB14: 0.00043758141 | AC14: NO | AD14: NO | AE14: 71345.134 | AF14: 0.0026703043 | AG14: 7351.8 | AH14: 0.00043758141 | AI14: NO | AJ14: 6362.3551 | AK14: 0.0026703043 | AL14: 0 | AM14: 0.00043758141 | AN14: NO
A15: 09001060600 | B15: Fairfield | C15: No | D15: =Table3[[#This Row],[Residential CLM $ Collected]]+Table3[[#This Row],[C&I CLM $ Collected]] -> 122971.58 | E15: =Table3[[#This Row],[CLM $ Collected ]]/'1.) CLM Reference'!$B$4 -> 0.0042257384 | F15: =Table3[[#This Row],[Residential Incentive Disbursements]]+Table3[[#This Row],[C&I Incentive Disbursements]] -> 95807 | G15: =Table3[[#This Row],[Incentive Disbursements]]/'1.) CLM Reference'!$B$5 -> 0.0057024623 | H15: =IF((Table3[[#This Row],[Incentive Disbursements]]>=0.5*Table3[[#This Row],[CLM $ Collected ]]),"YES",IF(Table3[[#This Row],[Incentive Disbursements]]<=1, "N/A", "NO")) -> YES | I15: =IF(ROUND(E15,5)<0.00001,"N/A",IF(ROUND(E15,5)<=ROUND(G15,5),"YES","NO")) -> YES | J15: 73188.417 | K15: =Table3[[#This Row],[CLM $ Collected ]]/'1.) CLM Reference'!$B$4 -> 0.0042257384 | L15: 6296 | M15: =Table3[[#This Row],[Incentive Disbursements]]/'1.) CLM Reference'!$B$5 -> 0.0057024623 | N15: =IF(ROUND(K15,5)<0.00001,"N/A",IF(ROUND(K15,5)<=ROUND(M15,5),"YES","NO")) -> YES | O15: 49783.158 | P15: =Table3[[#This Row],[CLM $ Collected ]]/'1.) CLM Reference'!$B$4 -> 0.0042257384 | Q15: 89511 | R15: =Table3[[#This Row],[Incentive Disbursements]]/'1.) CLM Reference'!$B$5 -> 0.0057024623 | S15: =IF(ROUND(P15,5)<0.00001,"N/A",IF(ROUND(P15,5)<=ROUND(R15,5),"YES","NO")) -> YES | U15: 09001060600 | V15: =RIGHT(Table5[[#This Row],[Census Tract]],10) -> 9001060600 | W15: Fairfield | X15: No | Y15: 122971.58 | Z15: 0.0042257384 | AA15: 95807 | AB15: 0.0057024623 | AC15: YES | AD15: YES | AE15: 73188.417 | AF15: 0.0042257384 | AG15: 6296 | AH15: 0.0057024623 | AI15: YES | AJ15: 49783.158 | AK15: 0.0042257384 | AL15: 89511 | AM15: 0.0057024623 | AN15: YES
A16: 09001060700 | B16: Fairfield | C16: No | D16: =Table3[[#This Row],[Residential CLM $ Collected]]+Table3[[#This Row],[C&I CLM $ Collected]] -> 117727.44 | E16: =Table3[[#This Row],[CLM $ Collected ]]/'1.) CLM Reference'!$B$4 -> 0.0040455315 | F16: =Table3[[#This Row],[Residential Incentive Disbursements]]+Table3[[#This Row],[C&I Incentive Disbursements]] -> 8336.04 | G16: =Table3[[#This Row],[Incentive Disbursements]]/'1.) CLM Reference'!$B$5 -> 0.00049616368 | H16: =IF((Table3[[#This Row],[Incentive Disbursements]]>=0.5*Table3[[#This Row],[CLM $ Collected ]]),"YES",IF(Table3[[#This Row],[Incentive Disbursements]]<=1, "N/A", "NO")) -> NO | I16: =IF(ROUND(E16,5)<0.00001,"N/A",IF(ROUND(E16,5)<=ROUND(G16,5),"YES","NO")) -> NO | J16: 98856.621 | K16: =Table3[[#This Row],[CLM $ Collected ]]/'1.) CLM Reference'!$B$4 -> 0.0040455315 | L16: 8336.04 | M16: =Table3[[#This Row],[Incentive Disbursements]]/'1.) CLM Reference'!$B$5 -> 0.00049616368 | N16: =IF(ROUND(K16,5)<0.00001,"N/A",IF(ROUND(K16,5)<=ROUND(M16,5),"YES","NO")) -> NO | O16: 18870.823 | P16: =Table3[[#This Row],[CLM $ Collected ]]/'1.) CLM Reference'!$B$4 -> 0.0040455315 | Q16: 0 | R16: =Table3[[#This Row],[Incentive Disbursements]]/'1.) CLM Reference'!$B$5 -> 0.00049616368 | S16: =IF(ROUND(P16,5)<0.00001,"N/A",IF(ROUND(P16,5)<=ROUND(R16,5),"YES","NO")) -> NO | U16: 09001060700 | V16: =RIGHT(Table5[[#This Row],[Census Tract]],10) -> 9001060700 | W16: Fairfield | X16: No | Y16: 117727.44 | Z16: 0.0040455315 | AA16: 8336.04 | AB16: 0.00049616368 | AC16: NO | AD16: NO | AE16: 98856.621 | AF16: 0.0040455315 | AG16: 8336.04 | AH16: 0.00049616368 | AI16: NO | AJ16: 18870.823 | AK16: 0.0040455315 | AL16: 0 | AM16: 0.00049616368 | AN16: NO
A17: 09001060800 | B17: Fairfield | C17: No | D17: =Table3[[#This Row],[Residential CLM $ Collected]]+Table3[[#This Row],[C&I CLM $ Collected]] -> 41183.172 | E17: =Table3[[#This Row],[CLM $ Collected ]]/'1.) CLM Reference'!$B$4 -> 0.0014151995 | F17: =Table3[[#This Row],[Residential Incentive Disbursements]]+Table3[[#This Row],[C&I Incentive Disbursements]] -> 4387.52 | G17: =Table3[[#This Row],[Incentive Disbursements]]/'1.) CLM Reference'!$B$5 -> 0.00026114655 | H17: =IF((Table3[[#This Row],[Incentive Disbursements]]>=0.5*Table3[[#This Row],[CLM $ Collected ]]),"YES",IF(Table3[[#This Row],[Incentive Disbursements]]<=1, "N/A", "NO")) -> NO | I17: =IF(ROUND(E17,5)<0.00001,"N/A",IF(ROUND(E17,5)<=ROUND(G17,5),"YES","NO")) -> NO | J17: 39085.891 | K17: =Table3[[#This Row],[CLM $ Collected ]]/'1.) CLM Reference'!$B$4 -> 0.0014151995 | L17: 4387.52 | M17: =Table3[[#This Row],[Incentive Disbursements]]/'1.) CLM Reference'!$B$5 -> 0.00026114655 | N17: =IF(ROUND(K17,5)<0.00001,"N/A",IF(ROUND(K17,5)<=ROUND(M17,5),"YES","NO")) -> NO | O17: 2097.2804 | P17: =Table3[[#This Row],[CLM $ Collected ]]/'1.) CLM Reference'!$B$4 -> 0.0014151995 | Q17: 0 | R17: =Table3[[#This Row],[Incentive Disbursements]]/'1.) CLM Reference'!$B$5 -> 0.00026114655 | S17: =IF(ROUND(P17,5)<0.00001,"N/A",IF(ROUND(P17,5)<=ROUND(R17,5),"YES","NO")) -> NO | U17: 09001060800 | V17: =RIGHT(Table5[[#This Row],[Census Tract]],10) -> 9001060800 | W17: Fairfield | X17: No | Y17: 41183.172 | Z17: 0.0014151995 | AA17: 4387.52 | AB17: 0.00026114655 | AC17: NO | AD17: NO | AE17: 39085.891 | AF17: 0.0014151995 | AG17: 4387.52 | AH17: 0.00026114655 | AI17: NO | AJ17: 2097.2804 | AK17: 0.0014151995 | AL17: 0 | AM17: 0.00026114655 | AN17: NO
... A414: UNKNOWN | B414: WOODBRIDGE | C414: No | D414: =Table3[[#This Row],[Residential CLM $ Collected]]+Table3[[#This Row],[C&I CLM $ Collected]] -> 0 | E414: =Table3[[#This Row],[CLM $ Collected ]]/'1.) CLM Reference'!$B$4 -> 0 | F414: =Table3[[#This Row],[Residential Incentive Disbursements]]+Table3[[#This Row],[C&I Incentive Disbursements]] -> 21933.921 | G414: =Table3[[#This Row],[Incentive Disbursements]]/'1.) CLM Reference'!$B$5 -> 0.0013055138 | H414: =IF((Table3[[#This Row],[Incentive Disbursements]]>=0.5*Table3[[#This Row],[CLM $ Collected ]]),"YES",IF(Table3[[#This Row],[Incentive Disbursements]]<=1, "N/A", "NO")) -> YES | I414: =IF(ROUND(E414,5)<0.00001,"N/A",IF(ROUND(E414,5)<=ROUND(G414,5),"YES","NO")) -> N/A | J414: 0 | K414: =Table3[[#This Row],[CLM $ Collected ]]/'1.) CLM Reference'!$B$4 -> 0 | L414: 21933.921 | M414: =Table3[[#This Row],[Incentive Disbursements]]/'1.) CLM Reference'!$B$5 -> 0.0013055138 | N414: =IF(ROUND(K414,5)<0.00001,"N/A",IF(ROUND(K414,5)<=ROUND(M414,5),"YES","NO")) -> N/A | O414: 0 | P414: =Table3[[#This Row],[CLM $ Collected ]]/'1.) CLM Reference'!$B$4 -> 0 | Q414: 0 | R414: =Table3[[#This Row],[Incentive Disbursements]]/'1.) CLM Reference'!$B$5 -> 0.0013055138 | S414: =IF(ROUND(P414,5)<0.00001,"N/A",IF(ROUND(P414,5)<=ROUND(R414,5),"YES","NO")) -> N/A | U414: UNKNOWN | V414: =RIGHT(Table5[[#This Row],[Census Tract]],10) -> UNKNOWN | W414: WOODBRIDGE | X414: No | Y414: 0 | Z414: 0 | AA414: 21933.921 | AB414: 0.0013055138 | AC414: YES | AD414: N/A | AE414: 0 | AF414: 0 | AG414: 21933.921 | AH414: 0.0013055138 | AI414: N/A | AJ414: 0 | AK414: 0 | AL414: 0 | AM414: 0.0013055138 | AN414: N/A
D415: =Table3[[#This Row],[Residential CLM $ Collected]]+Table3[[#This Row],[C&I CLM $ Collected]] -> 0 | E415: =Table3[[#This Row],[CLM $ Collected ]]/'1.) CLM Reference'!$B$4 -> 0 | F415: =Table3[[#This Row],[Residential Incentive Disbursements]]+Table3[[#This Row],[C&I Incentive Disbursements]] -> 0 | G415: =Table3[[#This Row],[Incentive Disbursements]]/'1.) CLM Reference'!$B$5 -> 0 | H415: =IF((Table3[[#This Row],[Incentive Disbursements]]>=0.5*Table3[[#This Row],[CLM $ Collected ]]),"YES",IF(Table3[[#This Row],[Incentive Disbursements]]<=1, "N/A", "NO")) -> YES | I415: =IF(ROUND(E415,5)<0.00001,"N/A",IF(ROUND(E415,5)<=ROUND(G415,5),"YES","NO")) -> N/A | K415: =Table3[[#This Row],[CLM $ Collected ]]/'1.) CLM Reference'!$B$4 -> 0 | M415: =Table3[[#This Row],[Incentive Disbursements]]/'1.) CLM Reference'!$B$5 -> 0 | N415: =IF(ROUND(K415,5)<0.00001,"N/A",IF(ROUND(K415,5)<=ROUND(M415,5),"YES","NO")) -> N/A | P415: =Table3[[#This Row],[CLM $ Collected ]]/'1.) CLM Reference'!$B$4 -> 0 | R415: =Table3[[#This Row],[Incentive Disbursements]]/'1.) CLM Reference'!$B$5 -> 0 | S415: =IF(ROUND(P415,5)<0.00001,"N/A",IF(ROUND(P415,5)<=ROUND(R415,5),"YES","NO")) -> N/A
D416: =Table3[[#This Row],[Residential CLM $ Collected]]+Table3[[#This Row],[C&I CLM $ Collected]] -> 0 | E416: =Table3[[#This Row],[CLM $ Collected ]]/'1.) CLM Reference'!$B$4 -> 0 | F416: =Table3[[#This Row],[Residential Incentive Disbursements]]+Table3[[#This Row],[C&I Incentive Disbursements]] -> 0 | G416: =Table3[[#This Row],[Incentive Disbursements]]/'1.) CLM Reference'!$B$5 -> 0 | H416: =IF((Table3[[#This Row],[Incentive Disbursements]]>=0.5*Table3[[#This Row],[CLM $ Collected ]]),"YES",IF(Table3[[#This Row],[Incentive Disbursements]]<=1, "N/A", "NO")) -> YES | I416: =IF(ROUND(E416,5)<0.00001,"N/A",IF(ROUND(E416,5)<=ROUND(G416,5),"YES","NO")) -> N/A | K416: =Table3[[#This Row],[CLM $ Collected ]]/'1.) CLM Reference'!$B$4 -> 0 | M416: =Table3[[#This Row],[Incentive Disbursements]]/'1.) CLM Reference'!$B$5 -> 0 | N416: =IF(ROUND(K416,5)<0.00001,"N/A",IF(ROUND(K416,5)<=ROUND(M416,5),"YES","NO")) -> N/A | P416: =Table3[[#This Row],[CLM $ Collected ]]/'1.) CLM Reference'!$B$4 -> 0 | R416: =Table3[[#This Row],[Incentive Disbursements]]/'1.) CLM Reference'!$B$5 -> 0 | S416: =IF(ROUND(P416,5)<0.00001,"N/A",IF(ROUND(P416,5)<=ROUND(R416,5),"YES","NO")) -> N/A
D417: =Table3[[#This Row],[Residential CLM $ Collected]]+Table3[[#This Row],[C&I CLM $ Collected]] -> 0 | E417: =Table3[[#This Row],[CLM $ Collected ]]/'1.) CLM Reference'!$B$4 -> 0 | F417: =Table3[[#This Row],[Residential Incentive Disbursements]]+Table3[[#This Row],[C&I Incentive Disbursements]] -> 0 | G417: =Table3[[#This Row],[Incentive Disbursements]]/'1.) CLM Reference'!$B$5 -> 0 | H417: =IF((Table3[[#This Row],[Incentive Disbursements]]>=0.5*Table3[[#This Row],[CLM $ Collected ]]),"YES",IF(Table3[[#This Row],[Incentive Disbursements]]<=1, "N/A", "NO")) -> YES | I417: =IF(ROUND(E417,5)<0.00001,"N/A",IF(ROUND(E417,5)<=ROUND(G417,5),"YES","NO")) -> N/A | K417: =Table3[[#This Row],[CLM $ Collected ]]/'1.) CLM Reference'!$B$4 -> 0 | M417: =Table3[[#This Row],[Incentive Disbursements]]/'1.) CLM Reference'!$B$5 -> 0 | N417: =IF(ROUND(K417,5)<0.00001,"N/A",IF(ROUND(K417,5)<=ROUND(M417,5),"YES","NO")) -> N/A | P417: =Table3[[#This Row],[CLM $ Collected ]]/'1.) CLM Reference'!$B$4 -> 0 | R417: =Table3[[#This Row],[Incentive Disbursements]]/'1.) CLM Reference'!$B$5 -> 0 | S417: =IF(ROUND(P417,5)<0.00001,"N/A",IF(ROUND(P417,5)<=ROUND(R417,5),"YES","NO")) -> N/A
D418: =Table3[[#This Row],[Residential CLM $ Collected]]+Table3[[#This Row],[C&I CLM $ Collected]] -> 0 | E418: =Table3[[#This Row],[CLM $ Collected ]]/'1.) CLM Reference'!$B$4 -> 0 | F418: =Table3[[#This Row],[Residential Incentive Disbursements]]+Table3[[#This Row],[C&I Incentive Disbursements]] -> 0 | G418: =Table3[[#This Row],[Incentive Disbursements]]/'1.) CLM Reference'!$B$5 -> 0 | H418: =IF((Table3[[#This Row],[Incentive Disbursements]]>=0.5*Table3[[#This Row],[CLM $ Collected ]]),"YES",IF(Table3[[#This Row],[Incentive Disbursements]]<=1, "N/A", "NO")) -> YES | I418: =IF(ROUND(E418,5)<0.00001,"N/A",IF(ROUND(E418,5)<=ROUND(G418,5),"YES","NO")) -> N/A | K418: =Table3[[#This Row],[CLM $ Collected ]]/'1.) CLM Reference'!$B$4 -> 0 | M418: =Table3[[#This Row],[Incentive Disbursements]]/'1.) CLM Reference'!$B$5 -> 0 | N418: =IF(ROUND(K418,5)<0.00001,"N/A",IF(ROUND(K418,5)<=ROUND(M418,5),"YES","NO")) -> N/A | P418: =Table3[[#This Row],[CLM $ Collected ]]/'1.) CLM Reference'!$B$4 -> 0 | R418: =Table3[[#This Row],[Incentive Disbursements]]/'1.) CLM Reference'!$B$5 -> 0 | S418: =IF(ROUND(P418,5)<0.00001,"N/A",IF(ROUND(P418,5)<=ROUND(R418,5),"YES","NO")) -> N/A
D419: =Table3[[#This Row],[Residential CLM $ Collected]]+Table3[[#This Row],[C&I CLM $ Collected]] -> 0 | E419: =Table3[[#This Row],[CLM $ Collected ]]/'1.) CLM Reference'!$B$4 -> 0 | F419: =Table3[[#This Row],[Residential Incentive Disbursements]]+Table3[[#This Row],[C&I Incentive Disbursements]] -> 0 | G419: =Table3[[#This Row],[Incentive Disbursements]]/'1.) CLM Reference'!$B$5 -> 0 | H419: =IF((Table3[[#This Row],[Incentive Disbursements]]>=0.5*Table3[[#This Row],[CLM $ Collected ]]),"YES",IF(Table3[[#This Row],[Incentive Disbursements]]<=1, "N/A", "NO")) -> YES | I419: =IF(ROUND(E419,5)<0.00001,"N/A",IF(ROUND(E419,5)<=ROUND(G419,5),"YES","NO")) -> N/A | K419: =Table3[[#This Row],[CLM $ Collected ]]/'1.) CLM Reference'!$B$4 -> 0 | M419: =Table3[[#This Row],[Incentive Disbursements]]/'1.) CLM Reference'!$B$5 -> 0 | N419: =IF(ROUND(K419,5)<0.00001,"N/A",IF(ROUND(K419,5)<=ROUND(M419,5),"YES","NO")) -> N/A | P419: =Table3[[#This Row],[CLM $ Collected ]]/'1.) CLM Reference'!$B$4 -> 0 | R419: =Table3[[#This Row],[Incentive Disbursements]]/'1.) CLM Reference'!$B$5 -> 0 | S419: =IF(ROUND(P419,5)<0.00001,"N/A",IF(ROUND(P419,5)<=ROUND(R419,5),"YES","NO")) -> N/A
D420: =Table3[[#This Row],[Residential CLM $ Collected]]+Table3[[#This Row],[C&I CLM $ Collected]] -> 0 | E420: =Table3[[#This Row],[CLM $ Collected ]]/'1.) CLM Reference'!$B$4 -> 0 | F420: =Table3[[#This Row],[Residential Incentive Disbursements]]+Table3[[#This Row],[C&I Incentive Disbursements]] -> 0 | G420: =Table3[[#This Row],[Incentive Disbursements]]/'1.) CLM Reference'!$B$5 -> 0 | H420: =IF((Table3[[#This Row],[Incentive Disbursements]]>=0.5*Table3[[#This Row],[CLM $ Collected ]]),"YES",IF(Table3[[#This Row],[Incentive Disbursements]]<=1, "N/A", "NO")) -> YES | I420: =IF(ROUND(E420,5)<0.00001,"N/A",IF(ROUND(E420,5)<=ROUND(G420,5),"YES","NO")) -> N/A | K420: =Table3[[#This Row],[CLM $ Collected ]]/'1.) CLM Reference'!$B$4 -> 0 | M420: =Table3[[#This Row],[Incentive Disbursements]]/'1.) CLM Reference'!$B$5 -> 0 | N420: =IF(ROUND(K420,5)<0.00001,"N/A",IF(ROUND(K420,5)<=ROUND(M420,5),"YES","NO")) -> N/A | P420: =Table3[[#This Row],[CLM $ Collected ]]/'1.) CLM Reference'!$B$4 -> 0 | R420: =Table3[[#This Row],[Incentive Disbursements]]/'1.) CLM Reference'!$B$5 -> 0 | S420: =IF(ROUND(P420,5)<0.00001,"N/A",IF(ROUND(P420,5)<=ROUND(R420,5),"YES","NO")) -> N/A
D421: =Table3[[#This Row],[Residential CLM $ Collected]]+Table3[[#This Row],[C&I CLM $ Collected]] -> 0 | E421: =Table3[[#This Row],[CLM $ Collected ]]/'1.) CLM Reference'!$B$4 -> 0 | F421: =Table3[[#This Row],[Residential Incentive Disbursements]]+Table3[[#This Row],[C&I Incentive Disbursements]] -> 0 | G421: =Table3[[#This Row],[Incentive Disbursements]]/'1.) CLM Reference'!$B$5 -> 0 | H421: =IF((Table3[[#This Row],[Incentive Disbursements]]>=0.5*Table3[[#This Row],[CLM $ Collected ]]),"YES",IF(Table3[[#This Row],[Incentive Disbursements]]<=1, "N/A", "NO")) -> YES | I421: =IF(ROUND(E421,5)<0.00001,"N/A",IF(ROUND(E421,5)<=ROUND(G421,5),"YES","NO")) -> N/A | K421: =Table3[[#This Row],[CLM $ Collected ]]/'1.) CLM Reference'!$B$4 -> 0 | M421: =Table3[[#This Row],[Incentive Disbursements]]/'1.) CLM Reference'!$B$5 -> 0 | N421: =IF(ROUND(K421,5)<0.00001,"N/A",IF(ROUND(K421,5)<=ROUND(M421,5),"YES","NO")) -> N/A | P421: =Table3[[#This Row],[CLM $ Collected ]]/'1.) CLM Reference'!$B$4 -> 0 | R421: =Table3[[#This Row],[Incentive Disbursements]]/'1.) CLM Reference'!$B$5 -> 0 | S421: =IF(ROUND(P421,5)<0.00001,"N/A",IF(ROUND(P421,5)<=ROUND(R421,5),"YES","NO")) -> N/A
D422: =Table3[[#This Row],[Residential CLM $ Collected]]+Table3[[#This Row],[C&I CLM $ Collected]] -> 0 | E422: =Table3[[#This Row],[CLM $ Collected ]]/'1.) CLM Reference'!$B$4 -> 0 | F422: =Table3[[#This Row],[Residential Incentive Disbursements]]+Table3[[#This Row],[C&I Incentive Disbursements]] -> 0 | G422: =Table3[[#This Row],[Incentive Disbursements]]/'1.) CLM Reference'!$B$5 -> 0 | H422: =IF((Table3[[#This Row],[Incentive Disbursements]]>=0.5*Table3[[#This Row],[CLM $ Collected ]]),"YES",IF(Table3[[#This Row],[Incentive Disbursements]]<=1, "N/A", "NO")) -> YES | I422: =IF(ROUND(E422,5)<0.00001,"N/A",IF(ROUND(E422,5)<=ROUND(G422,5),"YES","NO")) -> N/A | K422: =Table3[[#This Row],[CLM $ Collected ]]/'1.) CLM Reference'!$B$4 -> 0 | M422: =Table3[[#This Row],[Incentive Disbursements]]/'1.) CLM Reference'!$B$5 -> 0 | N422: =IF(ROUND(K422,5)<0.00001,"N/A",IF(ROUND(K422,5)<=ROUND(M422,5),"YES","NO")) -> N/A | P422: =Table3[[#This Row],[CLM $ Collected ]]/'1.) CLM Reference'!$B$4 -> 0 | R422: =Table3[[#This Row],[Incentive Disbursements]]/'1.) CLM Reference'!$B$5 -> 0 | S422: =IF(ROUND(P422,5)<0.00001,"N/A",IF(ROUND(P422,5)<=ROUND(R422,5),"YES","NO")) -> N/A
C423: Totals | D423: =SUBTOTAL(109,D6:D422) -> 17547919 | E423: =Table3[[#This Row],[CLM $ Collected ]]/'1.) CLM Reference'!$B$4 -> 0.60300857 | F423: =SUBTOTAL(109,F6:F422) -> 11650461 | G423: =Table3[[#This Row],[Incentive Disbursements]]/'1.) CLM Reference'!$B$5 -> 0.69343902 | H423: =IF((Table3[[#This Row],[Incentive Disbursements]]>=0.5*Table3[[#This Row],[CLM $ Collected ]]),"YES",IF(Table3[[#This Row],[Incentive Disbursements]]<=1, "N/A", "NO")) -> YES | I423: =IF(ROUND(E423,5)<0.00001,"N/A",IF(ROUND(E423,5)<=ROUND(G423,5),"YES","NO")) -> YES | J423: =SUBTOTAL(109,J6:J422) -> 12129793 | K423: =Table3[[#This Row],[CLM $ Collected ]]/'1.) CLM Reference'!$B$4 -> 0.60300857 | L423: =SUBTOTAL(109,L6:L422) -> 8494544.3 | M423: =Table3[[#This Row],[Incentive Disbursements]]/'1.) CLM Reference'!$B$5 -> 0.69343902 | N423: =IF(ROUND(K423,5)<0.00001,"N/A",IF(ROUND(K423,5)<=ROUND(M423,5),"YES","NO")) -> YES | O423: =SUBTOTAL(109,O6:O422) -> 5418126 | P423: =Table3[[#This Row],[CLM $ Collected ]]/'1.) CLM Reference'!$B$4 -> 0.60300857 | Q423: =SUBTOTAL(109,Q6:Q422) -> 3155916.3 | R423: =Table3[[#This Row],[Incentive Disbursements]]/'1.) CLM Reference'!$B$5 -> 0.69343902 | S423: =IF(ROUND(P423,5)<0.00001,"N/A",IF(ROUND(P423,5)<=ROUND(R423,5),"YES","NO")) -> YES
D441: CLM $ Collected | E441: Incentive Disbursements
D442: 0.9029 | E442: 0
D443: 539.357 | E443: 0
D444: 0 | E444: 11586.15
D445: 118414.09 | E445: 0
D446: 0 | E446: 8670.73
D447: 67503.345 | E447: 0
D448: 0 | E448: 213519.3
D449: 52641.309 | E449: 0
D450: 0 | E450: 2503.53
D451: 23919.493 | E451: 0
D452: 50.8641 | E452: 0
D453: 0 | E453: 16596.99
... D661: 0 | E661: 197582.24
D663: =SUM(D442:D661) -> 9091841.8 | E663: =SUM(E442:E661) -> 6667447.8

Sheet Sheet3
A1: Distressed Tract1 | B1: Yes
A2: Equitable | B2: N/A
A4: Row Labels | B4: Count of Census Tract | C4: Sum of % of Total CLM $ Collected | D4: Sum of % of Total Incentive Disbursements | E4: Sum of CLM $ Collected | F4: Sum of Incentive Disbursements
A5: 09001070400 | B5: 1 | C5: 0 | D5: 0.00068961123 | E5: 28740.396 | F5: 0
A6: 09001070900 | B6: 1 | C6: 0 | D6: 4.4619995e-05 | E6: 14584.582 | F6: 0
A7: 09001071000 | B7: 1 | C7: 0 | D7: 0.012708735 | E7: 21101.989 | F7: 0
A8: 09001071300 | B8: 1 | C8: 1.7478704e-06 | D8: 0 | E8: 33404.633 | F8: 0
A9: 09001071900 | B9: 1 | C9: 0 | D9: 0.0065848116 | E9: 30759.563 | F9: 0
A10: 09001073100 | B10: 1 | C10: 0 | D10: 7.9212604e-05 | E10: 43169.747 | F10: 0
A11: 09001073400 | B11: 1 | C11: 0 | D11: 1.3689671e-05 | E11: 11700.819 | F11: 0
A12: 09001073500 | B12: 1 | C12: 0 | D12: 0.00049759514 | E12: 2031.7844 | F12: 0
A13: 09001073900 | B13: 1 | C13: 0 | D13: 0.0044176075 | E13: 7462.4552 | F13: 0
A14: 09009140300 | B14: 1 | C14: 1.0286725e-06 | D14: 0 | E14: 396586.79 | F14: 0
A15: 09009140400 | B15: 1 | C15: 3.6796476e-08 | D15: 0 | E15: 16626.321 | F15: 0
A16: 09009140700 | B16: 1 | C16: 1.6170106e-07 | D16: 0 | E16: 54912.122 | F16: 0
... A22: Grand Total | B22: 17 | C22: 7.9155378e-06 | D22: 0.025096026 | E22: 921996.15 | F22: 0

Sheet Sheet8
A1: Census Tract | B1: Town | C1: Distressed Tract1 | D1: CLM $ Collected | E1: % of Total CLM $ Collected | F1: Incentive Disbursements | G1: % of Total Incentive Disbursements | H1: Equitable | I1: Residential CLM $ Collected | J1: % of Total Residential CLM $ Collected | K1: Residential Incentive Disbursements | L1: % of Total Residential Incentive Disbursements | M1: C&I CLM $ Collected | N1: % of Total C&I CLM $ Collected | O1: C&I Incentive Disbursements | P1: % of TotalC&I Incentive Disbursements | Q1: diversity index table.adjusted income (thousands of $) | R1: diversity index table.median census housing cost | S1: diversity index table.Combined affluence rank | T1: diversity index table.rural rank | U1: diversity index table.racial diversity index | V1: diversity index table.composit index | W1: diversity index table.rounded composite | X1: Column1
A2: 9001070200 | B2: BRIDGEPORT | C2: No | D2: 0 | E2: 0.0025897032 | F2: 85 | G2: 0.0020906646 | H2: NO | I2: 0 | J2: 0.0025897032 | K2: 0 | L2: 0.0020906646 | M2: 0 | N2: 0.0025897032 | O2: 85 | P2: 0.0020906646 | Q2: 27.729 | R2: 1292 | S2: 5 | T2: 1 | U2: 4 | V2: 4.5 | W2: 5 | X2: 9001070200
A3: 9001070200 | B3: Bridgeport | C3: Yes | D3: 23732.358 | E3: 0.0040787861 | F3: 0 | G3: 0.00052688509 | H3: NO | I3: 0 | J3: 0.0040787861 | K3: 0 | L3: 0.00052688509 | M3: 23732.358 | N3: 0.0040787861 | O3: 0 | P3: 0.00052688509 | Q3: 27.729 | R3: 1292 | S3: 5 | T3: 1 | U3: 4 | V3: 4.5 | W3: 5 | X3: 9001070200
A4: 9001070300 | B4: BRIDGEPORT | C4: No | D4: 0 | E4: 1.8534215e-05 | F4: 92446 | G4: 0 | H4: NO | I4: 0 | J4: 1.8534215e-05 | K4: 0 | L4: 0 | M4: 0 | N4: 1.8534215e-05 | O4: 92446 | P4: 0 | Q4: 5.532 | R4: 433 | S4: 5 | T4: 1 | U4: 4 | V4: 4.5 | W4: 5 | X4: 9001070300
A5: 9001070300 | B5: Bridgeport | C5: Yes | D5: 90882.648 | E5: 0.0064748126 | F5: 0 | G5: 0.0020653946 | H5: NO | I5: 0 | J5: 0.0064748126 | K5: 0 | L5: 0.0020653946 | M5: 90882.648 | N5: 0.0064748126 | O5: 0 | P5: 0.0020653946 | Q5: 5.532 | R5: 433 | S5: 5 | T5: 1 | U5: 4 | V5: 4.5 | W5: 5 | X5: 9001070300
A6: 9001071100 | B6: Bridgeport | C6: No | D6: 5250.7829 | E6: 0.0018089416 | F6: 0 | G6: 0 | H6: NO | I6: 0 | J6: 0.0018089416 | K6: 0 | L6: 0 | M6: 5250.7829 | N6: 0.0018089416 | O6: 0 | P6: 0 | Q6: 25.633 | R6: 1271 | S6: 5 | T6: 1 | U6: 5 | V6: 5 | W6: 5 | X6: 9001071100
A7: 9001071200 | B7: BRIDGEPORT | C7: No | D7: 0 | E7: 0 | F7: 4617 | G7: 0.00014901088 | H7: N/A | I7: 0 | J7: 0 | K7: 0 | L7: 0.00014901088 | M7: 0 | N7: 0 | O7: 4617 | P7: 0.00014901088 | Q7: 13.99 | R7: 1107 | S7: 5 | T7: 1 | U7: 5 | V7: 5 | W7: 5 | X7: 9001071200
A8: 9001071200 | B8: Bridgeport | C8: Yes | D8: 26819.624 | E8: 0.0008219584 | F8: 0 | G8: 0 | H8: NO | I8: 1014.0401 | J8: 0.0008219584 | K8: 0 | L8: 0 | M8: 25805.584 | N8: 0.0008219584 | O8: 0 | P8: 0 | Q8: 13.99 | R8: 1107 | S8: 5 | T8: 1 | U8: 5 | V8: 5 | W8: 5 | X8: 9001071200
A9: 9001071300 | B9: Bridgeport | C9: Yes | D9: 33404.633 | E9: 1.7478704e-06 | F9: 0 | G9: 0 | H9: N/A | I9: 0 | J9: 1.7478704e-06 | K9: 0 | L9: 0 | M9: 33404.633 | N9: 1.7478704e-06 | O9: 0 | P9: 0 | Q9: 17.511 | R9: 1078 | S9: 5 | T9: 1 | U9: 5 | V9: 5 | W9: 5 | X9: 9001071300
A10: 9001071400 | B10: Bridgeport | C10: No | D10: 17213.562 | E10: 0 | F10: 0 | G10: 0.00098785798 | H10: N/A | I10: 0 | J10: 0 | K10: 0 | L10: 0.00098785798 | M10: 17213.562 | N10: 0 | O10: 0 | P10: 0.00098785798 | Q10: 22.64 | R10: 1131 | S10: 5 | T10: 1 | U10: 5 | V10: 5 | W10: 5 | X10: 9001071400
A11: 9001071900 | B11: BRIDGEPORT | C11: No | D11: 0 | E11: 0.00099953018 | F11: 244 | G11: 0 | H11: NO | I11: 0 | J11: 0.00099953018 | K11: 0 | L11: 0 | M11: 0 | N11: 0.00099953018 | O11: 244 | P11: 0 | Q11: 26.15 | R11: 1287 | S11: 5 | T11: 1 | U11: 5 | V11: 5 | W11: 5 | X11: 9001071900
A12: 9001071900 | B12: Bridgeport | C12: Yes | D12: 30759.563 | E12: 0 | F12: 0 | G12: 0.0065848116 | H12: N/A | I12: 0 | J12: 0 | K12: 0 | L12: 0.0065848116 | M12: 30759.563 | N12: 0 | O12: 0 | P12: 0.0065848116 | Q12: 26.15 | R12: 1287 | S12: 5 | T12: 1 | U12: 5 | V12: 5 | W12: 5 | X12: 9001071900
A13: 9001072200 | B13: Bridgeport | C13: Yes | D13: 9298.1456 | E13: 0.0013769037 | F13: 0 | G13: 0 | H13: NO | I13: 0 | J13: 0.0013769037 | K13: 0 | L13: 0 | M13: 9298.1456 | N13: 0.0013769037 | O13: 0 | P13: 0 | Q13: 31.307 | R13: 1641 | S13: 4 | T13: 1 | U13: 4 | V13: 4 | W13: 4 | X13: 9001072200
... A61: 9009361402 | B61: New Haven | C61: Yes | D61: 119732.2 | E61: 1.4861268e-06 | F61: 0 | G61: 0 | H61: N/A | I61: 0 | J61: 1.4861268e-06 | K61: 0 | L61: 0 | M61: 119732.2 | N61: 1.4861268e-06 | O61: 0 | P61: 0 | Q61: 35.178 | R61: 1510 | S61: 4 | T61: 1 | U61: 5 | V61: 4.5 | W61: 5 | X61: 9009361402
D64: =SUM(Merge6[CLM $ Collected ]) -> 2611766.9

Sheet Sheet7
A1: Census Tract | B1: Town | C1: Distressed Tract1 | D1: CLM $ Collected | E1: % of Total CLM $ Collected | F1: Incentive Disbursements | G1: % of Total Incentive Disbursements | H1: Equitable | I1: Residential CLM $ Collected | J1: % of Total Residential CLM $ Collected | K1: Residential Incentive Disbursements | L1: % of Total Residential Incentive Disbursements | M1: C&I CLM $ Collected | N1: % of Total C&I CLM $ Collected | O1: C&I Incentive Disbursements | P1: % of TotalC&I Incentive Disbursements | Q1: diversity index table.adjusted income (thousands of $) | R1: diversity index table.median census housing cost | S1: diversity index table.Combined affluence rank | T1: diversity index table.rural rank | U1: diversity index table.racial diversity index | V1: diversity index table.composit index | W1: diversity index table.rounded composite | X1: Column1
A2: 9001060100 | B2: Fairfield | C2: No | D2: 100227.79 | E2: 1.3553941e-05 | F2: 0 | G2: 0 | H2: NO | I2: 0 | J2: 1.3553941e-05 | K2: 0 | L2: 0 | M2: 100227.79 | N2: 1.3553941e-05 | O2: 0 | P2: 0 | Q2: 85.387 | R2: 2313 | S2: 1 | T2: 1 | U2: 2 | V2: 1.5 | W2: 2 | X2: 9001060100
A3: 9001060200 | B3: Fairfield | C3: No | D3: 73601.252 | E3: 3.0498004e-05 | F3: 0 | G3: 0 | H3: NO | I3: 0 | J3: 3.0498004e-05 | K3: 0 | L3: 0 | M3: 73601.252 | N3: 3.0498004e-05 | O3: 0 | P3: 0 | Q3: 75.665 | R3: 2452 | S3: 1 | T3: 1 | U3: 3 | V3: 2 | W3: 2 | X3: 9001060200
A4: 9001060300 | B4: Fairfield | C4: No | D4: 37903.336 | E4: 3.1026838e-08 | F4: 1240 | G4: 0 | H4: N/A | I4: 0 | J4: 3.1026838e-08 | K4: 0 | L4: 0 | M4: 37903.336 | N4: 3.1026838e-08 | O4: 1240 | P4: 0 | Q4: 114.261 | R4: 3341 | S4: 1 | T4: 1 | U4: 2 | V4: 1.5 | W4: 2 | X4: 9001060300
A5: 9001060400 | B5: Fairfield | C5: No | D5: 9570.1769 | E5: 0.0024533084 | F5: 0 | G5: 0.0011966439 | H5: NO | I5: 0 | J5: 0.0024533084 | K5: 0 | L5: 0.0011966439 | M5: 9570.1769 | N5: 0.0024533084 | O5: 0 | P5: 0.0011966439 | Q5: 146.927 | R5: 3810 | S5: 1 | T5: 1 | U5: 1 | V5: 1 | W5: 1 | X5: 9001060400
A6: 9001060500 | B6: Fairfield | C6: No | D6: 4850.7232 | E6: 3.6427206e-06 | F6: 330 | G6: 0 | H6: N/A | I6: 0 | J6: 3.6427206e-06 | K6: 0 | L6: 0 | M6: 4850.7232 | N6: 3.6427206e-06 | O6: 330 | P6: 0 | Q6: 121.599 | R6: 3418 | S6: 1 | T6: 1 | U6: 1 | V6: 1 | W6: 1 | X6: 9001060500
A7: 9001060600 | B7: Fairfield | C7: No | D7: 33150.892 | E7: 0.0033323014 | F7: 0 | G7: 0.001876948 | H7: NO | I7: 0 | J7: 0.0033323014 | K7: 0 | L7: 0.001876948 | M7: 33150.892 | N7: 0.0033323014 | O7: 0 | P7: 0.001876948 | Q7: 116.734 | R7: 2525 | S7: 1 | T7: 1 | U7: 2 | V7: 1.5 | W7: 2 | X7: 9001060600
A8: 9001060700 | B8: Fairfield | C8: No | D8: 101146.56 | E8: 0.0034587413 | F8: 2245.5 | G8: 0.0011630691 | H8: NO | I8: 0 | J8: 0.0034587413 | K8: 0 | L8: 0.0011630691 | M8: 101146.56 | N8: 0.0034587413 | O8: 2245.5 | P8: 0.0011630691 | Q8: 104.15 | R8: 2864 | S8: 1 | T8: 1 | U8: 2 | V8: 1.5 | W8: 2 | X8: 9001060700
A9: 9001060900 | B9: Fairfield | C9: No | D9: 2542.0457 | E9: 0.0057714803 | F9: 0 | G9: 0.00097384928 | H9: NO | I9: 0 | J9: 0.0057714803 | K9: 0 | L9: 0.00097384928 | M9: 2542.0457 | N9: 0.0057714803 | O9: 0 | P9: 0.00097384928 | Q9: 82.66 | R9: 2698 | S9: 1 | T9: 1 | U9: 1 | V9: 1 | W9: 1 | X9: 9001060900
A10: 9001061000 | B10: Fairfield | C10: No | D10: 48402.934 | E10: 0.0026703043 | F10: 79085 | G10: 0.00043758141 | H10: NO | I10: 0 | J10: 0.0026703043 | K10: 0 | L10: 0.00043758141 | M10: 48402.934 | N10: 0.0026703043 | O10: 79085 | P10: 0.00043758141 | Q10: 49.471 | R10: 1741 | S10: 3 | T10: 1 | U10: 3 | V10: 3 | W10: 3 | X10: 9001061000
A11: 9001061100 | B11: Fairfield | C11: No | D11: 3413.4719 | E11: 0.0042257384 | F11: 0 | G11: 0.0057024623 | H11: YES | I11: 0 | J11: 0.0042257384 | K11: 0 | L11: 0.0057024623 | M11: 3413.4719 | N11: 0.0042257384 | O11: 0 | P11: 0.0057024623 | Q11: 94.519 | R11: 2692 | S11: 1 | T11: 1 | U11: 1 | V11: 1 | W11: 1 | X11: 9001061100
A12: 9001061300 | B12: Fairfield | C12: No | D12: 19307.045 | E12: 0.0040455315 | F12: 0 | G12: 0.00049616368 | H12: NO | I12: 1395.1154 | J12: 0.0040455315 | K12: 0 | L12: 0.00049616368 | M12: 17911.93 | N12: 0.0040455315 | O12: 0 | P12: 0.00049616368 | Q12: 54.923 | R12: 1857 | S12: 3 | T12: 1 | U12: 4 | V12: 3.5 | W12: 4 | X12: 9001061300
A13: 9001061400 | B13: Fairfield | C13: No | D13: 111401.45 | E13: 0.0014151995 | F13: 224266 | G13: 0.00026114655 | H13: NO | I13: 0 | J13: 0.0014151995 | K13: 0 | L13: 0.00026114655 | M13: 111401.45 | N13: 0.0014151995 | O13: 224266 | P13: 0.00026114655 | Q13: 56.725 | R13: 1873 | S13: 3 | T13: 1 | U13: 5 | V13: 4 | W13: 4 | X13: 9001061400
... A205: 9009361500 | B205: West Haven | C205: No | D205: 214352.33 | E205: 0 | F205: 3517 | G205: 5.7758508e-06 | H205: N/A | I205: 0 | J205: 0 | K205: 0 | L205: 5.7758508e-06 | M205: 214352.33 | N205: 0 | O205: 3517 | P205: 5.7758508e-06 | Q205: 34.21 | R205: 1260 | S205: 4 | T205: 1 | U205: 5 | V205: 4.5 | W205: 5 | X205: 9009361500

Sheet large load eqity calcs
A1: Census Tract | B1: Town | C1: Distressed Tract1 | D1: CLM $ Collected | E1: % of Total CLM $ Collected | F1: Incentive Disbursements | G1: % of Total Incentive Disbursements | H1: Equitable | I1: Residential CLM $ Collected | J1: % of Total Residential CLM $ Collected | K1: Residential Incentive Disbursements | L1: % of Total Residential Incentive Disbursements | M1: C&I CLM $ Collected | N1: % of Total C&I CLM $ Collected | O1: C&I Incentive Disbursements | P1: % of TotalC&I Incentive Disbursements | Q1: diversity index table.adjusted income (thousands of $) | R1: diversity index table.median census housing cost | S1: diversity index table.Combined affluence rank | T1: diversity index table.rural rank | U1: diversity index table.racial diversity index | V1: diversity index table.composit index | W1: diversity index table.rounded composite | X1: Column1
A2: 9001060100 | B2: Fairfield | C2: No | D2: 100227.79 | E2: 1.3553941e-05 | F2: 0 | G2: 0 | H2: NO | I2: 0 | J2: 1.3553941e-05 | K2: 0 | L2: 0 | M2: 100227.79 | N2: 1.3553941e-05 | O2: 0 | P2: 0 | Q2: 85.387 | R2: 2313 | S2: 1 | T2: 1 | U2: 2 | V2: 1.5 | W2: 2 | X2: =RIGHT(Merge1[[#This Row],[Census Tract]],10) -> 9001060100 | AG2: Composite Index
A3: 9001060200 | B3: Fairfield | C3: No | D3: 73601.252 | E3: 3.0498004e-05 | F3: 0 | G3: 0 | H3: NO | I3: 0 | J3: 3.0498004e-05 | K3: 0 | L3: 0 | M3: 73601.252 | N3: 3.0498004e-05 | O3: 0 | P3: 0 | Q3: 75.665 | R3: 2452 | S3: 1 | T3: 1 | U3: 3 | V3: 2 | W3: 2 | X3: =RIGHT(Merge1[[#This Row],[Census Tract]],10) -> 9001060200 | Z3: Row Labels | AA3: Sum of CLM $ Collected | AB3: Sum of Incentive Disbursements | AC3: Sum of Residential CLM $ Collected | AD3: Sum of Residential Incentive Disbursements | AE3: Sum of C&I CLM $ Collected | AF3: Sum of C&I Incentive Disbursements | AH3: Row Labels | AI3: Sum of CLM $ Collected | AJ3: Sum of Incentive Disbursements | AK3: Sum of Residential CLM $ Collected | AL3: Sum of Residential Incentive Disbursements | AM3: Sum of C&I CLM $ Collected | AN3: Sum of C&I Incentive Disbursements
A4: 9001060300 | B4: Fairfield | C4: No | D4: 37903.336 | E4: 3.1026838e-08 | F4: 1240 | G4: 0 | H4: N/A | I4: 0 | J4: 3.1026838e-08 | K4: 0 | L4: 0 | M4: 37903.336 | N4: 3.1026838e-08 | O4: 1240 | P4: 0 | Q4: 114.261 | R4: 3341 | S4: 1 | T4: 1 | U4: 2 | V4: 1.5 | W4: 2 | X4: =RIGHT(Merge1[[#This Row],[Census Tract]],10) -> 9001060300 | Z4: 1 | AA4: 644852.14 | AB4: 256726.5 | AC4: 2121.6126 | AD4: 0 | AE4: 642730.52 | AF4: 256726.5 | AH4: 1 | AI4: 380781.66 | AJ4: 50475 | AK4: 2121.6126 | AL4: 0 | AM4: 378660.05 | AN4: 50475
A5: 9001060400 | B5: Fairfield | C5: No | D5: 9570.1769 | E5: 0.0024533084 | F5: 0 | G5: 0.0011966439 | H5: NO | I5: 0 | J5: 0.0024533084 | K5: 0 | L5: 0.0011966439 | M5: 9570.1769 | N5: 0.0024533084 | O5: 0 | P5: 0.0011966439 | Q5: 146.927 | R5: 3810 | S5: 1 | T5: 1 | U5: 1 | V5: 1 | W5: 1 | X5: =RIGHT(Merge1[[#This Row],[Census Tract]],10) -> 9001060400 | Z5: 2 | AA5: 1620695.8 | AB5: 613013.79 | AC5: 6043.2621 | AD5: 0 | AE5: 1614652.5 | AF5: 613013.79 | AH5: 2 | AI5: 1351586.6 | AJ5: 592755 | AK5: 1844.7195 | AL5: 0 | AM5: 1349741.9 | AN5: 592755
A6: 9001060500 | B6: Fairfield | C6: No | D6: 4850.7232 | E6: 3.6427206e-06 | F6: 330 | G6: 0 | H6: N/A | I6: 0 | J6: 3.6427206e-06 | K6: 0 | L6: 0 | M6: 4850.7232 | N6: 3.6427206e-06 | O6: 330 | P6: 0 | Q6: 121.599 | R6: 3418 | S6: 1 | T6: 1 | U6: 1 | V6: 1 | W6: 1 | X6: =RIGHT(Merge1[[#This Row],[Census Tract]],10) -> 9001060500 | Z6: 3 | AA6: 3135886.9 | AB6: 748894.24 | AC6: 34364.036 | AD6: 0 | AE6: 3101522.8 | AF6: 748894.24 | AH6: 3 | AI6: 3220035.9 | AJ6: 912176.96 | AK6: 20016.873 | AL6: 0 | AM6: 3200019.1 | AN6: 912176.96
A7: 9001060600 | B7: Fairfield | C7: No | D7: 33150.892 | E7: 0.0033323014 | F7: 0 | G7: 0.001876948 | H7: NO | I7: 0 | J7: 0.0033323014 | K7: 0 | L7: 0.001876948 | M7: 33150.892 | N7: 0.0033323014 | O7: 0 | P7: 0.001876948 | Q7: 116.734 | R7: 2525 | S7: 1 | T7: 1 | U7: 2 | V7: 1.5 | W7: 2 | X7: =RIGHT(Merge1[[#This Row],[Census Tract]],10) -> 9001060600 | Z7: 4 | AA7: 2352159.7 | AB7: 1624963.1 | AC7: 28379.463 | AD7: 0 | AE7: 2323780.3 | AF7: 1624963.1 | AH7: 4 | AI7: 2923302.4 | AJ7: 1950597.6 | AK7: 33742.3 | AL7: 0 | AM7: 2889560.1 | AN7: 1950597.6
A8: 9001060700 | B8: Fairfield | C8: No | D8: 101146.56 | E8: 0.0034587413 | F8: 2245.5 | G8: 0.0011630691 | H8: NO | I8: 0 | J8: 0.0034587413 | K8: 0 | L8: 0.0011630691 | M8: 101146.56 | N8: 0.0034587413 | O8: 2245.5 | P8: 0.0011630691 | Q8: 104.15 | R8: 2864 | S8: 1 | T8: 1 | U8: 2 | V8: 1.5 | W8: 2 | X8: =RIGHT(Merge1[[#This Row],[Census Tract]],10) -> 9001060700 | Z8: 5 | AA8: 3799099.1 | AB8: 1906929.8 | AC8: 84377.858 | AD8: 800 | AE8: 3714721.3 | AF8: 1906129.8 | AH8: 5 | AI8: 3676987.1 | AJ8: 1644522.8 | AK8: 97560.726 | AL8: 800 | AM8: 3579426.4 | AN8: 1643722.8
A9: 9001060900 | B9: Fairfield | C9: No | D9: 2542.0457 | E9: 0.0057714803 | F9: 0 | G9: 0.00097384928 | H9: NO | I9: 0 | J9: 0.0057714803 | K9: 0 | L9: 0.00097384928 | M9: 2542.0457 | N9: 0.0057714803 | O9: 0 | P9: 0.00097384928 | Q9: 82.66 | R9: 2698 | S9: 1 | T9: 1 | U9: 1 | V9: 1 | W9: 1 | X9: =RIGHT(Merge1[[#This Row],[Census Tract]],10) -> 9001060900 | Z9: Grand Total | AA9: 11552694 | AB9: 5150527.4 | AC9: 155286.23 | AD9: 800 | AE9: 11397407 | AF9: 5149727.4 | AH9: Grand Total | AI9: 11552694 | AJ9: 5150527.4 | AK9: 155286.23 | AL9: 800 | AM9: 11397407 | AN9: 5149727.4
A10: 9001061000 | B10: Fairfield | C10: No | D10: 48402.934 | E10: 0.0026703043 | F10: 79085 | G10: 0.00043758141 | H10: NO | I10: 0 | J10: 0.0026703043 | K10: 0 | L10: 0.00043758141 | M10: 48402.934 | N10: 0.0026703043 | O10: 79085 | P10: 0.00043758141 | Q10: 49.471 | R10: 1741 | S10: 3 | T10: 1 | U10: 3 | V10: 3 | W10: 3 | X10: =RIGHT(Merge1[[#This Row],[Census Tract]],10) -> 9001061000
A11: 9001061100 | B11: Fairfield | C11: No | D11: 3413.4719 | E11: 0.0042257384 | F11: 0 | G11: 0.0057024623 | H11: YES | I11: 0 | J11: 0.0042257384 | K11: 0 | L11: 0.0057024623 | M11: 3413.4719 | N11: 0.0042257384 | O11: 0 | P11: 0.0057024623 | Q11: 94.519 | R11: 2692 | S11: 1 | T11: 1 | U11: 1 | V11: 1 | W11: 1 | X11: =RIGHT(Merge1[[#This Row],[Census Tract]],10) -> 9001061100 | AH11: Row Labels | AI11: Collections % | AJ11: Collections Disbursement | AK11: RES collections | AL11: RES disbursements | AM11: C&I Collection | AN11: C&I disburse
A12: 9001061300 | B12: Fairfield | C12: No | D12: 19307.045 | E12: 0.0040455315 | F12: 0 | G12: 0.00049616368 | H12: NO | I12: 1395.1154 | J12: 0.0040455315 | K12: 0 | L12: 0.00049616368 | M12: 17911.93 | N12: 0.0040455315 | O12: 0 | P12: 0.00049616368 | Q12: 54.923 | R12: 1857 | S12: 3 | T12: 1 | U12: 4 | V12: 3.5 | W12: 4 | X12: =RIGHT(Merge1[[#This Row],[Census Tract]],10) -> 9001061300 | AH12: 1 | AI12: =AI4/AI$9 -> 0.032960422 | AJ12: =AJ4/AJ$9 -> 0.0097999674 | AK12: =AK4/AK$9 -> 0.013662593 | AL12: =AL4/AL$9 -> 0 | AM12: =AM4/AM$9 -> 0.033223349 | AN12: =AN4/AN$9 -> 0.0098014898
A13: 9001061400 | B13: Fairfield | C13: No | D13: 111401.45 | E13: 0.0014151995 | F13: 224266 | G13: 0.00026114655 | H13: NO | I13: 0 | J13: 0.0014151995 | K13: 0 | L13: 0.00026114655 | M13: 111401.45 | N13: 0.0014151995 | O13: 224266 | P13: 0.00026114655 | Q13: 56.725 | R13: 1873 | S13: 3 | T13: 1 | U13: 5 | V13: 4 | W13: 4 | X13: =RIGHT(Merge1[[#This Row],[Census Tract]],10) -> 9001061400 | AH13: 2 | AI13: =AI5/AI$9 -> 0.1169932 | AJ13: =AJ5/AJ$9 -> 0.11508627 | AK13: =AK5/AK$9 -> 0.011879479 | AL13: =AL5/AL$9 -> 0 | AM13: =AM5/AM$9 -> 0.11842534 | AN13: =AN5/AN$9 -> 0.11510415
A14: 9001061500 | B14: Bridgeport | C14: No | D14: 2535.1002 | E14: 0.0016930697 | F14: 0 | G14: 0.0017877699 | H14: YES | I14: 0 | J14: 0.0016930697 | K14: 0 | L14: 0.0017877699 | M14: 2535.1002 | N14: 0.0016930697 | O14: 0 | P14: 0.0017877699 | Q14: 89.569 | R14: 2670 | S14: 1 | T14: 1 | U14: 4 | V14: 2.5 | W14: 3 | X14: =RIGHT(Merge1[[#This Row],[Census Tract]],10) -> 9001061500 | AH14: 3 | AI14: =AI6/AI$9 -> 0.27872599 | AJ14: =AJ6/AJ$9 -> 0.1771036 | AK14: =AK6/AK$9 -> 0.12890308 | AL14: =AL6/AL$9 -> 0 | AM14: =AM6/AM$9 -> 0.28076728 | AN14: =AN6/AN$9 -> 0.17713112
A15: 9001061500 | B15: Fairfield | C15: No | D15: 63380.399 | E15: 0.0048602243 | F15: 1555 | G15: 0.0050261324 | H15: YES | I15: 0 | J15: 0.0048602243 | K15: 0 | L15: 0.0050261324 | M15: 63380.399 | N15: 0.0048602243 | O15: 1555 | P15: 0.0050261324 | Q15: 89.569 | R15: 2670 | S15: 1 | T15: 1 | U15: 4 | V15: 2.5 | W15: 3 | X15: =RIGHT(Merge1[[#This Row],[Census Tract]],10) -> 9001061500 | AH15: 4 | AI15: =AI7/AI$9 -> 0.25304076 | AJ15: =AJ7/AJ$9 -> 0.37871804 | AK15: =AK7/AK$9 -> 0.21729099 | AL15: =AL7/AL$9 -> 0 | AM15: =AM7/AM$9 -> 0.25352784 | AN15: =AN7/AN$9 -> 0.37877688
A16: 9001061600 | B16: Fairfield | C16: No | D16: 32031.164 | E16: 0.0025042807 | F16: 49035 | G16: 0.00026623851 | H16: NO | I16: 2121.6126 | J16: 0.0025042807 | K16: 0 | L16: 0.00026623851 | M16: 29909.552 | N16: 0.0025042807 | O16: 49035 | P16: 0.00026623851 | Q16: 80.624 | R16: 2370 | S16: 1 | T16: 1 | U16: 1 | V16: 1 | W16: 1 | X16: =RIGHT(Merge1[[#This Row],[Census Tract]],10) -> 9001061600 | AH16: 5 | AI16: =AI8/AI$9 -> 0.31827963 | AJ16: =AJ8/AJ$9 -> 0.31929211 | AK16: =AK8/AK$9 -> 0.62826386 | AL16: =AL8/AL$9 -> 1 | AM16: =AM8/AM$9 -> 0.31405619 | AN16: =AN8/AN$9 -> 0.31918637
